Workbook

Sheet Cover Page
B3: Company: | C3: Tryonic AI Platform
B4: Project: | C4: POD T-Shirt Platform
B5: Document: | C5: Test Case Execution Summary v30
B6: Version: | C6: v30 — Source Code Sync 2026-03-26
B7: Date: | C7: 2026-03-26
B8: Structure: | C8: 9 Feature Sheets (Merged)
B9: Changes: | C9: v30: NEW: Profile Page (avatar, contact, stats, address mgmt), AddressPicker (multi-address CRUD max 5), CheckoutModal (3-step drawer). UPD: Checkout Page (AddressPicker integration, flash discount, promo codes), TopBar (/profile link), OrderModal (selectedSize)

Sheet Execution Summary
A1: Execution Summary — Test Progress Dashboard v30
A3: Feature | B3: Total TCs | C3: Pass | D3: Fail | E3: Untested | F3: N/A | G3: % Progress | H3: % Pass Rate
A4: HOME | B4: 53 | C4: =COUNTIF(HOME!O3:O59,"Pass") -> 0 | D4: =COUNTIF(HOME!O3:O59,"Fail") -> 0 | E4: =COUNTIF(HOME!O3:O59,"Untested") -> 53 | F4: =COUNTIF(HOME!O3:O59,"N/A") -> 0 | G4: =IF(B4=0,0,(B4-E4-F4)/B4) -> 0 | H4: =IF((B4-E4-F4)=0,0,C4/(B4-E4-F4)) -> 0
A5: DESIGN STUDIO | B5: 204 | C5: =COUNTIF('DESIGN STUDIO'!O3:O209,"Pass") -> 0 | D5: =COUNTIF('DESIGN STUDIO'!O3:O209,"Fail") -> 0 | E5: =COUNTIF('DESIGN STUDIO'!O3:O209,"Untested") -> 204 | F5: =COUNTIF('DESIGN STUDIO'!O3:O209,"N/A") -> 0 | G5: =IF(B5=0,0,(B5-E5-F5)/B5) -> 0 | H5: =IF((B5-E5-F5)=0,0,C5/(B5-E5-F5)) -> 0
A6: AI GENERATE | B6: 38 | C6: =COUNTIF('AI GENERATE'!O3:O44,"Pass") -> 0 | D6: =COUNTIF('AI GENERATE'!O3:O44,"Fail") -> 0 | E6: =COUNTIF('AI GENERATE'!O3:O44,"Untested") -> 38 | F6: =COUNTIF('AI GENERATE'!O3:O44,"N/A") -> 0 | G6: =IF(B6=0,0,(B6-E6-F6)/B6) -> 0 | H6: =IF((B6-E6-F6)=0,0,C6/(B6-E6-F6)) -> 0
A7: ĐẶT HÀNG | B7: 77 | C7: =COUNTIF('ĐẶT HÀNG'!O3:O81,"Pass") -> 0 | D7: =COUNTIF('ĐẶT HÀNG'!O3:O81,"Fail") -> 0 | E7: =COUNTIF('ĐẶT HÀNG'!O3:O81,"Untested") -> 77 | F7: =COUNTIF('ĐẶT HÀNG'!O3:O81,"N/A") -> 0 | G7: =IF(B7=0,0,(B7-E7-F7)/B7) -> 0 | H7: =IF((B7-E7-F7)=0,0,C7/(B7-E7-F7)) -> 0
A8: THANH TOÁN | B8: 65 | C8: =COUNTIF('THANH TOÁN'!O3:O69,"Pass") -> 0 | D8: =COUNTIF('THANH TOÁN'!O3:O69,"Fail") -> 0 | E8: =COUNTIF('THANH TOÁN'!O3:O69,"Untested") -> 65 | F8: =COUNTIF('THANH TOÁN'!O3:O69,"N/A") -> 0 | G8: =IF(B8=0,0,(B8-E8-F8)/B8) -> 0 | H8: =IF((B8-E8-F8)=0,0,C8/(B8-E8-F8)) -> 0
A9: LOGIN | B9: 120 | C9: =COUNTIF(LOGIN!O3:O125,"Pass") -> 0 | D9: =COUNTIF(LOGIN!O3:O125,"Fail") -> 0 | E9: =COUNTIF(LOGIN!O3:O125,"Untested") -> 120 | F9: =COUNTIF(LOGIN!O3:O125,"N/A") -> 0 | G9: =IF(B9=0,0,(B9-E9-F9)/B9) -> 0 | H9: =IF((B9-E9-F9)=0,0,C9/(B9-E9-F9)) -> 0
A10: E2E FLOW | B10: 6 | C10: =COUNTIF('[1]E2E FLOW'!O3:O8,"Pass") -> #VALUE! | D10: =COUNTIF('[1]E2E FLOW'!O3:O8,"Fail") -> #VALUE! | E10: =COUNTIF('[1]E2E FLOW'!O3:O8,"Untested") -> #VALUE! | F10: =COUNTIF('[1]E2E FLOW'!O3:O8,"N/A") -> #VALUE! | G10: =IF(B10=0,0,(B10-E10-F10)/B10) -> #VALUE! | H10: =IF((B10-E10-F10)=0,0,C10/(B10-E10-F10)) -> #VALUE!
A11: MY ORDERS | B11: 25 | C11: =COUNTIF('MY ORDERS'!O3:O29,"Pass") -> 0 | D11: =COUNTIF('MY ORDERS'!O3:O29,"Fail") -> 0 | E11: =COUNTIF('MY ORDERS'!O3:O29,"Untested") -> 25 | F11: =COUNTIF('MY ORDERS'!O3:O29,"N/A") -> 0 | G11: =IF(B11=0,0,(B11-E11-F11)/B11) -> 0 | H11: =IF((B11-E11-F11)=0,0,C11/(B11-E11-F11)) -> 0
A12: POLICY PAGES | B12: 10 | C12: =COUNTIF('POLICY PAGES'!O3:O14,"Pass") -> 0 | D12: =COUNTIF('POLICY PAGES'!O3:O14,"Fail") -> 0 | E12: =COUNTIF('POLICY PAGES'!O3:O14,"Untested") -> 10 | F12: =COUNTIF('POLICY PAGES'!O3:O14,"N/A") -> 0 | G12: =IF(B12=0,0,(B12-E12-F12)/B12) -> 0 | H12: =IF((B12-E12-F12)=0,0,C12/(B12-E12-F12)) -> 0
A13: TOTAL | B13: =SUM(B4:B12) -> 598 | C13: =SUM(C4:C12) -> #VALUE! | D13: =SUM(D4:D12) -> #VALUE! | E13: =SUM(E4:E12) -> #VALUE! | F13: =SUM(F4:F12) -> #VALUE!

Sheet HOME
A1: TC_ID | B1: Screen | C1: US_Mapping | D1: Module | E1: Title | F1: Type | G1: Priority | H1: Pre-condition | I1: Steps | J1: Expected Result | K1: Actual Result | L1: Action Type | M1: Create TCs Type | N1: Execution Type | O1: Result_R1 | P1: Test Date_R1 | Q1: Tester_R1 | R1: Bug ID_R1 | S1: Bug Desc_R1 | T1: Result_R2 | U1: Test Date_R2 | V1: Tester_R2 | W1: Bug ID_R2 | X1: Bug Desc_R2 | Y1: Evidence | Z1: Notes | AA1: Review_Manual (Feedback)
A2: 📌 UI/UX
A3: TC_HOME_UI_009 | B3: MH Trang chủ | C3: US-HP-03 | D3: AI Input | E3: Home page: Nút Generate style đúng | F3: 🎨 UI/UX | G3: **🔴 P0** | I3: 1. Truy cập vào trang 2. Quan sát nút Generate bên phải input box | J3: Nút hiển thị: text 'Tạo ngay' + icon Wand2 ✨. Background teal gradient (#0D9488), text trắng, bo tròn. Nút nằm bên phải input | L3: Add new | M3: By AI | N3: Manual | O3: Untested | T3: Untested
A4: TC_HOME_UI_008 | B4: MH Trang chủ | C4: US-HP-03 | D4: AI Input | E4: Home page: AI Input Box placeholder đúng | F4: 🎨 UI/UX | G4: **🟠 P1** | I4: 1. Truy cập vào trang 2. Quan sát ô nhập liệu AI ở giữa trang | J4: Placeholder hiển thị: 'Bạn muốn kể gì trên áo?'. Input dạng chat conversational, bo tròn. Animated gradient border (teal-cyan). Có nút đính kèm ảnh tham khảo bên trái, nút 'Tạo ngay' bên phải | L4: Add new | M4: By AI | N4: Manual | O4: Untested | T4: Untested
A5: TC_HOME_UI_010 | B5: MH Trang chủ | C5: US-HP-03 | D5: AI Input | E5: Home page: 6 Style Tags hiển thị đầy đủ | F5: 🎨 UI/UX | G5: **🟠 P1** | I5: 1. Truy cập vào trang 2. Quan sát các tag phía dưới AI Input Box | J5: Hiển thị đầy đủ 6 tags: 'Tối giản', 'Streetwear', 'Anime', 'Retro', 'Y2K vibes', 'Nghệ thuật'. Mỗi tag có emoji riêng (🎯🔥🌸🎸✨🎨), bo tròn full, gradient border khi selected. Font size ~14px | L5: Add new | M5: By AI | N5: Manual | O5: Untested | T5: Untested
A6: TC_HOME_UI_011 | B6: MH Trang chủ | C6: US-HP-03 | D6: AI Input | E6: Home page: Nút 'Chọn từ mẫu có sẵn' hiển thị | F6: 🎨 UI/UX | G6: **🟠 P1** | I6: 1. Truy cập vào trang 2. Quan sát 2 nút phía dưới Style Tags | J6: Nút 'Chọn từ mẫu có sẵn' hiển thị: Grid icon tím, subtitle 'Khám phá thư viện mẫu', background trắng, border tím. Font size title ~16px, subtitle ~13px | L6: Add new | M6: By AI | N6: Manual | O6: Untested | T6: Untested
A7: TC_HOME_UI_012 | B7: MH Trang chủ | C7: US-HP-03 | D7: AI Input | E7: Home page: Nút 'Tải lên ảnh của bạn' hiển thị | F7: 🎨 UI/UX | G7: **🟠 P1** | I7: 1. Truy cập vào trang 2. Quan sát nút thứ hai phía dưới Style Tags | J7: Nút 'Tải lên ảnh của bạn' hiển thị: Upload icon tím, subtitle 'Sử dụng file thiết kế riêng', background trắng, border tím. Font size title ~16px, subtitle ~13px | L7: Add new | M7: By AI | N7: Manual | O7: Untested | T7: Untested
A8: TC_HOME_016 | B8: MH Trang chủ | C8: US-HP-05 | D8: Accessibility | E8: Home page: Heading hierarchy đúng chuẩn | F8: 🎨 UI/UX | G8: **🟢 P2** | I8: 1. Truy cập vào trang 2. Kiểm tra source code: kiểm tra thứ tự h1, h2, h3 | J8: Trang chỉ có 1 thẻ h1 (Headline chính). Các heading phụ sử dụng h2, h3 đúng thứ tự. Không skip level (h1 → h3) | L8: Add new | M8: By AI | N8: Manual | O8: Untested | T8: Untested
A9: TC_HOME_017 | B9: MH Trang chủ | C9: US-HP-05 | D9: Accessibility | E9: Home page: Keyboard navigation (Tab order) | F9: 🎨 UI/UX | G9: **🟢 P2** | I9: 1. Truy cập vào trang 2. Nhấn Tab liên tục từ đầu trang | J9: Tab order hợp lý: Logo → Menu items → 'Thiết kế ngay' → AI Input → Generate → Style Tags → Action Buttons. Focus ring hiển thị rõ ràng | L9: Add new | M9: By AI | N9: Manual | O9: Untested | T9: Untested
A10: TC_HOME_UI_006 | B10: MH Trang chủ | C10: US-HP-02 | D10: Hero | E10: Home page: Headline text đúng nội dung (Updated v28) | F10: 🎨 UI/UX | G10: **🔴 P0** | I10: 1. Truy cập vào trang 2. Quan sát tiêu đề chính Hero section | J10: Headline hiển thị: 'Mỗi chiếc áo, một câu chuyện'. Phần highlight có màu tím gradient. Font size lớn (~48-56px), bold | L10: Add new | M10: By AI | N10: Manual | O10: Untested | T10: Untested
A11: TC_HOME_UI_005 | B11: MH Trang chủ | C11: US-HP-02 | D11: Hero | E11: Home page: Badge 'AI-Powered Design' hiển thị | F11: 🎨 UI/UX | G11: **🟢 P2** | I11: 1. Truy cập vào trang 2. Quan sát phần trên cùng Hero section | J11: Badge/chip hiển thị: '✨ AI-Powered Design' với background tím nhạt, icon sparkle, text tím đậm | L11: Add new | M11: By AI | N11: Manual | O11: Untested | T11: Untested
A12: TC_HOME_UI_007 | B12: MH Trang chủ | C12: US-HP-02 | D12: Hero | E12: Home page: Subtitle text đúng nội dung | F12: 🎨 UI/UX | G12: **🟢 P2** | I12: 1. Truy cập vào trang 2. Quan sát dòng mô tả bên dưới Headline | J12: Subtitle hiển thị: 'Kể mình nghe ý tưởng của bạn — mình biến nó thành artwork trên áo trong vài giây!'. Text xám, centered. Font size ~16-18px | L12: Add new | M12: By AI | N12: Manual | O12: Untested | T12: Untested
A13: TC_HOME_UI_016 | B13: MH Trang chủ | C13: US-HP-02 | D13: Hero | E13: Home page: Background gradient Hero section | F13: 🎨 UI/UX | G13: **🟢 P2** | I13: 1. Truy cập vào trang 2. Quan sát nền trang Hero section | J13: Nền hiển thị gradient nhẹ: trắng lavender (#F8F7FF) với các hiệu ứng trang trí 2 bên (hình trang trí mờ/blur) | L13: Add new | M13: By AI | N13: Manual | O13: Untested | T13: Untested
A14: TC_HOME_UI_003 | B14: MH Trang chủ | C14: US-HP-01 | D14: Home - Header | E14: Home page: Nút 'Thiết kế ngay' style đúng | F14: 🎨 UI/UX | G14: **🔴 P0** | I14: 1. Truy cập vào trang 2. Quan sát nút CTA góc phải header | J14: Nút 'Thiết kế ngay' hiển thị: background gradient tím→đỏ (#7C3AED→#E11D48), text trắng, bo tròn (rounded-full), font semi-bold | L14: Add new | M14: By AI | N14: Manual | O14: Untested | T14: Untested
... A30: TC_ERR_UI_001 | B30: Error Page | C30: Global | D30: Error - 404 | E30: Trang 404: URL không tồn tại | F30: 🎨 UI/UX | G30: **🟠 P1** | I30: 1. Truy cập URL không tồn tại (VD: /abc123) 2. Quan sát trang | J30: Hiển thị trang 404 thân thiện: illustration, text 'Trang không tồn tại', nút 'Về trang chủ'. KHÔNG hiển thị lỗi kỹ thuật | L30: Add new | M30: By AI | N30: Manual | O30: Untested | T30: Untested
A31: 📌 Validation
A32: TC_HOME_009 | B32: MH Trang chủ | C32: US-HP-03 | D32: AI Input | E32: Click Generate khi input rỗng | F32: ⚠️ Negative | G32: **🔴 P0** | I32: 1. Truy cập vào trang 2. Không nhập gì vào AI Input Box 3. Click nút 'Generate' | J32: Không validate. Chuyển sang Design Studio với thiết kế mặc định | L32: Add new | M32: By AI | N32: Manual | O32: Untested | T32: Untested
A33: TC_HOME_019 | B33: MH Trang chủ | C33: US-HP-03 | D33: AI Input | E33: AI prompt cực dài 5000+ ký tự (BVA max) | F33: ⚠️ Negative | G33: **🟠 P1** | I33: 1. Truy cập vào trang 2. Nhập text 5000+ ký tự vào AI Input Box 3. Click 'Generate' | J33: Input truncate hoặc hiển thị validation: 'Mô tả quá dài (tối đa X ký tự)'. Không gửi payload quá lớn | L33: Add new | M33: By AI | N33: Manual | O33: Untested | T33: Untested
A34: TC_HOME_020 | B34: MH Trang chủ | C34: US-HP-03 | D34: AI Input | E34: AI prompt chỉ có whitespace/spaces | F34: ⚠️ Negative | G34: **🟠 P1** | I34: 1. Truy cập vào trang 2. Nhập text: ' ' (chỉ spaces) vào AI Input Box 3. Click 'Generate' | J34: Hiển thị validation tương tự input rỗng: 'Vui lòng nhập mô tả'. Trim whitespace trước khi validate | L34: Add new | M34: By AI | N34: Manual | O34: Untested | T34: Untested
A35: TC_HOME_018 | B35: MH Trang chủ | C35: US-HP-03 | D35: AI Input | E35: AI prompt chỉ có 1 ký tự (BVA min) | F35: ⚠️ Negative | G35: **🟢 P2** | I35: 1. Truy cập vào trang 2. Nhập text: 'A' (1 ký tự) vào AI Input Box 3. Click 'Generate' | J35: Hiển thị validation: 'Mô tả quá ngắn' hoặc chấp nhận và xử lý. Behavior rõ ràng, không crash | L35: Add new | M35: By AI | N35: Manual | O35: Untested | T35: Untested
A36: TC_HOME_010 | B36: MH Trang chủ | C36: US-HP-01 | D36: Navigation | E36: Menu 'Sản phẩm' trỏ đúng route | F36: ⚠️ Negative | G36: **🟠 P1** | I36: 1. Truy cập vào trang 2. Click menu 'Sản phẩm' trên navigation 3. Quan sát URL | J36: URL chuyển sang /products hoặc trang sản phẩm tương ứng. Không trỏ ngược về /home/ (BUG hiện tại: trỏ sai) | L36: Add new | M36: By AI | N36: Manual | O36: Untested | T36: Untested
A37: TC_HOME_011 | B37: MH Trang chủ | C37: US-HP-01 | D37: Navigation | E37: Menu 'Dịch vụ' trỏ đúng route | F37: ⚠️ Negative | G37: **🟠 P1** | I37: 1. Truy cập vào trang 2. Click menu 'Dịch vụ' trên navigation 3. Quan sát URL | J37: URL chuyển sang /services hoặc trang dịch vụ tương ứng. Không trỏ ngược về /home/ (BUG hiện tại: trỏ sai) | L37: Add new | M37: By AI | N37: Manual | O37: Untested | T37: Untested
A38: TC_HOME_012 | B38: MH Trang chủ | C38: US-HP-01 | D38: Navigation | E38: Menu 'Liên hệ' trỏ đúng route | F38: ⚠️ Negative | G38: **🟠 P1** | I38: 1. Truy cập vào trang 2. Click menu 'Liên hệ' trên navigation 3. Quan sát URL | J38: URL chuyển sang /contact hoặc trang liên hệ tương ứng. Không trỏ ngược về /home/ (BUG hiện tại: trỏ sai) | L38: Add new | M38: By AI | N38: Manual | O38: Untested | T38: Untested
A39: 📌 Functional
A40: TC_HOME_004 | B40: MH Trang chủ | C40: US-HP-03 | D40: AI Input | E40: Nhập prompt vào AI Input Box và click Generate | F40: ✅ Positive | G40: **🔴 P0** | I40: 1. Truy cập vào trang 2. Nhập text: 'Áo minimalist hoa sakura' vào AI Input Box 3. Click nút 'Generate' | J40: Chuyển sang Design Studio và hiển thị kết quả AI. Prompt được xử lý. Loading state hiển thị | L40: Add new | M40: By AI | N40: Manual | O40: Untested | T40: Untested
A41: TC_HOME_025 | B41: MH Trang chủ | C41: US-HP-03 | D41: AI Input | E41: Click Generate sau khi chọn Style Tag | F41: ✅ Positive | G41: **🔴 P0** | I41: 1. Truy cập vào trang 2. Click tag 'Streetwear' 3. Nhập text: 'Áo phong cách đường phố' 4. Click nút 'Generate' | J41: Prompt được gửi kèm style tag đã chọn. Loading state hiển thị. Chuyển sang Design Studio với style 'Streetwear' | L41: Add new | M41: By AI | N41: Manual | O41: Untested | T41: Untested
A42: TC_HOME_005 | B42: MH Trang chủ | C42: US-HP-03 | D42: AI Input | E42: Click Style Tag thay đổi trạng thái | F42: ✅ Positive | G42: **🟠 P1** | I42: 1. Truy cập vào trang 2. Click tag 'Tối giản' 3. Click tag 'Anime' | J42: Tag được chọn có highlight (background đổi màu hoặc border đậm). Chỉ 1 tag active cùng lúc — tag trước đó tự động bỏ highlight khi chọn tag mới | L42: Add new | M42: By AI | N42: Manual | O42: Untested | T42: Untested
A43: TC_HOME_006 | B43: MH Trang chủ | C43: US-HP-03 | D43: AI Input | E43: Click nút 'Chọn từ mẫu có sẵn' | F43: ✅ Positive | G43: **🟠 P1** | I43: 1. Truy cập vào trang 2. Click nút 'Chọn từ mẫu có sẵn' | J43: Chuyển sang Design Studio và mở tab thư viện mẫu hiển thị danh sách templates có sẵn | L43: Add new | M43: By AI | N43: Manual | O43: Untested | T43: Untested
A44: TC_HOME_007 | B44: MH Trang chủ | C44: US-HP-03 | D44: AI Input | E44: Click nút 'Tải lên ảnh của bạn' | F44: ✅ Positive | G44: **🟠 P1** | I44: 1. Truy cập vào trang 2. Click nút 'Tải lên ảnh của bạn' | J44: Chuyển sang Design Studio và mở thư viện ảnh cho phép chọn file ảnh để tải lên. Chấp nhận formats: PNG, JPG, SVG | L44: Add new | M44: By AI | N44: Manual | O44: Untested | T44: Untested
A45: TC_HOME_021 | B45: MH Trang chủ | C45: US-HP-03 | D45: AI Input | E45: Click tag 'Streetwear' và verify style được áp dụng | F45: ✅ Positive | G45: **🟠 P1** | I45: 1. Truy cập vào trang 2. Click tag 'Streetwear' (🔥 icon) | J45: Tag 'Streetwear' highlight (border đậm hoặc background đổi). Các tag khác bỏ highlight. Prompt box cập nhật style tương ứng | L45: Add new | M45: By AI | N45: Manual | O45: Untested | T45: Untested
A46: TC_HOME_022 | B46: MH Trang chủ | C46: US-HP-03 | D46: AI Input | E46: Click tag 'Retro' và verify style được áp dụng | F46: ✅ Positive | G46: **🟠 P1** | I46: 1. Truy cập vào trang 2. Click tag 'Retro' (🎸 icon) | J46: Tag 'Retro' highlight. Các tag khác bỏ highlight | L46: Add new | M46: By AI | N46: Manual | O46: Untested | T46: Untested
A47: TC_HOME_023 | B47: MH Trang chủ | C47: US-HP-03 | D47: AI Input | E47: Click tag 'Y2K vibes' và verify style được áp dụng | F47: ✅ Positive | G47: **🟠 P1** | I47: 1. Truy cập vào trang 2. Click tag 'Y2K vibes' (✨ icon) | J47: Tag 'Y2K vibes' highlight. Các tag khác bỏ highlight | L47: Add new | M47: By AI | N47: Manual | O47: Untested | T47: Untested
A48: TC_HOME_024 | B48: MH Trang chủ | C48: US-HP-03 | D48: AI Input | E48: Click tag 'Nghệ thuật' và verify style được áp dụng | F48: ✅ Positive | G48: **🟠 P1** | I48: 1. Truy cập vào trang 2. Click tag 'Nghệ thuật' (🎨 icon) | J48: Tag 'Nghệ thuật' highlight. Các tag khác bỏ highlight | L48: Add new | M48: By AI | N48: Manual | O48: Untested | T48: Untested
A49: TC_HOME_008 | B49: MH Trang chủ | C49: US-HP-03 | D49: AI Input | E49: Submit AI Input bằng phím Enter | F49: ✅ Positive | G49: **🟢 P2** | I49: 1. Truy cập vào trang 2. Nhập text: 'Áo vintage rock band' 3. Nhấn phím Enter | J49: Form submit thành công — chuyển sang Design Studio hoặc hiển thị loading state. Behavior tương đương click nút Generate | L49: Add new | M49: By AI | N49: Manual | O49: Untested | T49: Untested
A50: TC_HOME_026 | B50: MH Trang chủ | C50: US-HP-02 | D50: Hero | E50: Click badge '✨ AI-Powered Design' | F50: ✅ Positive | G50: **🟢 P2** | I50: 1. Truy cập vào trang 2. Click badge '✨ AI-Powered Design' ở Hero section | J50: Badge không phải link → không redirect | L50: Add new | M50: By AI | N50: Manual | O50: Untested | T50: Untested
A51: TC_HOME_001 | B51: MH Trang chủ | C51: US-HP-01 | D51: Navigation | E51: Click nút 'Thiết kế ngay' mở Design Studio | F51: ✅ Positive | G51: **🔴 P0** | I51: 1. Truy cập vào trang 2. Mở /home/ 3. Click nút 'Thiết kế ngay' trên header | J51: Chuyển sang trang Design Studio. Canvas mockup áo thun hiển thị. Header đổi thành header Design Studio | L51: Add new | M51: By AI | N51: Manual | O51: Untested | T51: Untested
... A55: TC_ERR_F_001 | B55: SPA Routing | C55: Global | D55: Error - Navigation | E55: 404 → Click 'Về trang chủ' | F55: ✅ Positive | G55: **🟢 P2** | I55: 1. Truy cập URL không tồn tại 2. Click nút 'Về trang chủ' | J55: Redirect về /home/ thành công | L55: Add new | M55: By AI | N55: Manual | O55: Untested | T55: Untested
A56: 📌 Security
A57: TC_HOME_013 | B57: MH Trang chủ | C57: US-HP-03 | D57: AI Input | E57: Nhập prompt chứa ký tự đặc biệt và XSS | F57: ⚠️ Negative | G57: **🟠 P1** | I57: 1. Truy cập vào trang 2. Nhập text: '<script>alert(1)</script>' vào AI Input Box 3. Click Generate | J57: Hệ thống sanitize input. Không execute script. Prompt được escape đúng | L57: Add new | M57: By AI | N57: Manual | O57: Untested | T57: Untested
A58: 📌 Performance
A59: TC_ERR_UI_002 | B59: Error Page | C59: Global | D59: Error - Network | E59: Mất kết nối mạng → thông báo | F59: 🎨 UI/UX | G59: **🟢 P2** | I59: 1. Đang duyệt web 2. Ngắt kết nối mạng 3. Thực hiện thao tác | J59: Hiển thị toast/banner: 'Mất kết nối mạng' hoặc xử lý gracefully. Không blank screen | L59: Add new | M59: By AI | N59: Manual | O59: Untested | T59: Untested

Sheet DESIGN STUDIO
A1: TC_ID | B1: Screen | C1: US_Mapping | D1: Module | E1: Title | F1: Type | G1: Priority | H1: Pre-condition | I1: Steps | J1: Expected Result | K1: Actual Result | L1: Action Type | M1: Create TCs Type | N1: Execution Type | O1: Result_R1 | P1: Test Date_R1 | Q1: Tester_R1 | R1: Bug ID_R1 | S1: Bug Desc_R1 | T1: Result_R2 | U1: Test Date_R2 | V1: Tester_R2 | W1: Bug ID_R2 | X1: Bug Desc_R2 | Y1: Evidence | Z1: Notes | AA1: Review_Manual (Feedback)
A2: 📌 UI/UX
A3: TC_DS_UI_001 | B3: DS - Chung | C3: US-DS-01 | D3: DS Chung - Header | E3: Design Studio: Header hiển thị đầy đủ | F3: 🎨 UI/UX | G3: **🟠 P1** | I3: 1. Mở Design Studio (click 'Thiết kế ngay') 2. Quan sát header | J3: Header hiển thị: ← 'Quay lại' (trái), Logo 'Tryonic' icon (trái), text 'Design Studio' (giữa), Credits badge + nút 'Chia sẻ' + icon User + icon Giỏ hàng (phải) | L3: Add new | M3: By AI | N3: Manual | O3: Untested | T3: Untested
A4: TC_DS_UI_002 | B4: DS - Chung | C4: US-DS-01 | D4: DS Chung - Header | E4: Design Studio: Credits badge hiển thị số dư | F4: 🎨 UI/UX | G4: **🟠 P1** | I4: 1. Mở Design Studio 2. Quan sát góc phải header | J4: Hiển thị: '12 Credits' + nút 'Chia sẻ' (thay vì Nạp). Credits badge có icon coin/circle | L4: Add new | M4: By AI | N4: Manual | O4: Untested | T4: Untested
A5: TC_DS_UI_003 | B5: DS - Sidebar | C5: US-DS-02 | D5: Sidebar | E5: Design Studio: Sidebar trái hiển thị đầy đủ công cụ | F5: 🎨 UI/UX | G5: **🟠 P1** | I5: 1. Mở Design Studio 2. Quan sát sidebar trái | J5: Hiển thị 7 công cụ theo thứ tự: Hoàn Tác, Làm Lại, Mặt Sau, Thu Phóng, Thư Viện, Thử Đồ với AI, Chia Sẻ. Mỗi công cụ có icon + text label. 'Thử Đồ với AI' disabled khi chưa có artwork | L5: Add new | M5: By AI | N5: Manual | O5: Untested | T5: Untested
A6: TC_DS_UI_004 | B6: DS - Canvas | C6: US-DS-03 | D6: DS Chung - Canvas | E6: Design Studio: Canvas mockup áo mặc định | F6: 🎨 UI/UX | G6: **🔴 P0** | I6: 1. Mở Design Studio 2. Quan sát canvas trung tâm | J6: Hiển thị mockup áo thun trắng trên nền xám. Vùng thiết kế được đánh dấu bằng đường nét đứt xanh cyan. Text hướng dẫn: 'Nhấn "Thêm Hình", "Thư Viện" hoặc "AI Artwork" để bắt đầu thiết kế' | L6: Add new | M6: By AI | N6: Manual | O6: Untested | T6: Untested
A7: TC_DES_UI_031 | B7: DS - Editor/Canvas | C7: US-15 | D7: Editor - Canvas | E7: Canvas: Smart Guides (Bắt dính thông minh) | F7: 🎨 UI/UX | G7: **🟠 P1** | I7: 1. Truy cập vào trang 2. Kéo layer vào chính giữa Canvas (Vertical/Horizontal)\n2. Kéo ngang hàng với một layer khác | J7: Hiển thị các đường viền đỏ/xanh (Guides) tự động bắt dính báo hiệu layer đã vô giữa hoặc ngay ngắn | L7: Add new | M7: By AI | N7: Manual | O7: Untested | T7: Untested
A8: TC_DES_UI_032 | B8: DS - Editor/Canvas | C8: US-15 | D8: Editor - Canvas | E8: Canvas: Keyboard Shortcuts cơ bản | F8: 🎨 UI/UX | G8: **🟠 P1** | I8: 1. Truy cập vào trang 2. Nhấn Delete/Backspace\n2. Nhấn Ctrl+Z / Ctrl+Y\n3. Nhấn Ctrl+C rồi Ctrl+V | J8: 1. Layer bị xóa\n2. Undo/Redo chính xác\n3. Layer được copy/paste ngay cạnh layer gốc | L8: Add new | M8: By AI | N8: Manual | O8: Untested | T8: Untested
A9: TC_DES_UI_029a | B9: DS - Editor/Canvas | C9: US-15 | D9: Editor - Canvas Viewpoint | E9: Canvas: Zoom In / Zoom Out (bằng UI Buttons) | F9: 🎨 UI/UX | G9: **🟠 P1** | I9: 1. Truy cập vào trang Editor 2. Click nút + (Zoom In) và nút - (Zoom Out) trên UI | J9: Canvas và các layer phóng to/thu nhỏ mượt mà. Tâm zoom focus vào giữa màn hình. | L9: Add new | M9: By AI | N9: Manual | O9: Untested | T9: Untested
A10: TC_DES_UI_029b | B10: DS - Editor/Canvas | C10: US-15 | D10: Editor - Canvas Viewpoint | E10: Canvas: Zoom In / Zoom Out (bằng Ctrl + Scroll) | F10: 🎨 UI/UX | G10: **🟠 P1** | I10: 1. Truy cập vào trang Editor 2. Nhấn giữ phím Ctrl và lăn chuột lên (Zoom In) / xuống (Zoom Out) | J10: Canvas và các layer phóng to/thu nhỏ mức zoom tương ứng mượt mà. Tâm zoom focus vào vị trí con trỏ chuột. | L10: Add new | M10: By AI | N10: Manual | O10: Untested | T10: Untested
A11: TC_DES_UI_030a | B11: DS - Editor/Canvas | C11: US-15 | D11: Editor - Canvas Viewpoint | E11: Canvas: Pan (Di chuyển vùng nhìn bằng Space + Drag) | F11: 🎨 UI/UX | G11: **🟠 P1** | I11: 1. Truy cập vào trang Editor và zoom canvas lớn hơn màn hình 2. Nhấn giữ phím Space và click kéo thả chuột (Drag) | J11: Con trỏ đổi thành hình bàn tay (hand tool). Vùng nhìn di chuyển mượt mà lên/xuống/trái/phải để xem các góc khác của thiết kế. | L11: Add new | M11: By AI | N11: Manual | O11: Untested | T11: Untested
A12: TC_UIUX_003 | B12: DS - Editor/Canvas | C12: US-15 | D12: Editor - Canvas Viewpoint | E12: Verify Smart Guides magnetic alignment | F12: 🎨 UI/UX | G12: **🟠 P1** | I12: 1. Truy cập vào trang 2. Mở Editor 3. Kéo layer A di chuyển lại gần layer B / tâm canvas | J12: Chớp xuất hiện đường viền (guide) đỏ/xanh báo đã căn giữa/trái/phải | L12: Add new | M12: By AI | N12: Manual | O12: Untested | T12: Untested
A13: TC_UIUX_004 | B13: DS - Editor/Canvas | C13: US-15 | D13: Editor - Canvas Viewpoint | E13: Verify Keyboard Shortcuts mapping | F13: 🎨 UI/UX | G13: **🟠 P1** | I13: 1. Truy cập vào trang 2. Mở Editor 3. Chọn layer Text 4. Nhấn Ctrl+C rồi Ctrl+V rồi Delete | J13: Copy ra layer mới và sau đó xóa layer thành công | L13: Add new | M13: By AI | N13: Manual | O13: Untested | T13: Untested
A14: TC_UIUX_005 | B14: DS - Editor/Canvas | C14: US-16 | D14: Editor - Canvas Viewpoint | E14: Verify Layer Opacity slider | F14: 🎨 UI/UX | G14: **🟠 P1** | I14: 1. Truy cập vào trang 2. Mở Editor 3. Chọn layer 4. Kéo thanh trượt thay đổi Opacity xuống 50% | J14: Layer trở nên trong suốt 50%, nhìn xuyên thấu xuống background | L14: Add new | M14: By AI | N14: Manual | O14: Untested | T14: Untested
... A59: TC_GAL_UI_820 | B59: DS - Responsive | C59: Global | D59: Responsive (iPhone) | E59: Màn hình Gallery: Responsive trên iPhone (Safari/Chrome, Dọc - Portrait) | F59: 🎨 UI/UX | G59: **🔴 P0** | I59: 1. Truy cập trang Gallery trên iPhone ở chế độ cầm dọc (Portrait). 2. Cuộn lên/xuống toàn trang. 3. Tap thử các nút bấm, input field. | J59: Không xuất hiện thanh cuộn ngang thừa. Các khối nội dung hiển thị cột đơn (stacking). Các nút bấm (Touch Targets) không quá nhỏ, không nằm sát mép màn hình (có padding viền an toàn hợp lý). | L59: Add new | M59: By AI | N59: Manual | O59: Untested | T59: Untested
A60: 📌 Validation
A61: TC_DS_016 | B61: DS - Sidebar | C61: US-DS-02 | D61: Sidebar | E61: Click 'Hoàn Tác' khi không có action nào | F61: ⚠️ Negative | G61: **🟢 P2** | I61: 1. Mở Design Studio (canvas trống, chưa thao tác) 2. Click icon 'Hoàn Tác' | J61: Nút Undo disabled hoặc không có phản hồi. Không crash. Không thay đổi canvas | L61: Add new | M61: By AI | N61: Manual | O61: Untested | T61: Untested
A62: TC_DS_SC_038 | B62: DS - Canvas | C62: US-DS-03 | D62: Canvas - Undo | E62: Nút Undo disabled khi history rỗng | F62: ⚠️ Negative | G62: **🟢 P2** | I62: 1. Mở DS mới (chưa thao tác) 2. Quan sát nút Undo trên sidebar | J62: Nút Undo có opacity-40 (mờ). Click không có hiệu ứng. canUndo = false | L62: Add new | M62: By AI | N62: Manual | O62: Untested | T62: Untested
A63: TC_DS_SC_039 | B63: DS - Canvas | C63: US-DS-03 | D63: Canvas - Undo | E63: Nút Redo disabled khi không có undo | F63: ⚠️ Negative | G63: **🟢 P2** | I63: 1. Mở DS mới hoặc sau khi thêm element (chưa undo) 2. Quan sát nút Redo | J63: Nút Redo có opacity-40 (mờ). canRedo = false | L63: Add new | M63: By AI | N63: Manual | O63: Untested | T63: Untested
A64: TC_DES_020 | B64: DS - Editor/Canvas | C64: US-17 | D64: Editor - History | E64: Undo khi không có history | F64: ✅ Boundary | G64: **🟢 P2** | I64: 1. Truy cập vào trang 2. Click Undo | J64: Undo disabled hoặc không có hiệu ứng | L64: Add new | M64: By AI | N64: Manual | O64: Untested | T64: Untested
A65: TC_DES_022 | B65: DS - Editor/Canvas | C65: US-18 | D65: Editor - Save | E65: Save design khi Guest → yêu cầu login | F65: ⚠️ Negative | G65: **🔴 P0** | I65: 1. Truy cập vào trang 2. Click 'Save' | J65: Hiện popup login. Sau login → save + migrate | L65: Add new | M65: By AI | N65: Manual | O65: Untested | T65: Untested
A66: TC_DES_010 | B66: DS - Editor/Canvas | C66: US-14 | D66: Editor - Text | E66: Text rỗng | F66: ⚠️ Negative | G66: **🟠 P1** | I66: 1. Truy cập vào trang 2. Click 'Add Text' 3. Không nhập gì 4. Click ra ngoài | J66: Không tạo layer rỗng hoặc tự xóa layer trống | L66: Add new | M66: By AI | N66: Manual | O66: Untested | T66: Untested
A67: TC_DES_011 | B67: DS - Editor/Canvas | C67: US-14 | D67: Editor - Text | E67: Text rất dài (500+ ký tự) | F67: ✅ Boundary | G67: **🟠 P1** | I67: 1. Truy cập vào trang 2. Nhập text 500 ký tự | J67: Text wrap hoặc warning. Không vỡ canvas | L67: Add new | M67: By AI | N67: Manual | O67: Untested | T67: Untested
A68: TC_DSP_V_001 | B68: DS - Popup Sản phẩm | C68: US-DS-04 | D68: DS Sản phẩm - Modal | E68: Chọn size không có sẵn (nếu hết hàng) | F68: ⚠️ Negative | G68: **🟠 P1** | I68: 1. Mở Design Studio → Popup Sản phẩm (ProductSelectorModal) 2. Click size bị disabled/hết hàng | J68: Size không thể chọn. Hiển thị tooltip/thông báo 'Hết hàng' hoặc size bị gạch bỏ (strikethrough). Không crash | L68: Add new | M68: By AI | N68: Manual | O68: Untested | T68: Untested
A69: TC_DSP_V_002 | B69: DS - Popup Sản phẩm | C69: US-DS-04 | D69: DS Sản phẩm - Modal | E69: Chuyển tab khác rồi quay lại 'SẢN PHẨM' — trạng thái giữ nguyên | F69: ⚠️ Negative | G69: **🟢 P2** | I69: 1. Mở DS → Popup Sản phẩm (ProductSelectorModal) → Chọn màu Đen, size XL 2. Chuyển sang AI Panel 3. Quay lại popup sản phẩm | J69: Màu Đen và size XL vẫn được giữ nguyên. Không reset về mặc định | L69: Add new | M69: By AI | N69: Manual | O69: Untested | T69: Untested
A70: TC_DES_003 | B70: DS - Thư viện Ảnh | C70: US-13 | D70: Editor - Upload | E70: Upload file > 25MB | F70: ⚠️ Negative | G70: **🔴 P0** | I70: 1. Truy cập vào trang 2. Click Upload 3. Chọn file 30MB | J70: Hiển thị lỗi: 'File vượt quá 25MB' | L70: Add new | M70: By AI | N70: Manual | O70: Untested | T70: Untested
A71: TC_DES_004 | B71: DS - Thư viện Ảnh | C71: US-13 | D71: Editor - Upload | E71: Upload file format không hỗ trợ (PDF) | F71: ⚠️ Negative | G71: **🔴 P0** | I71: 1. Truy cập vào trang 2. Click Upload 3. Chọn file PDF | J71: Hiển thị lỗi: 'Chỉ hỗ trợ PNG/JPG' | L71: Add new | M71: By AI | N71: Manual | O71: Untested | T71: Untested
A72: TC_DES_006 | B72: DS - Thư viện Ảnh | C72: US-13 | D72: Editor - Upload | E72: Upload ảnh < 150 DPI - cảnh báo chất lượng | F72: ⚠️ Negative | G72: **🔴 P0** | I72: 1. Truy cập vào trang 2. Upload ảnh 72 DPI | J72: Hiển thị warning: 'Low Quality - May be blurry when printed' | L72: Add new | M72: By AI | N72: Manual | O72: Untested | T72: Untested
... A88: TC_DS_SC_018 | B88: DS - Chung | C88: US-DS-01 | D88: Auth Modal | E88: Submit form trống → validation error | F88: ⚠️ Negative | G88: **🟠 P1** | I88: 1. Mở InlineAuthModal 2. Không nhập gì → Click 'Đăng nhập' | J88: Hiển thị error: 'Vui lòng điền đầy đủ thông tin'. Error box bg-red-50, border-red-100, icon AlertCircle | L88: Add new | M88: By AI | N88: Manual | O88: Untested | T88: Untested
A89: 📌 Functional
A90: TC_DS_001 | B90: DS - Chung | C90: US-DS-01 | D90: DS Chung - Header | E90: Click 'Quay lại' từ Design Studio về trang chủ | F90: ✅ Positive | G90: **🟠 P1** | I90: 1. Mở Design Studio 2. Click '← Quay lại' | J90: Chuyển về trang /home/. Design Studio đóng lại | L90: Add new | M90: By AI | N90: Manual | O90: Untested | T90: Untested
A91: TC_DS_008a | B91: DS - Chung | C91: US-DS-01 | D91: DS Chung - Header | E91: Click icon User khi đã đăng nhập | F91: ✅ Positive | G91: **🟢 P2** | I91: 1. Đăng nhập → Mở Design Studio 2. Click icon User (góc phải header) | J91: Mở trang profile/account. Hiển thị thông tin tài khoản | L91: Add new | M91: By AI | N91: Manual | O91: Untested | T91: Untested
A92: TC_DS_008b | B92: DS - Chung | C92: US-DS-01 | D92: DS Chung - Header | E92: Click icon User khi chưa đăng nhập | F92: ✅ Positive | G92: **🟢 P2** | I92: 1. Truy cập Guest → Mở Design Studio 2. Click icon User (góc phải header) | J92: Hiển thị popup login. Cho phép đăng nhập hoặc đăng ký | L92: Add new | M92: By AI | N92: Manual | O92: Untested | T92: Untested
A93: TC_DS_009 | B93: DS - Chung | C93: US-DS-01 | D93: DS Chung - Header | E93: Click icon Giỏ hàng trên header | F93: ✅ Positive | G93: **🟢 P2** | I93: 1. Mở Design Studio 2. Click icon Giỏ hàng (góc phải header) | J93: Mở trang giỏ hàng hoặc sidebar cart. Hiển thị số lượng items (badge) | L93: Add new | M93: By AI | N93: Manual | O93: Untested | T93: Untested
A94: TC_DS_010 | B94: DS - Chung | C94: US-DS-01 | D94: DS Chung - Header | E94: Click nút 'Nạp' credits | F94: ✅ Positive | G94: **🟢 P2** | I94: 1. Mở Design Studio 2. Click nút 'Nạp' bên cạnh credits | J94: Hiển thị tooltip thông tin credits. Không mở trang nạp riêng | L94: Add new | M94: By AI | N94: Manual | O94: Untested | T94: Untested
A95: TC_DS_028 | B95: DS - Chung | C95: US-DS-01 | D95: DS Chung - Header | E95: Click logo 'Tryonic' trên header | F95: ✅ Positive | G95: **🟢 P2** | I95: 1. Mở Design Studio 2. Click logo 'Tryonic' (icon) trên header | J95: Redirect về trang chủ /home/ hoặc không phản hồi (nếu logo không phải link). Behavior nhất quán | L95: Add new | M95: By AI | N95: Manual | O95: Untested | T95: Untested
A96: TC_DS_SC_012 | B96: DS - Chung | C96: US-DS-01 | D96: DS Header - Cart | E96: Icon giỏ hàng hiển thị badge số lượng | F96: ✅ Positive | G96: **🟠 P1** | I96: 1. Thêm sản phẩm vào giỏ 2. Mở Design Studio | J96: Icon ShoppingBag hiển thị badge đỏ (#EF4444) với số lượng items. Badge nhỏ (w-4 h-4), font 10px, text trắng | L96: Add new | M96: By AI | N96: Manual | O96: Untested | T96: Untested
A97: TC_DS_SC_013 | B97: DS - Chung | C97: US-DS-01 | D97: DS Header - Cart | E97: Click icon giỏ hàng → mở CartDrawer | F97: ✅ Positive | G97: **🟠 P1** | I97: 1. Mở Design Studio 2. Click icon ShoppingBag | J97: Mở CartDrawer slide-over từ bên phải. Hiển thị danh sách items hoặc empty state | L97: Add new | M97: By AI | N97: Manual | O97: Untested | T97: Untested
A98: TC_DS_002 | B98: DS - Sidebar | C98: US-DS-02 | D98: Sidebar | E98: Click 'Mặt Sau' chuyển view canvas | F98: ✅ Positive | G98: **🟠 P1** | I98: 1. Mở Design Studio 2. Click icon 'Mặt Sau' trên sidebar | J98: Canvas chuyển sang hiển thị mặt sau áo thun. Vùng thiết kế mặt sau hiển thị | L98: Add new | M98: By AI | N98: Manual | O98: Untested | T98: Untested
A99: TC_DS_003 | B99: DS - Sidebar | C99: US-DS-02 | D99: Sidebar | E99: Click 'Thử Đồ với AI' mở tính năng try-on | F99: ✅ Positive | G99: **🟠 P1** | I99: 1. Mở Design Studio 2. Click icon 'Thử Đồ với AI' | J99: Mở tính năng AI Try-on. Hiển thị form upload ảnh hoặc modal thử đồ | L99: Add new | M99: By AI | N99: Manual | O99: Untested | T99: Untested
A100: TC_DS_014 | B100: DS - Sidebar | C100: US-DS-02 | D100: Sidebar | E100: Click 'Hoàn Tác' (Undo) sau khi thêm element | F100: ✅ Positive | G100: **🟠 P1** | I100: 1. Mở Design Studio 2. Thêm 1 element lên canvas 3. Click icon 'Hoàn Tác' | J100: Element vừa thêm biến mất khỏi canvas. Canvas quay về trạng thái trước đó | L100: Add new | M100: By AI | N100: Manual | O100: Untested | T100: Untested
A101: TC_DS_015 | B101: DS - Sidebar | C101: US-DS-02 | D101: Sidebar | E101: Click 'Làm Lại' (Redo) sau khi Undo | F101: ✅ Positive | G101: **🟠 P1** | I101: 1. Mở Design Studio 2. Thêm element → Click Undo 3. Click icon 'Làm Lại' | J101: Element xuất hiện trở lại trên canvas. Trạng thái khôi phục đúng | L101: Add new | M101: By AI | N101: Manual | O101: Untested | T101: Untested
... A207: TC_DS_F_PROF_002 | B207: DS - Chung | C207: US-TB-PROF | D207: DS - User Menu | E207: TopBar: Click 'Hồ sơ cá nhân' navigate đúng | F207: ✅ Positive | G207: **🟠 P1** | I207: 1. Click 'Hồ sơ cá nhân' | J207: Navigate đến /profile page. Profile page load thành công | L207: Add new | M207: By AI | N207: Manual | O207: Untested | T207: Untested
A208: 📌 Security
A209: TC_TEM_007 | B209: DS - Gallery | C209: US-07 | D209: Gallery - Search | E209: Search XSS injection | F209: ⚠️ Negative | G209: **🟠 P1** | I209: 1. Truy cập vào trang 2. Nhập script tag vào search | J209: Không execute. Sanitize input | L209: Add new | M209: By AI | N209: Manual | O209: Untested | T209: Untested

Sheet AI GENERATE
A1: TC_ID | B1: Screen | C1: US_Mapping | D1: Module | E1: Title | F1: Type | G1: Priority | H1: Pre-condition | I1: Steps | J1: Expected Result | K1: Actual Result | L1: Action Type | M1: Create TCs Type | N1: Execution Type | O1: Result_R1 | P1: Test Date_R1 | Q1: Tester_R1 | R1: Bug ID_R1 | S1: Bug Desc_R1 | T1: Result_R2 | U1: Test Date_R2 | V1: Tester_R2 | W1: Bug ID_R2 | X1: Bug Desc_R2 | Y1: Evidence | Z1: Notes | AA1: Review_Manual (Feedback)
A2: 📌 UI/UX
A3: TC_AI_UI_013 | B3: DS - AI Panel | C3: US-37 | D3: AI Gen - UI/UX | E3: AI page: UI form cấu hình layout | F3: 🎨 UI/UX | G3: **🟠 P1** | I3: 1. Truy cập vào trang 2. Quan sát layout input form | J3: Input placeholder: 'Mô tả ý tưởng của bạn'. Styles: Digital Art, Realistic, Watercolor, Anime, Oil Painting. Thanh trượt 1-4 hình | L3: Add new | M3: By AI | N3: Manual | O3: Untested | T3: Untested
A4: TC_AI_UI_014 | B4: DS - AI Panel | C4: US-37 | D4: AI Gen - UI/UX | E4: AI page: Hiển thị chi phí generate | F4: 🎨 UI/UX | G4: **🟠 P1** | I4: 1. Truy cập vào trang 2. Thay đổi số lượng ảnh | J4: Hiển thị text: 'Tiêu tốn: X credits' (Vd: 'Tiêu tốn: 5 credits' khi generate 4 hình) | L4: Add new | M4: By AI | N4: Manual | O4: Untested | T4: Untested
A5: TC_DS_UI_006 | B5: DS - AI Panel | C5: US-DS-04 | D5: DS Chung - AI Panel | E5: AI Panel (bên phải) nội dung đầy đủ | F5: 🎨 UI/UX | G5: **🟠 P1** | I5: 1. Mở Design Studio 2. Trên AI Panel (mặc định hiển thị bên phải) 3. Quan sát nội dung panel | J5: Hiển thị: 'MÔ TẢ ARTWORK' (textarea), 'ẢNH THAM KHẢO' (2 nút: 'Chọn từ thư viện', 'Tải ảnh lên'), 'PHONG CÁCH' (6 style cards), text 'Mỗi lần tạo tốn 3 Credits', nút '✨ Tạo Artwork Mới' | L5: Add new | M5: By AI | N5: Manual | O5: Untested | T5: Untested
A6: TC_DS_UI_007 | B6: DS - AI Panel | C6: US-DS-04 | D6: DS Chung - AI Panel | E6: 6 phong cách AI có ảnh minh họa | F6: 🎨 UI/UX | G6: **🟠 P1** | I6: 1. Mở Design Studio 2. Trong AI Panel, quan sát phần PHONG CÁCH | J6: Hiển thị 6 style cards: 'Watercolor', 'Minimalist', 'Line Art', 'Retro', 'Grunge', 'Flat Design'. Mỗi card có ảnh minh họa + text tên style | L6: Add new | M6: By AI | N6: Manual | O6: Untested | T6: Untested
A7: TC_DS_UI_009 | B7: DS - AI Panel | C7: US-DS-04 | D7: DS Chung - AI Panel | E7: Textarea MÔ TẢ ARTWORK placeholder | F7: 🎨 UI/UX | G7: **🟢 P2** | I7: 1. Mở Design Studio 2. Quan sát textarea trong AI Panel | J7: Placeholder hiển thị: 'VD: Rồng Việt Nam phong cách watercolor, màu xanh lam và vàng...' | L7: Add new | M7: By AI | N7: Manual | O7: Untested | T7: Untested
A8: TC_CRD_UI_009 | B8: MH Credits | C8: US-40 | D8: Credits - UI/UX | E8: Wallet page: Header card số dư | F8: 🎨 UI/UX | G8: **🟠 P1** | I8: 1. Truy cập vào trang 2. Quan sát card số dư màu tím | J8: Hiển thị: 'Số dư hiện tại: [X] Credits'. Nút: 'Nạp thêm Credits', 'Rút Credits' | L8: Add new | M8: By AI | N8: Manual | O8: Untested | T8: Untested
A9: TC_CRD_UI_010 | B9: MH Credits | C9: US-41 | D9: Credits - UI/UX | E9: Wallet page: Lịch sử và Tabs | F9: 🎨 UI/UX | G9: **🟢 P2** | I9: 1. Truy cập vào trang 2. Quan sát bảng lịch sử giao dịch | J9: Có Tabs: 'Tất cả', 'Nhận', 'Sử dụng'. Bảng có: Ngày giao dịch, Loại, Nội dung, Số tiền (+/-), Số dư sau giao dịch. (vd: 'Chào mừng (+5)', 'Mua hàng (+10)') | L9: Add new | M9: By AI | N9: Manual | O9: Untested | T9: Untested
A10: TC_CRD_UI_011 | B10: MH Credits | C10: US-41 | D10: Credits - UI/UX | E10: Wallet page: Empty state | F10: 🎨 UI/UX | G10: **🟢 P2** | I10: 1. Truy cập vào trang 2. Mở trang Ví Credits | J10: Hiển thị empty state: 'Chưa có giao dịch credits nào' | L10: Add new | M10: By AI | N10: Manual | O10: Untested | T10: Untested
A11: 📌 Validation
A12: TC_AI_002 | B12: DS - AI Panel | C12: US-37 | D12: AI Gen - Engine | E12: Prompt rỗng | F12: ⚠️ Negative | G12: **🔴 P0** | I12: 1. Truy cập vào trang 2. Không nhập prompt 3. Click 'Generate' | J12: Validation: 'Vui lòng nhập mô tả' | L12: Add new | M12: By AI | N12: Manual | O12: Untested | T12: Untested
A13: TC_AI_003 | B13: DS - AI Panel | C13: US-37 | D13: AI Gen - Engine | E13: Prompt chứa nội dung nhạy cảm | F13: ⚠️ Negative | G13: **🔴 P0** | I13: 1. Truy cập vào trang 2. Nhập prompt vi phạm policy 3. Click 'Generate' | J13: Từ chối: 'Nội dung không phù hợp'. Không trừ credit | L13: Add new | M13: By AI | N13: Manual | O13: Untested | T13: Untested
A14: TC_AI_004 | B14: DS - AI Panel | C14: US-37 | D14: AI Gen - Engine | E14: Prompt rất dài (1000+ ký tự) | F14: ✅ Boundary | G14: **🟠 P1** | I14: 1. Truy cập vào trang 2. Nhập prompt 1000+ ký tự 3. Click 'Generate' | J14: Truncate hoặc warning max length | L14: Add new | M14: By AI | N14: Manual | O14: Untested | T14: Untested
A15: TC_AI_009 | B15: DS - AI Panel | C15: — | D15: AI Gen - Quota | E15: Guest: 2 lượt/ngày | F15: ⚠️ Negative | G15: **🔴 P0** | I15: 1. Truy cập vào trang 2. Click 'Generate' lần thứ 3 | J15: Hiển thị: 'Out of Credits'. Gợi ý đăng ký tài khoản | L15: Add new | M15: By AI | N15: Manual | O15: Untested | T15: Untested
A16: TC_AI_010 | B16: DS - AI Panel | C16: — | D16: AI Gen - Quota | E16: Free user: 10 lượt/ngày | F16: ⚠️ Negative | G16: **🔴 P0** | I16: 1. Truy cập vào trang 2. Click 'Generate' lần thứ 11 | J16: Hiển thị: 'Hết lượt tạo hôm nay'. Gợi ý chờ reset | L16: Add new | M16: By AI | N16: Manual | O16: Untested | T16: Untested
A17: TC_AI_011 | B17: DS - AI Panel | C17: — | D17: AI Gen - Quota | E17: Quota reset lúc 00:00 | F17: ✅ Boundary | G17: **🟠 P1** | I17: 1. Truy cập vào trang 2. Chờ qua 00:00 3. Thử Generate | J17: Quota reset. Generate thành công | L17: Add new | M17: By AI | N17: Manual | O17: Untested | T17: Untested
A18: TC_AI_007 | B18: DS - AI Panel | C18: US-38 | D18: AI Gen - Upscale | E18: Upscale khi hết credits | F18: ⚠️ Negative | G18: **🔴 P0** | I18: 1. Truy cập vào trang 2. Click 'Dùng ngay' | J18: Hiển thị: 'Hết credits'. Gợi ý chờ reset hoặc mua thêm | L18: Add new | M18: By AI | N18: Manual | O18: Untested | T18: Untested
A19: TC_DS_011 | B19: DS - AI Panel | C19: US-DS-04 | D19: DS Chung - AI Panel | E19: Nút 'Tạo Artwork Mới' disabled khi textarea MÔ TẢ rỗng | F19: ⚠️ Negative | G19: **🔴 P0** | I19: 1. Mở Design Studio 2. Không nhập gì vào textarea MÔ TẢ ARTWORK 3. Quan sát nút '✨ Tạo Artwork Mới' | J19: Nút '✨ Tạo Artwork Mới' bị disabled (mờ đi, không click được). Không trừ credits. Cursor không chuyển sang pointer khi hover | L19: Add new | M19: By AI | N19: Manual | O19: Untested | T19: Untested
A20: TC_DS_012 | B20: DS - AI Panel | C20: US-DS-04 | D20: DS Chung - AI Panel | E20: Tạo Artwork khi hết credits (0 credits) | F20: ⚠️ Negative | G20: **🔴 P0** | H20: Precondition: Tài khoản có 0 credits | I20: 1. Mở Design Studio 2. Nhập mô tả hợp lệ 3. Click '✨ Tạo Artwork Mới' | J20: Hiển thị: 'Hết credits'. Gợi ý nạp thêm. Không cho phép tạo artwork. Không trừ credits | L20: Add new | M20: By AI | N20: Manual | O20: Untested | T20: Untested
A21: TC_CRD_008 | B21: MH Credits | C21: US-42b | D21: Credits - Daily Reset | E21: Reset đúng theo timezone | F21: ✅ Boundary | G21: **🟠 P1** | I21: 1. Truy cập vào trang 2. Kiểm tra thời điểm reset | J21: Reset lúc 00:00 theo timezone server/user | L21: Add new | M21: By AI | N21: Manual | O21: Untested | T21: Untested
A22: TC_CRD_005 | B22: MH Credits | C22: US-42 | D22: Credits - Spend | E22: Dùng credits khi balance = 0 | F22: ⚠️ Negative | G22: **🔴 P0** | I22: 1. Truy cập vào trang 2. Thử Generate | J22: Hiển thị: 'Hết credits'. Không cho thực hiện | L22: Add new | M22: By AI | N22: Manual | O22: Untested | T22: Untested
A23: 📌 Functional
A24: TC_AI_001 | B24: DS - AI Panel | C24: US-37 | D24: AI Gen - Engine | E24: Nhập prompt → 4 preview ảnh | F24: ✅ Positive | G24: **🔴 P0** | I24: 1. Truy cập vào trang 2. Nhập prompt tiếng Việt 3. Chọn style: Digital Art 4. Click 'Generate' | J24: Loading state. Trả về 4 ảnh preview low-res trong 30-60s. Trừ 1 credit | L24: Add new | M24: By AI | N24: Manual | O24: Untested | T24: Untested
A25: TC_AI_005 | B25: DS - AI Panel | C25: US-37 | D25: AI Gen - Engine | E25: Generate khi đang generate (double click) | F25: ✅ Edge Case | G25: **🟠 P1** | I25: 1. Truy cập vào trang 2. Click 'Generate' 2 lần nhanh | J25: Chỉ 1 request được xử lý. Button disabled khi đang loading | L25: Add new | M25: By AI | N25: Manual | O25: Untested | T25: Untested
A26: TC_AI_008 | B26: DS - AI Panel | C26: US-39 | D26: AI Gen - UX | E26: Aha Moment messages khi render | F26: ✅ Positive | G26: **🟠 P1** | I26: 1. Truy cập vào trang 2. Quan sát loading state | J26: Messages xoay vui: 'Đang pha màu...', 'AI đang vẽ...' | L26: Add new | M26: By AI | N26: Manual | O26: Untested | T26: Untested
A27: TC_AI_006 | B27: DS - AI Panel | C27: US-38 | D27: AI Gen - Upscale | E27: Chọn 1 ảnh → upscale ≥2048px | F27: ✅ Positive | G27: **🔴 P0** | I27: 1. Truy cập vào trang 2. Click 'Dùng ngay' trên ảnh 1 | J27: Upscale 2k/4k. Lưu My Gallery. Chuyển sang Editor | L27: Add new | M27: By AI | N27: Manual | O27: Untested | T27: Untested
A28: TC_DS_032 | B28: DS - AI Panel | C28: US-DS-04 | D28: DS Chung - AI Panel | E28: Tạo Artwork thành công (happy path đầy đủ) | F28: ✅ Positive | G28: **🔴 P0** | I28: 1. Mở Design Studio → AI Panel (bên phải) 2. Nhập: 'Rồng Việt Nam phong cách watercolor' 3. Chọn style 'Watercolor' 4. Click '✨ Tạo Artwork Mới' | J28: Loading state hiển thị. Artwork mới xuất hiện trên canvas. Credits giảm 3 (từ 12 → 9) | L28: Add new | M28: By AI | N28: Manual | O28: Untested | T28: Untested
A29: TC_DS_006 | B29: DS - AI Panel | C29: US-DS-04 | D29: DS Chung - AI Panel | E29: Click style card để chọn phong cách AI | F29: ✅ Positive | G29: **🟠 P1** | I29: 1. Mở Design Studio → AI Panel (bên phải) 2. Click card 'Watercolor' 3. Click card 'Retro' | J29: Style card được chọn có highlight (border đậm hoặc background đổi). Style trước đó bỏ highlight | L29: Add new | M29: By AI | N29: Manual | O29: Untested | T29: Untested
A30: TC_DS_026 | B30: DS - AI Panel | C30: US-DS-04 | D30: DS Chung - AI Panel | E30: Click 'Chọn từ thư viện' trong ẢNH THAM KHẢO | F30: ✅ Positive | G30: **🟠 P1** | I30: 1. Mở Design Studio → AI Panel (bên phải) 2. Click nút 'Chọn từ thư viện' tại phần ẢNH THAM KHẢO | J30: Mở modal/gallery thư viện ảnh tham khảo. Cho phép chọn ảnh làm reference cho AI generate | L30: Add new | M30: By AI | N30: Manual | O30: Untested | T30: Untested
A31: TC_DS_027 | B31: DS - AI Panel | C31: US-DS-04 | D31: DS Chung - AI Panel | E31: Click 'Tải ảnh lên' trong ẢNH THAM KHẢO | F31: ✅ Positive | G31: **🟠 P1** | I31: 1. Mở Design Studio → AI Panel (bên phải) 2. Click nút 'Tải ảnh lên' tại phần ẢNH THAM KHẢO | J31: Mở native file picker (OS dialog). Chấp nhận file ảnh PNG/JPG. Ảnh upload hiển thị preview tại phần ẢNH THAM KHẢO | L31: Add new | M31: By AI | N31: Manual | O31: Untested | T31: Untested
A32: TC_DS_029 | B32: DS - AI Panel | C32: US-DS-04 | D32: DS Chung - AI Panel | E32: Click style card 'Line Art' chọn phong cách | F32: ✅ Positive | G32: **🟠 P1** | I32: 1. Mở Design Studio → AI Panel (bên phải) 2. Click card 'Line Art' | J32: Card 'Line Art' highlight (border đậm). Các card khác bỏ highlight | L32: Add new | M32: By AI | N32: Manual | O32: Untested | T32: Untested
A33: TC_DS_030 | B33: DS - AI Panel | C33: US-DS-04 | D33: DS Chung - AI Panel | E33: Click style card 'Grunge' chọn phong cách | F33: ✅ Positive | G33: **🟠 P1** | I33: 1. Mở Design Studio → AI Panel (bên phải) 2. Click card 'Grunge' | J33: Card 'Grunge' highlight. Các card khác bỏ highlight | L33: Add new | M33: By AI | N33: Manual | O33: Untested | T33: Untested
A34: TC_DS_031 | B34: DS - AI Panel | C34: US-DS-04 | D34: DS Chung - AI Panel | E34: Click style card 'Flat Design' chọn phong cách | F34: ✅ Positive | G34: **🟠 P1** | I34: 1. Mở Design Studio → AI Panel (bên phải) 2. Click card 'Flat Design' | J34: Card 'Flat Design' highlight. Các card khác bỏ highlight | L34: Add new | M34: By AI | N34: Manual | O34: Untested | T34: Untested
A35: TC_CRD_006 | B35: MH Credits | C35: US-42b | D35: Credits - Daily Reset | E35: Credits refill mỗi 24h | F35: ✅ Positive | G35: **🔴 P0** | I35: 1. Truy cập vào trang 2. Chờ qua 00:00 3. Kiểm tra balance | J35: Balance tự refill về mức mặc định (vd: 10 credits) | L35: Add new | M35: By AI | N35: Manual | O35: Untested | T35: Untested
... A40: TC_CRD_004 | B40: MH Credits | C40: US-42 | D40: Credits - Spend | E40: Dùng credits cho upscale | F40: ✅ Positive | G40: **🔴 P0** | I40: 1. Truy cập vào trang 2. Click 'Dùng ngay' (upscale) 3. Kiểm tra balance | J40: Trừ credits cho upscale | L40: Add new | M40: By AI | N40: Manual | O40: Untested | T40: Untested
A41: 📌 Security
A42: TC_DS_013 | B42: DS - AI Panel | C42: US-DS-04 | D42: DS Chung - AI Panel | E42: Nhập XSS vào textarea MÔ TẢ ARTWORK | F42: ⚠️ Negative | G42: **🟠 P1** | I42: 1. Mở Design Studio 2. Nhập '<script>alert(1)</script>' vào textarea 3. Click '✨ Tạo Artwork Mới' | J42: Hệ thống sanitize input. Không execute script. Prompt được escape đúng | L42: Add new | M42: By AI | N42: Manual | O42: Untested | T42: Untested
A43: 📌 Performance
A44: TC_AI_012 | B44: DS - AI Panel | C44: — | D44: AI Gen - Network | E44: Generate khi mất mạng giữa chừng | F44: ⚠️ Negative | G44: **🟠 P1** | I44: 1. Truy cập vào trang 2. Ngắt mạng giữa quá trình render | J44: Timeout message. Không trừ credit nếu chưa có kết quả | L44: Add new | M44: By AI | N44: Manual | O44: Untested | T44: Untested

Sheet ĐẶT HÀNG
A1: TC_ID | B1: Screen | C1: US_Mapping | D1: Module | E1: Title | F1: Type | G1: Priority | H1: Pre-condition | I1: Steps | J1: Expected Result | K1: Actual Result | L1: Action Type | M1: Create TCs Type | N1: Execution Type | O1: Result_R1 | P1: Test Date_R1 | Q1: Tester_R1 | R1: Bug ID_R1 | S1: Bug Desc_R1 | T1: Result_R2 | U1: Test Date_R2 | V1: Tester_R2 | W1: Bug ID_R2 | X1: Bug Desc_R2 | Y1: Evidence | Z1: Notes | AA1: Review_Manual (Feedback)
A2: 📌 UI/UX
A3: TC_CAR_UI_809 | B3: DS - OrderModal | C3: Global | D3: Responsive & Zoom | E3: Màn hình Cart: Browser Zoom In/Out (50% - 200%) giữ nguyên layout | F3: 🎨 UI/UX | G3: **🟠 P1** | I3: 1. Truy cập trang Cart. 2. Nhấn Ctrl/Cmd + [+] để Zoom In 200%. 3. Nhấn Ctrl/Cmd + [-] để Zoom Out 50%. 4. Cuộn và quan sát toàn màn hình. | J3: Text/SVG luôn sắc nét, không bị vỡ hạt (pixelated). Bố cục (Layout) thu phóng đúng tỷ lệ, không rớt dòng bậy bạ, không che lấp button quan trọng. | L3: Add new | M3: By AI | N3: Manual | O3: Untested | T3: Untested
A4: TC_CAR_UI_833 | B4: DS - OrderModal | C4: Global | D4: Responsive (Android Tablet) | E4: Màn hình Cart: Responsive trên Android Tablet (Chrome, Dọc - Portrait) | F4: 🎨 UI/UX | G4: **🟠 P1** | I4: 1. Truy cập trang Cart trên Tablet Android ở chế độ cầm dọc (Portrait). 2. Thao tác trên giao diện. | J4: Giao diện hoạt động trơn tru tương tự iPad, icon và text scale đúng chuẩn tỉ lệ (không quá bé hoặc quá khổng lồ). | L4: Add new | M4: By AI | N4: Manual | O4: Untested | T4: Untested
A5: TC_CAR_UI_831 | B5: DS - OrderModal | C5: Global | D5: Responsive (Android) | E5: Màn hình Cart: Responsive trên Android Phone (Chrome, Dọc - Portrait) | F5: 🎨 UI/UX | G5: **🔴 P0** | I5: 1. Truy cập trang Cart trên điện thoại Android chế độ cầm dọc (Portrait). 2. Cuộn lên/xuống toàn bộ trang. 3. Focus vào các input (bàn phím ảo hiện lên). | J5: Bố cục hoàn toàn responsive (tương tự iPhone). Đảm bảo thanh bar dưới cùng của trình duyệt Android hoặc bàn phím ảo không che khuất các nút CTA quan trọng. Màn hình không bị giật/nháy (flicker). | L5: Add new | M5: By AI | N5: Manual | O5: Untested | T5: Untested
A6: TC_CAR_UI_834 | B6: DS - OrderModal | C6: Global | D6: Responsive (Landscape) | E6: Màn hình Cart: Responsive chế độ Xoay Ngang (Landscape - Điện thoại/Tablet) | F6: 🎨 UI/UX | G6: **🔴 P0** | I6: 1. Từ trạng thái dọc, xoay ngang thiết bị di động (Landscape). 2. Đảm bảo tính năng xoay màn hình của hệ điều hành được bật. 3. Quan sát quá trình chuyển đổi giao diện. | J6: UI tự động sắp xếp lại chiều ngang phù hợp. Ở điện thoại, Sticky Footer/Header không chiếm quá nhiều không gian theo chiều dọc (để lại đủ không gian hiển thị nội dung). Không bị lủng layout trong lúc/sau khi xoay. | L6: Add new | M6: By AI | N6: Manual | O6: Untested | T6: Untested
A7: TC_CAR_UI_832 | B7: DS - OrderModal | C7: Global | D7: Responsive (iPad) | E7: Màn hình Cart: Responsive trên iPad (Safari, Dọc - Portrait) | F7: 🎨 UI/UX | G7: **🟠 P1** | I7: 1. Truy cập trang Cart trên iPad ở chế độ cầm dọc (Portrait). 2. Quan sát bố cục. | J7: Màn hình căn giữa hợp lý hoặc duy trì layout multi-column của Desktop nếu đủ không gian. Không bị rớt nút, không bị trải rộng (stretch) hình ảnh quá mức làm nhòa tỷ lệ. | L7: Add new | M7: By AI | N7: Manual | O7: Untested | T7: Untested
A8: TC_CAR_UI_830 | B8: DS - OrderModal | C8: Global | D8: Responsive (iPhone) | E8: Màn hình Cart: Responsive trên iPhone (Safari/Chrome, Dọc - Portrait) | F8: 🎨 UI/UX | G8: **🔴 P0** | I8: 1. Truy cập trang Cart trên iPhone ở chế độ cầm dọc (Portrait). 2. Cuộn lên/xuống toàn trang. 3. Tap thử các nút bấm, input field. | J8: Không xuất hiện thanh cuộn ngang thừa. Các khối nội dung hiển thị cột đơn (stacking). Các nút bấm (Touch Targets) không quá nhỏ, không nằm sát mép màn hình (có padding viền an toàn hợp lý). | L8: Add new | M8: By AI | N8: Manual | O8: Untested | T8: Untested
A9: TC_DSDH_UI_004 | B9: DS - OrderModal | C9: US-DS-05 | D9: Đặt hàng - Bottom Bar | E9: Nút 'Đặt hàng' style nổi bật | F9: 🎨 UI/UX | G9: **🟠 P1** | I9: 1. Mở Design Studio 2. Quan sát nút 'Đặt hàng' trên bottom bar | J9: Nút 'Đặt hàng' có background đậm, text trắng, bo tròn. Đủ lớn để click. Có hover effect | L9: Add new | M9: By AI | N9: Manual | O9: Untested | T9: Untested
A10: TC_DSDH_UI_001 | B10: DS - OrderModal | C10: US-DS-05 | D10: Đặt hàng - Panel | E10: OrderModal (popup từ StatusBar): Form đặt hàng hiển thị đầy đủ | F10: 🎨 UI/UX | G10: **🟠 P1** | I10: 1. Mở Design Studio 2. Click nút 'Đặt hàng' trên StatusBar → OrderModal 3. Quan sát panel | J10: Hiển thị form đặt hàng: thông tin sản phẩm (tên, màu, size), ảnh preview thiết kế, số lượng selector, tổng giá. Nút 'Đặt hàng' nổi bật | L10: Add new | M10: By AI | N10: Manual | O10: Untested | T10: Untested
A11: TC_DSDH_UI_002 | B11: DS - OrderModal | C11: US-DS-05 | D11: Đặt hàng - Panel | E11: Thông tin giá hiển thị rõ ràng | F11: 🎨 UI/UX | G11: **🟠 P1** | I11: 1. Mở DS → OrderModal (popup từ StatusBar) 2. Quan sát phần giá | J11: Hiển thị: Đơn giá, Số lượng, Phí in (nếu có), Tổng cộng. Font size tổng cộng lớn hơn, đậm hơn. Đơn vị tiền VNĐ rõ ràng | L11: Add new | M11: By AI | N11: Manual | O11: Untested | T11: Untested
A12: TC_DSDH_UI_003 | B12: DS - OrderModal | C12: US-DS-05 | D12: Đặt hàng - Panel | E12: Preview thiết kế trong form đặt hàng | F12: 🎨 UI/UX | G12: **🟠 P1** | I12: 1. Mở DS (có artwork trên canvas) → OrderModal (popup từ StatusBar) 2. Quan sát preview | J12: Hiển thị ảnh preview sản phẩm với thiết kế đã tạo. Preview rõ nét, tương ứng với canvas | L12: Add new | M12: By AI | N12: Manual | O12: Untested | T12: Untested
A13: TC_PRO_007 | B13: MH Chi tiết SP | C13: US-12 | D13: Sản phẩm - Size | E13: Size Chart responsive mobile | F13: 🎨 UI/UX | G13: **🟢 P2** | I13: 1. Truy cập vào trang 2. Mở bảng size trên mobile | J13: Bảng scroll ngang hoặc stack. Không bị cắt cột | L13: Add new | M13: By AI | N13: Manual | O13: Untested | T13: Untested
A14: TC_CART_UI_003 | B14: MH Giỏ hàng | C14: US-20 | D14: Giỏ hàng - Empty | E14: MH Giỏ hàng: Empty state khi giỏ trống | F14: 🎨 UI/UX | G14: **🟠 P1** | I14: 1. Mở MH Giỏ hàng (chưa thêm sản phẩm) 2. Quan sát nội dung | J14: Hiển thị empty state: icon giỏ hàng trống + text 'Giỏ hàng trống' + nút CTA 'Thiết kế ngay' hoặc 'Khám phá sản phẩm' | L14: Add new | M14: By AI | N14: Manual | O14: Untested | T14: Untested
... A22: TC_CART_UI_861 | B22: MH Giỏ hàng | C22: Global | D22: Responsive (iPhone) | E22: MH Giỏ hàng: Responsive iPhone (Portrait) | F22: 🎨 UI/UX | G22: **🔴 P0** | I22: 1. Truy cập MH Giỏ hàng trên iPhone Portrait 2. Thao tác với các items | J22: Không thanh cuộn ngang. Items hiển thị dạng card stacking. Nút xóa dễ tap. Touch targets ≥44px | L22: Add new | M22: By AI | N22: Manual | O22: Untested | T22: Untested
A23: 📌 Validation
A24: TC_DH_SC_011 | B24: DS - OrderModal | C24: US-DS-05 | D24: OrderTab - Discount | E24: <10 chiếc → KHÔNG giảm giá | F24: ⚠️ Negative | G24: **🟠 P1** | I24: 1. OrderModal 2. Thêm 5 chiếc | J24: Dòng 'Giảm SL' KHÔNG hiển thị. Tổng = giá gốc. discountPercent = 0 | L24: Add new | M24: By AI | N24: Manual | O24: Untested | T24: Untested
A25: TC_DH_SC_015 | B25: DS - OrderModal | C25: US-DS-05 | D25: OrderTab - Promo | E25: Mã sai → hiện 'Mã không hợp lệ hoặc đã hết hạn' | F25: ⚠️ Negative | G25: **🟠 P1** | I25: 1. OrderModal → Nhập mã 'INVALIDCODE' 2. Click 'Áp dụng' | J25: Hiển thị dòng đỏ: 'Mã không hợp lệ hoặc đã hết hạn'. Mã không được áp dụng | L25: Add new | M25: By AI | N25: Manual | O25: Untested | T25: Untested
A26: TC_DSDH_V_004 | B26: DS - OrderModal | C26: US-DS-05 | D26: Thanh toán | E26: Thanh toán thiếu thông tin bắt buộc | F26: ⚠️ Negative | G26: **🔴 P0** | I26: 1. Từ Mua ngay → Trang Thanh toán 2. Để trống các field bắt buộc (tên, địa chỉ, SĐT) 3. Click Xác nhận | J26: Hiển thị validation error cho từng field trống. Không tạo đơn hàng | L26: Add new | M26: By AI | N26: Manual | O26: Untested | T26: Untested
A27: TC_DSDH_V_001 | B27: DS - OrderModal | C27: US-DS-05 | D27: Đặt hàng - Panel | E27: Đặt hàng khi canvas trống (không có thiết kế) | F27: ⚠️ Negative | G27: **🔴 P0** | I27: 1. Mở DS (canvas trống, không có artwork) 2. Click 'Đặt hàng' | J27: Hiển thị thông báo: 'Vui lòng thêm thiết kế trước khi đặt hàng'. Không cho phép checkout với áo trống | L27: Add new | M27: By AI | N27: Manual | O27: Untested | T27: Untested
A28: TC_DSDH_V_002 | B28: DS - OrderModal | C28: US-DS-05 | D28: Đặt hàng - Panel | E28: Số lượng = 0 hoặc âm | F28: ⚠️ Negative | G28: **🟠 P1** | I28: 1. Mở DS → OrderModal (popup từ StatusBar) 2. Nhập số lượng = 0 hoặc -1 | J28: Không cho phép đặt với số lượng ≤ 0. Nút disabled hoặc hiển thị validation error. Số lượng tối thiểu = 1 | L28: Add new | M28: By AI | N28: Manual | O28: Untested | T28: Untested
A29: TC_DSDH_V_003 | B29: DS - OrderModal | C29: US-DS-05 | D29: Đặt hàng - Panel | E29: Số lượng vượt giới hạn tối đa | F29: ⚠️ Negative | G29: **🟢 P2** | I29: 1. Mở DS → OrderModal (popup từ StatusBar) 2. Nhập số lượng = 99999 | J29: Hiển thị giới hạn tối đa (ví dụ: 100). Không cho phép vượt. Thông báo 'Số lượng tối đa là X' | L29: Add new | M29: By AI | N29: Manual | O29: Untested | T29: Untested
A30: TC_PRO_005 | B30: MH Chi tiết SP | C30: US-11 | D30: Sản phẩm - Color | E30: Đổi màu nhiều lần liên tiếp | F30: ✅ Boundary | G30: **🟠 P1** | I30: 1. Truy cập vào trang 2. Click Navy 3. Click White 4. Click Red nhanh liên tục | J30: Mockup update mượt, không lag/flicker | L30: Add new | M30: By AI | N30: Manual | O30: Untested | T30: Untested
A31: TC_ORD_002 | B31: MH Giỏ hàng | C31: US-20 | D31: Giỏ hàng - Add | E31: Add với qty = 0 | F31: ⚠️ Negative | G31: **🟠 P1** | I31: 1. Truy cập vào trang 2. Nhập Qty: 0 3. Click 'Add to Cart' | J31: Validation: qty phải >= 1 | L31: Add new | M31: By AI | N31: Manual | O31: Untested | T31: Untested
A32: TC_CART_V_001 | B32: MH Giỏ hàng | C32: US-20 | D32: Giỏ hàng - Qty | E32: Cập nhật số lượng = 0 | F32: ⚠️ Negative | G32: **🟠 P1** | I32: 1. Mở Giỏ hàng 2. Giảm qty xuống 0 | J32: Hiển thị confirm xóa item hoặc tự động xóa. Qty tối thiểu = 1 | L32: Add new | M32: By AI | N32: Manual | O32: Untested | T32: Untested
A33: TC_CART_V_002 | B33: MH Giỏ hàng | C33: US-20 | D33: Giỏ hàng - Qty | E33: Nhập số lượng bằng chữ | F33: ⚠️ Negative | G33: **🟢 P2** | I33: 1. Mở Giỏ hàng 2. Nhập qty: 'abc' | J33: Input chỉ nhận số. Không crash | L33: Add new | M33: By AI | N33: Manual | O33: Untested | T33: Untested
A34: TC_CART_V_003 | B34: MH Giỏ hàng | C34: US-20 | D34: Giỏ hàng - Qty | E34: Số lượng vượt tối đa (>100) | F34: ⚠️ Negative | G34: **🟢 P2** | I34: 1. Mở Giỏ hàng 2. Nhập qty: 999 | J34: Giới hạn tối đa hoặc hiển thị warning | L34: Add new | M34: By AI | N34: Manual | O34: Untested | T34: Untested
A35: 📌 Functional
A36: TC_DH_SC_007 | B36: DS - OrderModal | C36: US-DS-05 | D36: OrderTab - Discount | E36: 10-29 chiếc → giảm 5% | F36: ✅ Positive | G36: **🟠 P1** | I36: 1. OrderModal 2. Thêm tổng 10+ chiếc (vd: S×5, M×5) | J36: Hiển thị dòng 'Giảm SL −5%' màu xanh. Số tiền giảm = 5% × subtotal. Source: {min:10, percent:5} | L36: Add new | M36: By AI | N36: Manual | O36: Untested | T36: Untested
A37: TC_DH_SC_008 | B37: DS - OrderModal | C37: US-DS-05 | D37: OrderTab - Discount | E37: 30-49 chiếc → giảm 10% | F37: ✅ Positive | G37: **🟠 P1** | I37: 1. OrderModal 2. Thêm tổng 30+ chiếc | J37: Hiển thị 'Giảm SL −10%'. Source: {min:30, percent:10} | L37: Add new | M37: By AI | N37: Manual | O37: Untested | T37: Untested
A38: TC_DH_SC_009 | B38: DS - OrderModal | C38: US-DS-05 | D38: OrderTab - Discount | E38: 50-99 chiếc → giảm 15% | F38: ✅ Positive | G38: **🟠 P1** | I38: 1. OrderModal 2. Thêm tổng 50+ chiếc | J38: Hiển thị 'Giảm SL −15%'. Source: {min:50, percent:15} | L38: Add new | M38: By AI | N38: Manual | O38: Untested | T38: Untested
A39: TC_DH_SC_010 | B39: DS - OrderModal | C39: US-DS-05 | D39: OrderTab - Discount | E39: 100+ chiếc → giảm 20% | F39: ✅ Positive | G39: **🟠 P1** | I39: 1. OrderModal 2. Thêm tổng 100+ chiếc | J39: Hiển thị 'Giảm SL −20%'. Source: {min:100, percent:20} | L39: Add new | M39: By AI | N39: Manual | O39: Untested | T39: Untested
A40: TC_DH_SC_001 | B40: DS - OrderModal | C40: US-DS-05 | D40: OrderTab - Pricing | E40: Giá sizes S/M/L = 120.000đ | F40: ✅ Positive | G40: **🔴 P0** | I40: 1. Mở DS → OrderModal 2. Chọn size S, M hoặc L | J40: Giá mỗi chiếc = 120.000đ. Hiển thị đúng trong bảng giá. Source: SIZE_PRICES = {S:120000, M:120000, L:120000} | L40: Add new | M40: By AI | N40: Manual | O40: Untested | T40: Untested
A41: TC_DH_SC_002 | B41: DS - OrderModal | C41: US-DS-05 | D41: OrderTab - Pricing | E41: Giá size XL = 130.000đ | F41: ✅ Positive | G41: **🔴 P0** | I41: 1. Mở DS → OrderModal 2. Chọn size XL | J41: Giá mỗi chiếc = 130.000đ. Chênh +10k so với S/M/L | L41: Add new | M41: By AI | N41: Manual | O41: Untested | T41: Untested
A42: TC_DH_SC_003 | B42: DS - OrderModal | C42: US-DS-05 | D42: OrderTab - Pricing | E42: Giá size 2XL = 140.000đ | F42: ✅ Positive | G42: **🔴 P0** | I42: 1. Mở DS → OrderModal 2. Chọn size 2XL | J42: Giá mỗi chiếc = 140.000đ. Chênh +20k so với S/M/L | L42: Add new | M42: By AI | N42: Manual | O42: Untested | T42: Untested
A43: TC_DH_SC_004 | B43: DS - OrderModal | C43: US-DS-05 | D43: OrderTab - Pricing | E43: Phí in DTG = 30.000đ/chiếc | F43: ✅ Positive | G43: **🟠 P1** | I43: 1. Có artwork trên canvas 2. Mở OrderModal, thêm size S ×1 | J43: Dòng 'Phí in DTG' hiển thị = 30.000đ × số chiếc. Source: PRINT_COST=30000 | L43: Add new | M43: By AI | N43: Manual | O43: Untested | T43: Untested
A44: TC_DH_SC_005 | B44: DS - OrderModal | C44: US-DS-05 | D44: OrderTab - Pricing | E44: Phí thiết kế = 5.000đ (cố định) | F44: ✅ Positive | G44: **🟠 P1** | I44: 1. Có artwork trên canvas 2. Mở OrderModal | J44: Dòng 'Phí thiết kế' hiển thị = 5.000đ (cố định, không nhân theo số lượng). Source: DESIGN_FEE=5000 | L44: Add new | M44: By AI | N44: Manual | O44: Untested | T44: Untested
A45: TC_DH_SC_006 | B45: DS - OrderModal | C45: US-DS-05 | D45: OrderTab - Pricing | E45: Không có artwork → KHÔNG tính phí in + phí thiết kế | F45: ✅ Positive | G45: **🟠 P1** | I45: 1. Canvas trống (không có artwork) 2. Mở OrderModal | J45: Dòng 'Phí in DTG' và 'Phí thiết kế' KHÔNG hiển thị. Tổng = chỉ tiền áo. Source: hasDesign=false check | L45: Add new | M45: By AI | N45: Manual | O45: Untested | T45: Untested
A46: TC_DH_SC_012 | B46: DS - OrderModal | C46: US-DS-05 | D46: OrderTab - Promo | E46: Mã TRYONIC20 → giảm 20% | F46: ✅ Positive | G46: **🟠 P1** | I46: 1. OrderModal → Nhập mã 'TRYONIC20' 2. Click 'Áp dụng' | J46: Hiển thị 'Mã TRYONIC20 (−20%)' màu teal. Số tiền giảm = 20% × subtotal | L46: Add new | M46: By AI | N46: Manual | O46: Untested | T46: Untested
A47: TC_DH_SC_013 | B47: DS - OrderModal | C47: US-DS-05 | D47: OrderTab - Promo | E47: Mã WELCOME10 → giảm 10% | F47: ✅ Positive | G47: **🟠 P1** | I47: 1. OrderModal → Nhập mã 'WELCOME10' 2. Click 'Áp dụng' | J47: Hiển thị 'Mã WELCOME10 (−10%)'. Áp dụng thành công | L47: Add new | M47: By AI | N47: Manual | O47: Untested | T47: Untested
... A81: TC_ORD_F_SIZE_001 | B81: DS - OrderModal | C81: US-ORD-SIZE | D81: DS - OrderModal | E81: OrderModal: Truyền selectedSize prop | F81: ✅ Positive | G81: **🟢 P2** | I81: 1. Chọn size trên canvas 2. Mở OrderModal | J81: Size đã chọn trước đó auto-select trong OrderTab | L81: Add new | M81: By AI | N81: Manual | O81: Untested | T81: Untested

Sheet THANH TOÁN
A1: TC_ID | B1: Screen | C1: US_Mapping | D1: Module | E1: Title | F1: Type | G1: Priority | H1: Pre-condition | I1: Steps | J1: Expected Result | K1: Actual Result | L1: Action Type | M1: Create TCs Type | N1: Execution Type | O1: Result_R1 | P1: Test Date_R1 | Q1: Tester_R1 | R1: Bug ID_R1 | S1: Bug Desc_R1 | T1: Result_R2 | U1: Test Date_R2 | V1: Tester_R2 | W1: Bug ID_R2 | X1: Bug Desc_R2 | Y1: Evidence | Z1: Notes | AA1: Review_Manual (Feedback)
A2: 📌 UI/UX
A3: TC_CHE_UI_811 | B3: MH Checkout | C3: Global | D3: Responsive & Zoom | E3: Màn hình Checkout: Browser Zoom In/Out (50% - 200%) giữ nguyên layout | F3: 🎨 UI/UX | G3: **🟠 P1** | I3: 1. Truy cập trang Checkout. 2. Nhấn Ctrl/Cmd + [+] để Zoom In 200%. 3. Nhấn Ctrl/Cmd + [-] để Zoom Out 50%. 4. Cuộn và quan sát toàn màn hình. | J3: Text/SVG luôn sắc nét, không bị vỡ hạt (pixelated). Bố cục (Layout) thu phóng đúng tỷ lệ, không rớt dòng bậy bạ, không che lấp button quan trọng. | L3: Add new | M3: By AI | N3: Manual | O3: Untested | T3: Untested
A4: TC_PAY_UI_813 | B4: MH Checkout | C4: Global | D4: Responsive & Zoom | E4: Màn hình Payment: Browser Zoom In/Out (50% - 200%) giữ nguyên layout | F4: 🎨 UI/UX | G4: **🟠 P1** | I4: 1. Truy cập trang Payment. 2. Nhấn Ctrl/Cmd + [+] để Zoom In 200%. 3. Nhấn Ctrl/Cmd + [-] để Zoom Out 50%. 4. Cuộn và quan sát toàn màn hình. | J4: Text/SVG luôn sắc nét, không bị vỡ hạt (pixelated). Bố cục (Layout) thu phóng đúng tỷ lệ, không rớt dòng bậy bạ, không che lấp button quan trọng. | L4: Add new | M4: By AI | N4: Manual | O4: Untested | T4: Untested
A5: TC_CHE_UI_838 | B5: MH Checkout | C5: Global | D5: Responsive (Android Tablet) | E5: Màn hình Checkout: Responsive trên Android Tablet (Chrome, Dọc - Portrait) | F5: 🎨 UI/UX | G5: **🟠 P1** | I5: 1. Truy cập trang Checkout trên Tablet Android ở chế độ cầm dọc (Portrait). 2. Thao tác trên giao diện. | J5: Giao diện hoạt động trơn tru tương tự iPad, icon và text scale đúng chuẩn tỉ lệ (không quá bé hoặc quá khổng lồ). | L5: Add new | M5: By AI | N5: Manual | O5: Untested | T5: Untested
A6: TC_PAY_UI_843 | B6: MH Checkout | C6: Global | D6: Responsive (Android Tablet) | E6: Màn hình Payment: Responsive trên Android Tablet (Chrome, Dọc - Portrait) | F6: 🎨 UI/UX | G6: **🟠 P1** | I6: 1. Truy cập trang Payment trên Tablet Android ở chế độ cầm dọc (Portrait). 2. Thao tác trên giao diện. | J6: Giao diện hoạt động trơn tru tương tự iPad, icon và text scale đúng chuẩn tỉ lệ (không quá bé hoặc quá khổng lồ). | L6: Add new | M6: By AI | N6: Manual | O6: Untested | T6: Untested
A7: TC_CHE_UI_836 | B7: MH Checkout | C7: Global | D7: Responsive (Android) | E7: Màn hình Checkout: Responsive trên Android Phone (Chrome, Dọc - Portrait) | F7: 🎨 UI/UX | G7: **🔴 P0** | I7: 1. Truy cập trang Checkout trên điện thoại Android chế độ cầm dọc (Portrait). 2. Cuộn lên/xuống toàn bộ trang. 3. Focus vào các input (bàn phím ảo hiện lên). | J7: Bố cục hoàn toàn responsive (tương tự iPhone). Đảm bảo thanh bar dưới cùng của trình duyệt Android hoặc bàn phím ảo không che khuất các nút CTA quan trọng. Màn hình không bị giật/nháy (flicker). | L7: Add new | M7: By AI | N7: Manual | O7: Untested | T7: Untested
A8: TC_PAY_UI_841 | B8: MH Checkout | C8: Global | D8: Responsive (Android) | E8: Màn hình Payment: Responsive trên Android Phone (Chrome, Dọc - Portrait) | F8: 🎨 UI/UX | G8: **🔴 P0** | I8: 1. Truy cập trang Payment trên điện thoại Android chế độ cầm dọc (Portrait). 2. Cuộn lên/xuống toàn bộ trang. 3. Focus vào các input (bàn phím ảo hiện lên). | J8: Bố cục hoàn toàn responsive (tương tự iPhone). Đảm bảo thanh bar dưới cùng của trình duyệt Android hoặc bàn phím ảo không che khuất các nút CTA quan trọng. Màn hình không bị giật/nháy (flicker). | L8: Add new | M8: By AI | N8: Manual | O8: Untested | T8: Untested
A9: TC_CHE_UI_839 | B9: MH Checkout | C9: Global | D9: Responsive (Landscape) | E9: Màn hình Checkout: Responsive chế độ Xoay Ngang (Landscape - Điện thoại/Tablet) | F9: 🎨 UI/UX | G9: **🔴 P0** | I9: 1. Từ trạng thái dọc, xoay ngang thiết bị di động (Landscape). 2. Đảm bảo tính năng xoay màn hình của hệ điều hành được bật. 3. Quan sát quá trình chuyển đổi giao diện. | J9: UI tự động sắp xếp lại chiều ngang phù hợp. Ở điện thoại, Sticky Footer/Header không chiếm quá nhiều không gian theo chiều dọc (để lại đủ không gian hiển thị nội dung). Không bị lủng layout trong lúc/sau khi xoay. | L9: Add new | M9: By AI | N9: Manual | O9: Untested | T9: Untested
A10: TC_PAY_UI_844 | B10: MH Checkout | C10: Global | D10: Responsive (Landscape) | E10: Màn hình Payment: Responsive chế độ Xoay Ngang (Landscape - Điện thoại/Tablet) | F10: 🎨 UI/UX | G10: **🔴 P0** | I10: 1. Từ trạng thái dọc, xoay ngang thiết bị di động (Landscape). 2. Đảm bảo tính năng xoay màn hình của hệ điều hành được bật. 3. Quan sát quá trình chuyển đổi giao diện. | J10: UI tự động sắp xếp lại chiều ngang phù hợp. Ở điện thoại, Sticky Footer/Header không chiếm quá nhiều không gian theo chiều dọc (để lại đủ không gian hiển thị nội dung). Không bị lủng layout trong lúc/sau khi xoay. | L10: Add new | M10: By AI | N10: Manual | O10: Untested | T10: Untested
A11: TC_CHE_UI_837 | B11: MH Checkout | C11: Global | D11: Responsive (iPad) | E11: Màn hình Checkout: Responsive trên iPad (Safari, Dọc - Portrait) | F11: 🎨 UI/UX | G11: **🟠 P1** | I11: 1. Truy cập trang Checkout trên iPad ở chế độ cầm dọc (Portrait). 2. Quan sát bố cục. | J11: Màn hình căn giữa hợp lý hoặc duy trì layout multi-column của Desktop nếu đủ không gian. Không bị rớt nút, không bị trải rộng (stretch) hình ảnh quá mức làm nhòa tỷ lệ. | L11: Add new | M11: By AI | N11: Manual | O11: Untested | T11: Untested
A12: TC_PAY_UI_842 | B12: MH Checkout | C12: Global | D12: Responsive (iPad) | E12: Màn hình Payment: Responsive trên iPad (Safari, Dọc - Portrait) | F12: 🎨 UI/UX | G12: **🟠 P1** | I12: 1. Truy cập trang Payment trên iPad ở chế độ cầm dọc (Portrait). 2. Quan sát bố cục. | J12: Màn hình căn giữa hợp lý hoặc duy trì layout multi-column của Desktop nếu đủ không gian. Không bị rớt nút, không bị trải rộng (stretch) hình ảnh quá mức làm nhòa tỷ lệ. | L12: Add new | M12: By AI | N12: Manual | O12: Untested | T12: Untested
A13: TC_CHE_UI_835 | B13: MH Checkout | C13: Global | D13: Responsive (iPhone) | E13: Màn hình Checkout: Responsive trên iPhone (Safari/Chrome, Dọc - Portrait) | F13: 🎨 UI/UX | G13: **🔴 P0** | I13: 1. Truy cập trang Checkout trên iPhone ở chế độ cầm dọc (Portrait). 2. Cuộn lên/xuống toàn trang. 3. Tap thử các nút bấm, input field. | J13: Không xuất hiện thanh cuộn ngang thừa. Các khối nội dung hiển thị cột đơn (stacking). Các nút bấm (Touch Targets) không quá nhỏ, không nằm sát mép màn hình (có padding viền an toàn hợp lý). | L13: Add new | M13: By AI | N13: Manual | O13: Untested | T13: Untested
A14: TC_PAY_UI_840 | B14: MH Checkout | C14: Global | D14: Responsive (iPhone) | E14: Màn hình Payment: Responsive trên iPhone (Safari/Chrome, Dọc - Portrait) | F14: 🎨 UI/UX | G14: **🔴 P0** | I14: 1. Truy cập trang Payment trên iPhone ở chế độ cầm dọc (Portrait). 2. Cuộn lên/xuống toàn trang. 3. Tap thử các nút bấm, input field. | J14: Không xuất hiện thanh cuộn ngang thừa. Các khối nội dung hiển thị cột đơn (stacking). Các nút bấm (Touch Targets) không quá nhỏ, không nằm sát mép màn hình (có padding viền an toàn hợp lý). | L14: Add new | M14: By AI | N14: Manual | O14: Untested | T14: Untested
... A19: TC_CKM_UI_002 | B19: MH Checkout Modal | C19: US-CKM-01 | D19: Checkout Modal - Drawer | E19: CheckoutModal: Drawer slide-in từ phải | F19: 🎨 UI/UX | G19: **🟠 P1** | I19: 1. Mở CheckoutModal | J19: Drawer 480px max-width, slide từ phải (slideInRight animation). Backdrop blur | L19: Add new | M19: By AI | N19: Manual | O19: Untested | T19: Untested
A20: 📌 Validation
A21: TC_ORD_006 | B21: MH Checkout | C21: US-21 | D21: Address | E21: Bỏ trống Phone | F21: ⚠️ Negative | G21: **🔴 P0** | I21: 1. Truy cập vào trang 2. Bỏ trống Phone 3. Click tiếp | J21: Hiển thị lỗi: 'Vui lòng nhập số điện thoại' | L21: Add new | M21: By AI | N21: Manual | O21: Untested | T21: Untested
A22: TC_ORD_007 | B22: MH Checkout | C22: US-21 | D22: Address | E22: Phone format sai | F22: ⚠️ Negative | G22: **🟠 P1** | I22: 1. Truy cập vào trang 2. Nhập Phone: abc | J22: Validation error: format SĐT không hợp lệ | L22: Add new | M22: By AI | N22: Manual | O22: Untested | T22: Untested
A23: TC_TT_SC_014 | B23: MH Checkout | C23: US-23 | D23: Checkout - Promo | E23: Mã sai trên checkout → 'Mã không hợp lệ' | F23: ⚠️ Negative | G23: **🟠 P1** | I23: 1. Nhập mã 'INVALIDCODE' 2. Click 'Áp dụng' | J23: Hiển thị text đỏ: 'Mã không hợp lệ'. Mã không được áp dụng | L23: Add new | M23: By AI | N23: Manual | O23: Untested | T23: Untested
A24: TC_TT_SC_018 | B24: MH Checkout | C24: US-25 | D24: Checkout - Redirect | E24: Truy cập checkout không có order data → redirect studio | F24: ⚠️ Negative | G24: **🟠 P1** | I24: 1. Truy cập trực tiếp /studio/checkout (không qua flow mua hàng) 2. Không có localStorage 'checkout_order' | J24: Auto redirect về /studio. Không hiển thị trang checkout trống | L24: Add new | M24: By AI | N24: Manual | O24: Untested | T24: Untested
A25: TC_TT_SC_010 | B25: MH Checkout | C25: US-21 | D25: Checkout - Shipping | E25: Submit thiếu field bắt buộc → scroll đến form | F25: ⚠️ Negative | G25: **🔴 P0** | I25: 1. Để trống Họ tên và SĐT 2. Click 'Thanh toán' | J25: Hiển thị error đỏ: 'Vui lòng nhập họ tên', 'Vui lòng nhập số điện thoại'. Auto-scroll đến section shipping | L25: Add new | M25: By AI | N25: Manual | O25: Untested | T25: Untested
A26: TC_ORD_011 | B26: MH Checkout | C26: US-23 | D26: Discount | E26: Áp mã hết hạn | F26: ⚠️ Negative | G26: **🟠 P1** | I26: 1. Truy cập vào trang 2. Nhập code hết hạn | J26: Hiển thị: 'Mã giảm giá đã hết hạn' | L26: Add new | M26: By AI | N26: Manual | O26: Untested | T26: Untested
A27: TC_ORD_012 | B27: MH Checkout | C27: US-23 | D27: Discount | E27: Áp mã không tồn tại | F27: ⚠️ Negative | G27: **🟠 P1** | I27: 1. Truy cập vào trang 2. Nhập mã không tồn tại | J27: Hiển thị: 'Mã giảm giá không hợp lệ' | L27: Add new | M27: By AI | N27: Manual | O27: Untested | T27: Untested
A28: TC_ORD_017 | B28: MH Checkout | C28: US-24 | D28: Online | E28: Ví POD không đủ Credits | F28: ⚠️ Negative | G28: **🟠 P1** | I28: 1. Truy cập vào trang 2. Chọn 'Ví POD' | J28: Hiển thị báo lỗi không đủ số dư. Chọn phương thức khác | L28: Add new | M28: By AI | N28: Manual | O28: Untested | T28: Untested
A29: TC_CK_V_ADDR_001 | B29: MH Checkout | C29: US-CK-ADDR | D29: Checkout - No Address | E29: Checkout: Submit khi chưa chọn địa chỉ | F29: ⚠️ Negative | G29: **🔴 P0** | I29: 1. Vào checkout 2. Không chọn địa chỉ nào 3. Click 'Thanh toán' | J29: Scroll đến section-shipping. Nút disabled (gray) khi isFormValid=false | L29: Add new | M29: By AI | N29: Manual | O29: Untested | T29: Untested
A30: TC_CK_V_ADDR_002 | B30: MH Checkout | C30: US-CK-ADDR | D30: Checkout - Invalid Promo | E30: Checkout: Nhập mã khuyến mại sai | F30: ⚠️ Negative | G30: **🟠 P1** | I30: 1. Click 'Nhập mã khuyến mại' 2. Nhập 'INVALID' 3. Click 'Áp dụng' | J30: Error đỏ 'Mã không hợp lệ'. Không áp dụng giảm giá | L30: Add new | M30: By AI | N30: Manual | O30: Untested | T30: Untested
A31: TC_CKM_V_001 | B31: MH Checkout Modal | C31: US-CKM-03 | D31: Checkout Modal - Invalid Step1 | E31: CheckoutModal: 'Tiếp tục' khi form empty | F31: ⚠️ Negative | G31: **🔴 P0** | I31: 1. Không điền gì 2. Click 'Tiếp tục →' | J31: Nút disabled (bg-gray-300, cursor-not-allowed). Không chuyển step | L31: Add new | M31: By AI | N31: Manual | O31: Untested | T31: Untested
A32: TC_CKM_V_002 | B32: MH Checkout Modal | C32: US-CKM-03 | D32: Checkout Modal - Countdown Zero | E32: CheckoutModal: Countdown hết giờ | F32: ✅ Boundary | G32: **🟢 P2** | I32: 1. Chờ countdown về 0:00 | J32: Banner biến mất (seconds <= 0 return null). Ưu đãi hết hạn | L32: Add new | M32: By AI | N32: Manual | O32: Untested | T32: Untested
A33: 📌 Functional
A34: TC_ORD_005 | B34: MH Checkout | C34: US-21 | D34: Address | E34: Nhập địa chỉ đầy đủ | F34: ✅ Positive | G34: **🔴 P0** | I34: 1. Truy cập vào trang 2. Nhập Name, Phone, Address 3. Chọn City/Dist/Ward | J34: Tính phí ship. Hiển thị tổng tiền | L34: Add new | M34: By AI | N34: Manual | O34: Untested | T34: Untested
A35: TC_TT_SC_005 | B35: MH Checkout | C35: US-25 | D35: Checkout - Auth | E35: Auth banner hiển thị khi chưa login | F35: ✅ Positive | G35: **🟠 P1** | I35: 1. Truy cập checkout (Guest) 2. Quan sát auth section | J35: Banner hiển thị: 'Đăng nhập để mua nhanh hơn', subtitle 'Auto-fill thông tin, theo dõi đơn hàng'. 3 nút: Facebook (xanh), Google (trắng), Email (xám). Nút X để đóng | L35: Add new | M35: By AI | N35: Manual | O35: Untested | T35: Untested
A36: TC_TT_SC_006 | B36: MH Checkout | C36: US-25 | D36: Checkout - Auth | E36: Login Facebook trên checkout → auto-fill form | F36: ✅ Positive | G36: **🟠 P1** | I36: 1. Click nút 'Facebook' trên auth banner | J36: Mock login thành công. Form shipping tự động điền: Nguyễn Văn A, 0901234567, a.nguyen@gmail.com, TP.HCM, Quận 1, 123 Lê Lợi. Banner auth biến mất | L36: Add new | M36: By AI | N36: Manual | O36: Untested | T36: Untested
A37: TC_TT_SC_007 | B37: MH Checkout | C37: US-25 | D37: Checkout - Auth | E37: Login Email trên checkout | F37: ✅ Positive | G37: **🟠 P1** | I37: 1. Click nút 'Email' 2. Nhập email + password 3. Click 'Đăng nhập' | J37: Hiển thị inline form (email + password). Sau login → auto-fill form. Banner hiển thị: '✓ Đã đăng nhập — thông tin được tự động điền' | L37: Add new | M37: By AI | N37: Manual | O37: Untested | T37: Untested
A38: TC_TT_SC_008 | B38: MH Checkout | C38: US-25 | D38: Checkout - Auth | E38: Chuyển đổi đăng nhập ↔ đăng ký trên checkout | F38: ✅ Positive | G38: **🟢 P2** | I38: 1. Click 'Email' → form đăng nhập 2. Click 'Đăng ký' ở bottom | J38: Form chuyển thành mode đăng ký. Text đổi: 'Đăng ký tài khoản'. Nút 'Đăng ký' | L38: Add new | M38: By AI | N38: Manual | O38: Untested | T38: Untested
A39: TC_TT_SC_003 | B39: MH Checkout | C39: US-25 | D39: Checkout - Countdown | E39: Countdown banner hiển thị 15:00 phút | F39: ✅ Positive | G39: **🟠 P1** | I39: 1. Mở checkout 2. Quan sát banner trên cùng | J39: Banner gradient teal-orange: icon Flame + text 'Freeship + Giảm 20k' + subtitle 'Hoàn tất thanh toán trong thời gian ưu đãi' + countdown MM:SS (bắt đầu từ 15:00) | L39: Add new | M39: By AI | N39: Manual | O39: Untested | T39: Untested
A40: TC_TT_SC_004 | B40: MH Checkout | C40: US-25 | D40: Checkout - Countdown | E40: Countdown đếm ngược realtime | F40: ✅ Positive | G40: **🟠 P1** | I40: 1. Mở checkout 2. Chờ 10 giây 3. Quan sát countdown | J40: Timer giảm từ 15:00 → 14:50. Khi hết → banner biến mất (seconds <= 0 return null) | L40: Add new | M40: By AI | N40: Manual | O40: Untested | T40: Untested
A41: TC_TT_SC_001 | B41: MH Checkout | C41: US-25 | D41: Checkout - Layout | E41: Header checkout hiển thị 'Thanh toán' + nút Quay lại | F41: ✅ Positive | G41: **🟠 P1** | I41: 1. Navigate đến /studio/checkout 2. Quan sát header | J41: Header sticky: nút '← Quay lại Studio' (trái), text 'Thanh toán' (phải). Background white, border-bottom | L41: Add new | M41: By AI | N41: Manual | O41: Untested | T41: Untested
A42: TC_TT_SC_002 | B42: MH Checkout | C42: US-25 | D42: Checkout - Layout | E42: Page title: 'Hoàn tất đơn hàng' | F42: ✅ Positive | G42: **🟢 P2** | I42: 1. Mở trang checkout 2. Quan sát tiêu đề | J42: H1: 'Hoàn tất đơn hàng'. Subtitle: 'Nhập thông tin giao hàng và thanh toán'. Font 2xl, font-black | L42: Add new | M42: By AI | N42: Manual | O42: Untested | T42: Untested
A43: TC_TT_SC_015 | B43: MH Checkout | C43: US-24 | D43: Checkout - Payment | E43: Phương thức thanh toán: Ví MoMo (mặc định) | F43: ✅ Positive | G43: **🟠 P1** | I43: 1. Mở checkout 2. Quan sát phần payment | J43: Hiển thị: 'Ví MoMo' với logo MoMo (bg-[#a50064]). Radio checked mặc định. Badge ✓ xanh. Text: 'Thanh toán qua ví điện tử MoMo' | L43: Add new | M43: By AI | N43: Manual | O43: Untested | T43: Untested
A44: TC_TT_SC_012 | B44: MH Checkout | C44: US-23 | D44: Checkout - Pricing | E44: Phí giao hàng = 30k (gạch bỏ) + Freeship + Giảm 20k | F44: ✅ Positive | G44: **🟠 P1** | I44: 1. Mở checkout 2. Quan sát phần pricing | J44: Hiển thị: 'Phí giao hàng' = 30.000đ (gạch bỏ line-through). Dòng xanh: 'Ưu đãi Freeship + Giảm 20k' = −50.000đ (SHIPPING_FEE + FLASH_DISCOUNT) | L44: Add new | M44: By AI | N44: Manual | O44: Untested | T44: Untested
A45: TC_TT_SC_013 | B45: MH Checkout | C45: US-23 | D45: Checkout - Promo | E45: Mã TRYONIC10 → giảm 10% trên checkout | F45: ✅ Positive | G45: **🟠 P1** | I45: 1. Click 'Nhập mã khuyến mại (nếu có)' 2. Nhập 'TRYONIC10' 3. Click 'Áp dụng' | J45: Mã áp dụng thành công: 'Mã TRYONIC10 (−10%)'. Tổng thanh toán giảm. Nút X để xóa mã | L45: Add new | M45: By AI | N45: Manual | O45: Untested | T45: Untested
... A69: TC_CKM_F_007 | B69: MH Checkout Modal | C69: US-CKM-02 | D69: Checkout Modal - Back Step | E69: CheckoutModal: Nút '← Quay lại' giữa steps | F69: ✅ Positive | G69: **🟠 P1** | I69: 1. Step 2 → Click '← Quay lại' | J69: Quay về Step 1, form data giữ nguyên | L69: Add new | M69: By AI | N69: Manual | O69: Untested | T69: Untested

Sheet LOGIN
A1: TC_ID | B1: Screen | C1: US_Mapping | D1: Module | E1: Title | F1: Type | G1: Priority | H1: Pre-condition | I1: Steps | J1: Expected Result | K1: Actual Result | L1: Action Type | M1: Create TCs Type | N1: Execution Type | O1: Result_R1 | P1: Test Date_R1 | Q1: Tester_R1 | R1: Bug ID_R1 | S1: Bug Desc_R1 | T1: Result_R2 | U1: Test Date_R2 | V1: Tester_R2 | W1: Bug ID_R2 | X1: Bug Desc_R2 | Y1: Evidence | Z1: Notes | AA1: Review_Manual (Feedback)
A2: 📌 UI/UX
A3: TC_ACC_UI_817 | B3: MH Đăng nhập | C3: Global | D3: Responsive & Zoom | E3: Màn hình Account: Browser Zoom In/Out (50% - 200%) giữ nguyên layout | F3: 🎨 UI/UX | G3: **🟠 P1** | I3: 1. Truy cập trang Account. 2. Nhấn Ctrl/Cmd + [+] để Zoom In 200%. 3. Nhấn Ctrl/Cmd + [-] để Zoom Out 50%. 4. Cuộn và quan sát toàn màn hình. | J3: Text/SVG luôn sắc nét, không bị vỡ hạt (pixelated). Bố cục (Layout) thu phóng đúng tỷ lệ, không rớt dòng bậy bạ, không che lấp button quan trọng. | L3: Add new | M3: By AI | N3: Manual | O3: Untested | T3: Untested
A4: TC_LOG_UI_803 | B4: MH Đăng nhập | C4: Global | D4: Responsive & Zoom | E4: Màn hình Login: Browser Zoom In/Out (50% - 200%) giữ nguyên layout | F4: 🎨 UI/UX | G4: **🟠 P1** | I4: 1. Truy cập trang Login. 2. Nhấn Ctrl/Cmd + [+] để Zoom In 200%. 3. Nhấn Ctrl/Cmd + [-] để Zoom Out 50%. 4. Cuộn và quan sát toàn màn hình. | J4: Text/SVG luôn sắc nét, không bị vỡ hạt (pixelated). Bố cục (Layout) thu phóng đúng tỷ lệ, không rớt dòng bậy bạ, không che lấp button quan trọng. | L4: Add new | M4: By AI | N4: Manual | O4: Untested | T4: Untested
A5: TC_REG_UI_801 | B5: MH Đăng nhập | C5: Global | D5: Responsive & Zoom | E5: Màn hình Registration: Browser Zoom In/Out (50% - 200%) giữ nguyên layout | F5: 🎨 UI/UX | G5: **🟠 P1** | I5: 1. Truy cập trang Registration. 2. Nhấn Ctrl/Cmd + [+] để Zoom In 200%. 3. Nhấn Ctrl/Cmd + [-] để Zoom Out 50%. 4. Cuộn và quan sát toàn màn hình. | J5: Text/SVG luôn sắc nét, không bị vỡ hạt (pixelated). Bố cục (Layout) thu phóng đúng tỷ lệ, không rớt dòng bậy bạ, không che lấp button quan trọng. | L5: Add new | M5: By AI | N5: Manual | O5: Untested | T5: Untested
A6: TC_ACC_UI_853 | B6: MH Đăng nhập | C6: Global | D6: Responsive (Android Tablet) | E6: Màn hình Account: Responsive trên Android Tablet (Chrome, Dọc - Portrait) | F6: 🎨 UI/UX | G6: **🟠 P1** | I6: 1. Truy cập trang Account trên Tablet Android ở chế độ cầm dọc (Portrait). 2. Thao tác trên giao diện. | J6: Giao diện hoạt động trơn tru tương tự iPad, icon và text scale đúng chuẩn tỉ lệ (không quá bé hoặc quá khổng lồ). | L6: Add new | M6: By AI | N6: Manual | O6: Untested | T6: Untested
A7: TC_LOG_UI_818 | B7: MH Đăng nhập | C7: Global | D7: Responsive (Android Tablet) | E7: Màn hình Login: Responsive trên Android Tablet (Chrome, Dọc - Portrait) | F7: 🎨 UI/UX | G7: **🟠 P1** | I7: 1. Truy cập trang Login trên Tablet Android ở chế độ cầm dọc (Portrait). 2. Thao tác trên giao diện. | J7: Giao diện hoạt động trơn tru tương tự iPad, icon và text scale đúng chuẩn tỉ lệ (không quá bé hoặc quá khổng lồ). | L7: Add new | M7: By AI | N7: Manual | O7: Untested | T7: Untested
A8: TC_REG_UI_813 | B8: MH Đăng nhập | C8: Global | D8: Responsive (Android Tablet) | E8: Màn hình Registration: Responsive trên Android Tablet (Chrome, Dọc - Portrait) | F8: 🎨 UI/UX | G8: **🟠 P1** | I8: 1. Truy cập trang Registration trên Tablet Android ở chế độ cầm dọc (Portrait). 2. Thao tác trên giao diện. | J8: Giao diện hoạt động trơn tru tương tự iPad, icon và text scale đúng chuẩn tỉ lệ (không quá bé hoặc quá khổng lồ). | L8: Add new | M8: By AI | N8: Manual | O8: Untested | T8: Untested
A9: TC_ACC_UI_851 | B9: MH Đăng nhập | C9: Global | D9: Responsive (Android) | E9: Màn hình Account: Responsive trên Android Phone (Chrome, Dọc - Portrait) | F9: 🎨 UI/UX | G9: **🔴 P0** | I9: 1. Truy cập trang Account trên điện thoại Android chế độ cầm dọc (Portrait). 2. Cuộn lên/xuống toàn bộ trang. 3. Focus vào các input (bàn phím ảo hiện lên). | J9: Bố cục hoàn toàn responsive (tương tự iPhone). Đảm bảo thanh bar dưới cùng của trình duyệt Android hoặc bàn phím ảo không che khuất các nút CTA quan trọng. Màn hình không bị giật/nháy (flicker). | L9: Add new | M9: By AI | N9: Manual | O9: Untested | T9: Untested
A10: TC_LOG_UI_816 | B10: MH Đăng nhập | C10: Global | D10: Responsive (Android) | E10: Màn hình Login: Responsive trên Android Phone (Chrome, Dọc - Portrait) | F10: 🎨 UI/UX | G10: **🔴 P0** | I10: 1. Truy cập trang Login trên điện thoại Android chế độ cầm dọc (Portrait). 2. Cuộn lên/xuống toàn bộ trang. 3. Focus vào các input (bàn phím ảo hiện lên). | J10: Bố cục hoàn toàn responsive (tương tự iPhone). Đảm bảo thanh bar dưới cùng của trình duyệt Android hoặc bàn phím ảo không che khuất các nút CTA quan trọng. Màn hình không bị giật/nháy (flicker). | L10: Add new | M10: By AI | N10: Manual | O10: Untested | T10: Untested
A11: TC_REG_UI_811 | B11: MH Đăng nhập | C11: Global | D11: Responsive (Android) | E11: Màn hình Registration: Responsive trên Android Phone (Chrome, Dọc - Portrait) | F11: 🎨 UI/UX | G11: **🔴 P0** | I11: 1. Truy cập trang Registration trên điện thoại Android chế độ cầm dọc (Portrait). 2. Cuộn lên/xuống toàn bộ trang. 3. Focus vào các input (bàn phím ảo hiện lên). | J11: Bố cục hoàn toàn responsive (tương tự iPhone). Đảm bảo thanh bar dưới cùng của trình duyệt Android hoặc bàn phím ảo không che khuất các nút CTA quan trọng. Màn hình không bị giật/nháy (flicker). | L11: Add new | M11: By AI | N11: Manual | O11: Untested | T11: Untested
A12: TC_ACC_UI_854 | B12: MH Đăng nhập | C12: Global | D12: Responsive (Landscape) | E12: Màn hình Account: Responsive chế độ Xoay Ngang (Landscape - Điện thoại/Tablet) | F12: 🎨 UI/UX | G12: **🔴 P0** | I12: 1. Từ trạng thái dọc, xoay ngang thiết bị di động (Landscape). 2. Đảm bảo tính năng xoay màn hình của hệ điều hành được bật. 3. Quan sát quá trình chuyển đổi giao diện. | J12: UI tự động sắp xếp lại chiều ngang phù hợp. Ở điện thoại, Sticky Footer/Header không chiếm quá nhiều không gian theo chiều dọc (để lại đủ không gian hiển thị nội dung). Không bị lủng layout trong lúc/sau khi xoay. | L12: Add new | M12: By AI | N12: Manual | O12: Untested | T12: Untested
A13: TC_LOG_UI_819 | B13: MH Đăng nhập | C13: Global | D13: Responsive (Landscape) | E13: Màn hình Login: Responsive chế độ Xoay Ngang (Landscape - Điện thoại/Tablet) | F13: 🎨 UI/UX | G13: **🔴 P0** | I13: 1. Từ trạng thái dọc, xoay ngang thiết bị di động (Landscape). 2. Đảm bảo tính năng xoay màn hình của hệ điều hành được bật. 3. Quan sát quá trình chuyển đổi giao diện. | J13: UI tự động sắp xếp lại chiều ngang phù hợp. Ở điện thoại, Sticky Footer/Header không chiếm quá nhiều không gian theo chiều dọc (để lại đủ không gian hiển thị nội dung). Không bị lủng layout trong lúc/sau khi xoay. | L13: Add new | M13: By AI | N13: Manual | O13: Untested | T13: Untested
A14: TC_REG_UI_814 | B14: MH Đăng nhập | C14: Global | D14: Responsive (Landscape) | E14: Màn hình Registration: Responsive chế độ Xoay Ngang (Landscape - Điện thoại/Tablet) | F14: 🎨 UI/UX | G14: **🔴 P0** | I14: 1. Từ trạng thái dọc, xoay ngang thiết bị di động (Landscape). 2. Đảm bảo tính năng xoay màn hình của hệ điều hành được bật. 3. Quan sát quá trình chuyển đổi giao diện. | J14: UI tự động sắp xếp lại chiều ngang phù hợp. Ở điện thoại, Sticky Footer/Header không chiếm quá nhiều không gian theo chiều dọc (để lại đủ không gian hiển thị nội dung). Không bị lủng layout trong lúc/sau khi xoay. | L14: Add new | M14: By AI | N14: Manual | O14: Untested | T14: Untested
... A52: TC_ADDR_UI_005 | B52: MH Profile - Địa chỉ | C52: US-ADDR-01 | D52: Address Picker - Form | E52: AddressPicker: Form thêm/sửa hiển thị inline | F52: 🎨 UI/UX | G52: **🟠 P1** | I52: 1. Click 'Thêm địa chỉ mới' 2. Quan sát form | J52: Form inline: Label (Nhà/Công ty/Khác buttons), Họ tên*, SĐT*, Email, 3 dropdowns Tỉnh/Quận/Phường, Địa chỉ chi tiết*, nút Lưu + Hủy | L52: Add new | M52: By AI | N52: Manual | O52: Untested | T52: Untested
A53: 📌 Validation
A54: TC_AUTH_018 | B54: MH Đăng nhập | C54: US-03 | D54: Đăng nhập - Login | E54: Đăng nhập sai password | F54: ⚠️ Negative | G54: **🔴 P0** | I54: 1. Truy cập vào trang 2. Nhập email: user@test.com 3. Nhập password: wrongpass 4. Click 'Đăng nhập' | J54: Hiển thị: 'Email hoặc mật khẩu không đúng'. Không tiết lộ email tồn tại hay không | L54: Add new | M54: By AI | N54: Manual | O54: Untested | T54: Untested
A55: TC_AUTH_019 | B55: MH Đăng nhập | C55: US-03 | D55: Đăng nhập - Login | E55: Đăng nhập email chưa verify | F55: ⚠️ Negative | G55: **🔴 P0** | I55: 1. Truy cập vào trang 2. Nhập email/pass đúng 3. Click 'Đăng nhập' | J55: Hiển thị: 'Vui lòng xác thực email trước khi đăng nhập'. Link resend verify | L55: Add new | M55: By AI | N55: Manual | O55: Untested | T55: Untested
A56: TC_AUTH_020 | B56: MH Đăng nhập | C56: US-03 | D56: Đăng nhập - Login | E56: Đăng nhập email không tồn tại | F56: ⚠️ Negative | G56: **🔴 P0** | I56: 1. Truy cập vào trang 2. Nhập email: ghost@test.com 3. Nhập password bất kỳ 4. Click 'Đăng nhập' | J56: Hiển thị: 'Email hoặc mật khẩu không đúng' (thông báo chung, không tiết lộ) | L56: Add new | M56: By AI | N56: Manual | O56: Untested | T56: Untested
A57: TC_AUTH_021 | B57: MH Đăng nhập | C57: US-03 | D57: Đăng nhập - Login | E57: Đăng nhập bỏ trống cả Email và Mật khẩu | F57: ⚠️ Negative | G57: **🔴 P0** | I57: 1. Truy cập vào trang 2. Không nhập gì 3. Click 'Đăng nhập' | J57: Hiển thị inline error: 'Vui lòng nhập email' + 'Vui lòng nhập mật khẩu' | L57: Add new | M57: By AI | N57: Manual | O57: Untested | T57: Untested
A58: TC_AUTH_022 | B58: MH Đăng nhập | C58: US-03 | D58: Đăng nhập - Login | E58: Đăng nhập bỏ trống Password | F58: ⚠️ Negative | G58: **🔴 P0** | I58: 1. Truy cập vào trang 2. Nhập email: user@test.com 3. Bỏ trống Mật khẩu 4. Click 'Đăng nhập' | J58: Hiển thị inline error dưới field Mật khẩu | L58: Add new | M58: By AI | N58: Manual | O58: Untested | T58: Untested
A59: TC_AUTH_013 | B59: MH Đăng nhập | C59: US-02 | D59: Đăng nhập - OAuth | E59: Google OAuth - user deny permission | F59: ⚠️ Negative | G59: **🟠 P1** | I59: 1. Truy cập vào trang 2. Click 'Tiếp tục với Google' 3. Cancel ở Google consent screen | J59: Redirect về trang Login. Hiển thị: 'Đăng nhập bị hủy'. Trang login hiện lại đầy đủ | L59: Add new | M59: By AI | N59: Manual | O59: Untested | T59: Untested
A60: TC_AUTH_016 | B60: MH Đăng nhập | C60: US-02b | D60: Đăng nhập - OAuth | E60: Facebook OAuth deny permission | F60: ⚠️ Negative | G60: **🟠 P1** | I60: 1. Truy cập vào trang 2. Click 'Tiếp tục với Facebook' 3. Cancel permission | J60: Redirect Login. Hiển thị thông báo hủy | L60: Add new | M60: By AI | N60: Manual | O60: Untested | T60: Untested
A61: TC_AUTH_002 | B61: MH Đăng ký | C61: US-01 | D61: Signup (Email) | E61: Đăng ký pass yếu thiếu số | F61: ⚠️ Negative | G61: **🔴 P0** | I61: 1. Truy cập vào trang 2. Nhập Password: Abcdefgh 3. Click 'Đăng ký' | J61: Hiển thị lỗi: 'Mật khẩu phải có ít nhất 8 ký tự, 1 chữ hoa, 1 số'. Không tạo account | L61: Add new | M61: By AI | N61: Manual | O61: Untested | T61: Untested
A62: TC_AUTH_003 | B62: MH Đăng ký | C62: US-01 | D62: Signup (Email) | E62: Đăng ký pass thiếu chữ hoa | F62: ⚠️ Negative | G62: **🔴 P0** | I62: 1. Truy cập vào trang 2. Nhập Password: test@1234 3. Click 'Đăng ký' | J62: Hiển thị lỗi validation password | L62: Add new | M62: By AI | N62: Manual | O62: Untested | T62: Untested
A63: TC_AUTH_004 | B63: MH Đăng ký | C63: US-01 | D63: Signup (Email) | E63: Đăng ký email đã tồn tại | F63: ⚠️ Negative | G63: **🔴 P0** | I63: 1. Truy cập vào trang 2. Nhập Email: existing@test.com 3. Nhập Password: Test@123 4. Click 'Đăng ký' | J63: Hiển thị lỗi: 'Email đã được sử dụng' | L63: Add new | M63: By AI | N63: Manual | O63: Untested | T63: Untested
A64: TC_AUTH_005 | B64: MH Đăng ký | C64: US-01 | D64: Signup (Email) | E64: Đăng ký email format sai | F64: ⚠️ Negative | G64: **🔴 P0** | I64: 1. Truy cập vào trang 2. Nhập Email: invalid-email 3. Click 'Đăng ký' | J64: Hiển thị lỗi: 'Email không hợp lệ' | L64: Add new | M64: By AI | N64: Manual | O64: Untested | T64: Untested
A65: TC_AUTH_006 | B65: MH Đăng ký | C65: US-01 | D65: Signup (Email) | E65: Đăng ký bỏ trống tất cả field | F65: ⚠️ Negative | G65: **🔴 P0** | I65: 1. Truy cập vào trang 2. Không nhập gì 3. Click 'Đăng ký' | J65: Hiển thị inline error cho tất cả required fields | L65: Add new | M65: By AI | N65: Manual | O65: Untested | T65: Untested
... A75: TC_ADDR_V_003 | B75: MH Profile - Địa chỉ | C75: US-ADDR-03 | D75: Address Picker - Delete Last | E75: AddressPicker: Xóa khi chỉ còn 1 | F75: ⚠️ Negative | G75: **🟠 P1** | I75: 1. Xóa đến còn 1 địa chỉ 2. Quan sát nút Trash | J75: Nút Trash2 ẩn đi (addresses.length > 1 check). Không cho xóa hết | L75: Add new | M75: By AI | N75: Manual | O75: Untested | T75: Untested
A76: 📌 Functional
A77: TC_AUTH_017 | B77: MH Đăng nhập | C77: US-03 | D77: Đăng nhập - Login | E77: Đăng nhập email/pass đúng | F77: ✅ Positive | G77: **🔴 P0** | I77: 1. Truy cập vào trang 2. Mở /login 3. Nhập email: user@test.com vào field Email (placeholder: 'example@email.com') 4. Nhập password: Test@123 vào field Mật khẩu 5. Click button 'Đăng nhập' (purple) | J77: Redirect Dashboard. Header hiển thị tên user. Session tạo | L77: Add new | M77: By AI | N77: Manual | O77: Untested | T77: Untested
A78: TC_AUTH_011 | B78: MH Đăng nhập | C78: US-02 | D78: Đăng nhập - OAuth | E78: Click 'Tiếp tục với Google' thành công | F78: ✅ Positive | G78: **🔴 P0** | I78: 1. Truy cập vào trang 2. Mở /login 3. Click button 'Tiếp tục với Google' 4. Chọn tài khoản Google 5. Authorize permissions | J78: Redirect về Dashboard. Header hiển thị tên + avatar từ Google. Session tạo 24h | L78: Add new | M78: By AI | N78: Manual | O78: Untested | T78: Untested
A79: TC_AUTH_012 | B79: MH Đăng nhập | C79: US-02 | D79: Đăng nhập - OAuth | E79: Google OAuth lần đầu - auto tạo account | F79: ✅ Positive | G79: **🔴 P0** | I79: 1. Truy cập vào trang 2. Click 'Tiếp tục với Google' 3. Chọn tài khoản mới | J79: Tạo account mới. DB: auth_provider=google. Redirect Dashboard | L79: Add new | M79: By AI | N79: Manual | O79: Untested | T79: Untested
A80: TC_AUTH_014 | B80: MH Đăng nhập | C80: US-02 | D80: Đăng nhập - OAuth | E80: Google OAuth - email trùng account email/pass | F80: ✅ Edge Case | G80: **🟠 P1** | I80: 1. Truy cập vào trang 2. Click 'Tiếp tục với Google' với email đã có | J80: Liên kết account hoặc hiển thị lỗi trùng email (tùy BR) | L80: Add new | M80: By AI | N80: Manual | O80: Untested | T80: Untested
A81: TC_AUTH_015 | B81: MH Đăng nhập | C81: US-02b | D81: Đăng nhập - OAuth | E81: Click 'Tiếp tục với Facebook' thành công | F81: ✅ Positive | G81: **🟠 P1** | I81: 1. Truy cập vào trang 2. Click button 'Tiếp tục với Facebook' 3. Authorize | J81: Đăng nhập thành công. Redirect Dashboard. Hiển thị tên từ FB | L81: Add new | M81: By AI | N81: Manual | O81: Untested | T81: Untested
A82: TC_AUTH_001 | B82: MH Đăng ký | C82: US-01 | D82: Signup (Email) | E82: Đăng ký email/password hợp lệ | F82: ✅ Positive | G82: **🔴 P0** | I82: 1. Truy cập vào trang 2. Mở trang /signup 3. Nhập Name: Nguyễn Văn A 4. Nhập Email: newuser@test.com 5. Nhập Password: Test@123 6. Click 'Đăng ký' | J82: Hiển thị 'Đăng ký thành công'. Gửi email verify đến newuser@test.com. DB tạo record users.status=pending | L82: Add new | M82: By AI | N82: Manual | O82: Untested | T82: Untested
A83: TC_AUTH_009 | B83: MH Đăng ký | C83: US-01 | D83: Signup (Email) | E83: Email chứa ký tự đặc biệt hợp lệ | F83: ✅ Edge Case | G83: **🟢 P2** | I83: 1. Truy cập vào trang 2. Nhập Email: user+tag@test.com 3. Hoàn tất form 4. Click 'Đăng ký' | J83: Đăng ký thành công. Email có dấu + được chấp nhận | L83: Add new | M83: By AI | N83: Manual | O83: Untested | T83: Untested
A84: TC_AUTH_050 | B84: MH Đăng ký | C84: US-02b | D84: Signup (Facebook) | E84: Đăng ký bằng Facebook thành công | F84: ✅ Positive | G84: **🔴 P0** | I84: 1. Truy cập vào trang 2. Click 'Đăng ký với Facebook' 3. Xác thực Facebook App | J84: Hệ thống tạo tài khoản mới ngay lập tức. Redirect Dashboard. Hiển thị thông báo chào mừng | L84: Add new | M84: By AI | N84: Manual | O84: Untested | T84: Untested
A85: TC_AUTH_049 | B85: MH Đăng ký | C85: US-02 | D85: Signup (Google) | E85: Đăng ký bằng Google thành công | F85: ✅ Positive | G85: **🔴 P0** | I85: 1. Truy cập vào trang 2. Click 'Đăng ký với Google' 3. Xác thực màn hình Consent | J85: Hệ thống tạo tài khoản mới. DB: auth_provider=google. Redirect Dashboard | L85: Add new | M85: By AI | N85: Manual | O85: Untested | T85: Untested
A86: TC_AUTH_046 | B86: MH Tài khoản | C86: US-05 | D86: Hồ sơ - Account | E86: Cập nhật profile thành công | F86: ✅ Positive | G86: **🟠 P1** | I86: 1. Truy cập vào trang 2. Vào Profile 3. Sửa Phone: 0901234567 4. Upload Avatar 5. Click Save | J86: Data lưu DB. Trang hiển thị data mới | L86: Add new | M86: By AI | N86: Manual | O86: Untested | T86: Untested
A87: TC_AUTH_037 | B87: MH Guest | C87: US-03b | D87: Guest - Browser | E87: Guest vào Editor thiết kế bình thường | F87: ✅ Positive | G87: **🔴 P0** | I87: 1. Truy cập vào trang 2. Truy cập /editor không login 3. Add artwork/text 4. Thao tác drag/resize | J87: Cho phép thao tác bình thường. Data lưu localStorage | L87: Add new | M87: By AI | N87: Manual | O87: Untested | T87: Untested
A88: TC_AUTH_038 | B88: MH Guest | C88: US-03b | D88: Guest - Browser | E88: Guest data persist khi refresh | F88: ✅ Positive | G88: **🟠 P1** | I88: 1. Truy cập vào trang 2. Tạo design 3. Refresh browser | J88: Design vẫn còn từ localStorage | L88: Add new | M88: By AI | N88: Manual | O88: Untested | T88: Untested
... A103: TC_ADDR_F_007 | B103: MH Profile - Địa chỉ | C103: US-ADDR-02 | D103: Address Picker - Seed Data | E103: AddressPicker: Seed data lần đầu | F103: ✅ Positive | G103: **🟢 P2** | I103: 1. Xóa tryonic_addresses từ localStorage 2. Refresh | J103: 2 addresses mẫu xuất hiện: 'Nhà' (default) + 'Công ty'. localStorage ghi SEED_ADDRESSES | L103: Add new | M103: By AI | N103: Manual | O103: Untested | T103: Untested
A104: 📌 Security
A105: TC_AUTH_023 | B105: MH Đăng nhập | C105: US-03 | D105: Đăng nhập - Security | E105: Login sai 5 lần liên tiếp - lock account | F105: ⚠️ Negative | G105: **🔴 P0** | I105: 1. Truy cập vào trang 2. Nhập sai password 5 lần liên tiếp 3. Quan sát sau lần thứ 5 | J105: Account bị lock 15 phút. Hiển thị: 'Tài khoản bị khóa tạm thời. Vui lòng thử lại sau 15 phút' | L105: Add new | M105: By AI | N105: Manual | O105: Untested | T105: Untested
A106: TC_AUTH_024 | B106: MH Đăng nhập | C106: US-03 | D106: Đăng nhập - Security | E106: Login sai lần 4 - cảnh báo | F106: ⚠️ Negative | G106: **🟠 P1** | I106: 1. Truy cập vào trang 2. Nhập sai password lần thứ 4 3. Xem thông báo | J106: Hiển thị cảnh báo: 'Còn 1 lần nữa tài khoản sẽ bị khóa' | L106: Add new | M106: By AI | N106: Manual | O106: Untested | T106: Untested
A107: TC_AUTH_025 | B107: MH Đăng nhập | C107: US-03 | D107: Đăng nhập - Security | E107: Counter reset sau login thành công | F107: ✅ Positive | G107: **🟠 P1** | I107: 1. Truy cập vào trang 2. Đăng nhập đúng 3. Logout 4. Sai 1 lần 5. Kiểm tra counter | J107: Counter về 0 sau login thành công | L107: Add new | M107: By AI | N107: Manual | O107: Untested | T107: Untested
A108: TC_AUTH_026 | B108: MH Đăng nhập | C108: US-03 | D108: Đăng nhập - Security | E108: Lock per-account, không per-IP | F108: ✅ Boundary | G108: **🟠 P1** | I108: 1. Truy cập vào trang 2. Máy A sai 3 lần account X 3. Máy B sai 2 lần account X | J108: Account X bị lock dù login từ nhiều IP khác nhau | L108: Add new | M108: By AI | N108: Manual | O108: Untested | T108: Untested
A109: TC_AUTH_027 | B109: MH Đăng nhập | C109: US-03 | D109: Đăng nhập - Security | E109: Bypass OAuth khi account bị lock | F109: ✅ Edge Case | G109: **🟠 P1** | I109: 1. Truy cập vào trang 2. Account bị lock 3. Thử login bằng 'Tiếp tục với Google' cùng email | J109: Xử lý nhất quán: block hoặc cho phép OAuth. Không bypass mặc định | L109: Add new | M109: By AI | N109: Manual | O109: Untested | T109: Untested
A110: TC_AUTH_028 | B110: MH Đăng nhập | C110: US-03 | D110: Đăng nhập - Security | E110: Lock message không tiết lộ thông tin | F110: ⚠️ Negative | G110: **🟠 P1** | I110: 1. Truy cập vào trang 2. Nhập email không tồn tại sai pass 5+ lần | J110: Không hiển thị 'Email không tồn tại'. Thông báo chung. Counter không tăng cho email không tồn tại | L110: Add new | M110: By AI | N110: Manual | O110: Untested | T110: Untested
A111: TC_AUTH_029 | B111: MH Đăng nhập | C111: US-03 | D111: Đăng nhập - Security | E111: Admin unlock account trước 15 phút | F111: ✅ Positive | G111: **🟠 P1** | I111: 1. Truy cập vào trang 2. Admin vào portal 3. Unlock tài khoản 4. User thử login lại | J111: Mở khóa ngay. User login thành công | L111: Add new | M111: By AI | N111: Manual | O111: Untested | T111: Untested
A112: TC_AUTH_030 | B112: MH Đăng nhập | C112: US-03 | D112: Đăng nhập - Security | E112: Concurrent login attempts (race condition) | F112: ✅ Boundary | G112: **🟠 P1** | I112: 1. Truy cập vào trang 2. Gửi đồng thời 10 request login sai 3. Kiểm tra lock | J112: Không bị race condition. Account lock sau đúng 5 lần thực sự | L112: Add new | M112: By AI | N112: Manual | O112: Untested | T112: Untested
A113: TC_AUTH_031 | B113: MH Đăng nhập | C113: US-03 | D113: Đăng nhập - Security | E113: Lock persist sau clear cookies | F113: ✅ Edge Case | G113: **🟠 P1** | I113: 1. Truy cập vào trang 2. Clear cookie/localStorage 3. Sai thêm vào account đó | J113: Vẫn bị lock. Lock server-side, không client-side | L113: Add new | M113: By AI | N113: Manual | O113: Untested | T113: Untested
A114: TC_AUTH_032 | B114: MH Đăng nhập | C114: US-03 | D114: Đăng nhập - Security | E114: Lock time chính xác 15 phút | F114: ✅ Boundary | G114: **🟠 P1** | I114: 1. Truy cập vào trang 2. Thử login sau 14:50 3. Thử login sau 15:00 | J114: 14:50 vẫn lock. 15:00 có thể login | L114: Add new | M114: By AI | N114: Manual | O114: Untested | T114: Untested
A115: TC_AUTH_033 | B115: MH Đăng nhập | C115: US-03 | D115: Đăng nhập - Security | E115: API rate limit POST /api/login | F115: ⚠️ Negative | G115: **🟠 P1** | I115: 1. Truy cập vào trang 2. Gọi POST /api/login sai pass 5+ lần qua API 3. Kiểm tra response | J115: API trả 429 Too Many Requests hoặc lock. Không bypass được qua API | L115: Add new | M115: By AI | N115: Manual | O115: Untested | T115: Untested
A116: TC_AUTH_036 | B116: MH Đăng nhập | C116: US-03 | D116: Đăng nhập - Security | E116: Remember me session 30 ngày | F116: ✅ Positive | G116: **🟠 P1** | I116: 1. Truy cập vào trang 2. Tick 'Remember me' 3. Login thành công 4. Kiểm tra session expiry | J116: Session kéo dài 30 ngày thay vì 24h mặc định | L116: Add new | M116: By AI | N116: Manual | O116: Untested | T116: Untested
... A125: TC_PROF_S_002 | B125: MH Profile | C125: US-PROF-04 | D125: Profile - LocalStorage Tamper | E125: Profile: Sửa localStorage trực tiếp | F125: 🔒 Security | G125: **🟠 P1** | I125: 1. Sửa user_profile trong DevTools 2. Refresh | J125: App handle JSON.parse error gracefully, fallback DEFAULT_PROFILE | L125: Add new | M125: By AI | N125: Manual | O125: Untested | T125: Untested

Sheet MY ORDERS
A1: TC_ID | B1: Screen | C1: US_Mapping | D1: Module | E1: Title | F1: Type | G1: Priority | H1: Pre-condition | I1: Steps | J1: Expected Result | K1: Actual Result | L1: Action Type | M1: Create TCs Type | N1: Execution Type | O1: Result_R1 | P1: Test Date_R1 | Q1: Tester_R1 | R1: Bug ID_R1 | S1: Bug Desc_R1 | T1: Result_R2 | U1: Test Date_R2 | V1: Tester_R2 | W1: Bug ID_R2 | X1: Bug Desc_R2 | Y1: Evidence | Z1: Notes | AA1: Review_Manual (Feedback)
A2: 📌 UI/UX
A3: TC_MO_UI_004 | B3: MH My Orders | C3: US-26 | D3: My Orders - Card | E3: Order card hiển thị thông tin | F3: 🎨 UI/UX | G3: **🟠 P1** | I3: 1. Mở My Orders (có ≥1 đơn) 2. Quan sát card đơn hàng | J3: Card hiển thị: mã đơn (#TRY-XXX), ngày đặt, status badge (màu theo trạng thái), preview items (max 2), tổng tiền. Có nút 'Chi tiết' | L3: Add new | M3: By AI | N3: Manual | O3: Untested | T3: Untested
A4: TC_MO_UI_005 | B4: MH My Orders | C4: US-26 | D4: My Orders - Empty | E4: Empty state khi chưa có đơn hàng | F4: 🎨 UI/UX | G4: **🟢 P2** | I4: 1. Mở My Orders (user mới, chưa đặt đơn) 2. Quan sát nội dung | J4: Hiển thị: 'Chưa có đơn hàng nào' + nút CTA 'Thiết kế ngay' → navigate về Design Studio | L4: Add new | M4: By AI | N4: Manual | O4: Untested | T4: Untested
A5: TC_MO_UI_001 | B5: MH My Orders | C5: US-26 | D5: My Orders - Header | E5: MH My Orders: Header hiển thị đầy đủ | F5: 🎨 UI/UX | G5: **🟠 P1** | I5: 1. Đăng nhập → Click User avatar → 'Đơn hàng của tôi' 2. Quan sát header | J5: Header hiển thị: nút '← Studio' quay về studio, tiêu đề 'Đơn hàng của tôi' + count badge (số đơn hàng) | L5: Add new | M5: By AI | N5: Manual | O5: Untested | T5: Untested
A6: TC_MO_UI_006 | B6: MH My Orders | C6: US-26 | D6: My Orders - Loading | E6: Loading state (skeleton) | F6: 🎨 UI/UX | G6: **🟢 P2** | I6: 1. Truy cập My Orders (mạng chậm) 2. Quan sát loading | J6: Skeleton animation (pulse blocks) thay cho cards đơn hàng. Không blank screen | L6: Add new | M6: By AI | N6: Manual | O6: Untested | T6: Untested
A7: TC_MO_UI_860 | B7: MH My Orders | C7: Global | D7: Responsive & Zoom | E7: MH My Orders: Browser Zoom (50%-200%) | F7: 🎨 UI/UX | G7: **🟠 P1** | I7: 1. Truy cập My Orders 2. Zoom In 200% / Zoom Out 50% | J7: Layout giữ nguyên. Tabs wrap xuống hàng nếu cần. Cards vẫn hiển thị đầy đủ | L7: Add new | M7: By AI | N7: Manual | O7: Untested | T7: Untested
A8: TC_MO_UI_864 | B8: MH My Orders | C8: Global | D8: Responsive (Android Tablet) | E8: MH My Orders: Responsive Android Tablet | F8: 🎨 UI/UX | G8: **🟠 P1** | I8: 1. Truy cập My Orders trên Tablet Android | J8: Tương tự iPad | L8: Add new | M8: By AI | N8: Manual | O8: Untested | T8: Untested
A9: TC_MO_UI_862 | B9: MH My Orders | C9: Global | D9: Responsive (Android) | E9: MH My Orders: Responsive Android Phone (Portrait) | F9: 🎨 UI/UX | G9: **🔴 P0** | I9: 1. Truy cập My Orders trên Android Portrait | J9: Tương tự iPhone. Không thanh cuộn ngang thừa | L9: Add new | M9: By AI | N9: Manual | O9: Untested | T9: Untested
A10: TC_MO_UI_865 | B10: MH My Orders | C10: Global | D10: Responsive (Landscape) | E10: MH My Orders: Responsive Landscape | F10: 🎨 UI/UX | G10: **🔴 P0** | I10: 1. Xoay ngang thiết bị | J10: UI tự sắp xếp phù hợp. Tabs vẫn hiển thị | L10: Add new | M10: By AI | N10: Manual | O10: Untested | T10: Untested
A11: TC_MO_UI_863 | B11: MH My Orders | C11: Global | D11: Responsive (iPad) | E11: MH My Orders: Responsive iPad (Portrait) | F11: 🎨 UI/UX | G11: **🟠 P1** | I11: 1. Truy cập My Orders trên iPad Portrait | J11: Cards có thể 2 cột hoặc 1 cột hợp lý. Tabs hiển thị đủ trên 1 hàng | L11: Add new | M11: By AI | N11: Manual | O11: Untested | T11: Untested
A12: TC_MO_UI_861 | B12: MH My Orders | C12: Global | D12: Responsive (iPhone) | E12: MH My Orders: Responsive iPhone (Portrait) | F12: 🎨 UI/UX | G12: **🔴 P0** | I12: 1. Truy cập My Orders trên iPhone Portrait | J12: Tabs scroll ngang hoặc wrap. Cards full-width stacking. Nút Chi tiết dễ tap (≥44px) | L12: Add new | M12: By AI | N12: Manual | O12: Untested | T12: Untested
A13: TC_MO_UI_002 | B13: MH My Orders - Tìm | C13: US-26 | D13: My Orders - Search | E13: Ô tìm kiếm đơn hàng hiển thị | F13: 🎨 UI/UX | G13: **🟠 P1** | I13: 1. Mở My Orders 2. Quan sát ô tìm kiếm | J13: Placeholder: 'Tìm theo mã đơn hoặc tên sản phẩm...'. Icon search bên trái. Bo tròn, full-width | L13: Add new | M13: By AI | N13: Manual | O13: Untested | T13: Untested
A14: TC_MO_UI_003 | B14: MH My Orders - Filter | C14: US-26 | D14: My Orders - Status Tabs | E14: 7 status tabs hiển thị đầy đủ | F14: 🎨 UI/UX | G14: **🔴 P0** | I14: 1. Mở My Orders 2. Quan sát thanh tab trạng thái | J14: 7 tabs: 'Tất cả', 'Chờ xác nhận', 'Đã xác nhận', 'Đang in', 'Đang giao', 'Đã giao', 'Đã hủy'. Mỗi tab có count badge. Tab active có highlight teal | L14: Add new | M14: By AI | N14: Manual | O14: Untested | T14: Untested
A15: 📌 Validation
A16: TC_MO_V_001 | B16: MH My Orders - Tìm | C16: US-26 | D16: My Orders - Search | E16: Tìm kiếm không có kết quả | F16: ⚠️ Negative | G16: **🟢 P2** | I16: 1. Mở My Orders 2. Nhập 'xyznotexist123' | J16: Hiển thị: 'Không tìm thấy đơn hàng'. Không crash | L16: Add new | M16: By AI | N16: Manual | O16: Untested | T16: Untested
A17: TC_MO_V_002 | B17: MH My Orders - Hủy | C17: US-28 | D17: My Orders - Cancel | E17: Hủy đơn khi trạng thái 'Đang in' | F17: ⚠️ Negative | G17: **🟠 P1** | I17: 1. Mở My Orders 2. Tìm đơn trạng thái 'Đang in' | J17: Nút 'Hủy đơn' ẩn hoặc disabled. Không cho phép hủy đơn đang sản xuất | L17: Add new | M17: By AI | N17: Manual | O17: Untested | T17: Untested
A18: TC_MO_V_003 | B18: MH My Orders - Hủy | C18: US-28 | D18: My Orders - Cancel | E18: Hủy đơn khi trạng thái 'Đã giao' | F18: ⚠️ Negative | G18: **🟠 P1** | I18: 1. Mở My Orders 2. Tìm đơn trạng thái 'Đã giao' | J18: Nút 'Hủy đơn' ẩn. Không cho hủy đơn đã giao | L18: Add new | M18: By AI | N18: Manual | O18: Untested | T18: Untested
A19: 📌 Functional
A20: TC_MO_F_008 | B20: MH My Orders | C20: US-26 | D20: My Orders - Navigate | E20: Click '← Studio' quay về Design Studio | F20: ✅ Positive | G20: **🟢 P2** | I20: 1. Mở My Orders 2. Click nút '← Studio' trên header | J20: Navigate về /studio. Design Studio hiển thị đầy đủ | L20: Add new | M20: By AI | N20: Manual | O20: Untested | T20: Untested
A21: TC_ORD_025 | B21: MH My Orders | C21: US-29 | D21: Re-order | E21: Re-order design cũ | F21: ✅ Positive | G21: **🟠 P1** | I21: 1. Mở My Orders 2. Click 'Đặt lại' 3. Chọn Size/Qty | J21: Tạo đơn mới với cùng design. Vào Cart | L21: Add new | M21: By AI | N21: Manual | O21: Untested | T21: Untested
A22: TC_ORD_026 | B22: MH My Orders | C22: US-29 | D22: Re-order | E22: Re-order sản phẩm đã ngưng bán | F22: ✅ Edge Case | G22: **🟢 P2** | I22: 1. Mở My Orders 2. Click 'Đặt lại' | J22: Hiển thị: 'Sản phẩm này không còn bán'. Không cho re-order | L22: Add new | M22: By AI | N22: Manual | O22: Untested | T22: Untested
A23: TC_MO_F_001 | B23: MH My Orders - Tìm | C23: US-26 | D23: My Orders - Search | E23: Tìm kiếm theo mã đơn | F23: ✅ Positive | G23: **🟠 P1** | I23: 1. Mở My Orders 2. Nhập mã đơn 'TRY-001' vào ô tìm kiếm | J23: Danh sách filter hiển thị chỉ đơn hàng có mã TRY-001. Realtime filtering khi gõ | L23: Add new | M23: By AI | N23: Manual | O23: Untested | T23: Untested
A24: TC_MO_F_002 | B24: MH My Orders - Tìm | C24: US-26 | D24: My Orders - Search | E24: Tìm kiếm theo tên sản phẩm | F24: ✅ Positive | G24: **🟠 P1** | I24: 1. Mở My Orders 2. Nhập 'Premium Cotton' vào ô tìm kiếm | J24: Hiển thị đơn hàng chứa SP 'Premium Cotton' | L24: Add new | M24: By AI | N24: Manual | O24: Untested | T24: Untested
A25: TC_MO_F_003 | B25: MH My Orders - Filter | C25: US-26 | D25: My Orders - Filter | E25: Click tab 'Chờ xác nhận' | F25: ✅ Positive | G25: **🟠 P1** | I25: 1. Mở My Orders 2. Click tab 'Chờ xác nhận' | J25: Chỉ hiển thị đơn hàng có trạng thái 'Chờ xác nhận'. Count badge cập nhật. Tab active highlight | L25: Add new | M25: By AI | N25: Manual | O25: Untested | T25: Untested
A26: TC_MO_F_004 | B26: MH My Orders - Filter | C26: US-26 | D26: My Orders - Filter | E26: Click tab 'Đã giao' | F26: ✅ Positive | G26: **🟠 P1** | I26: 1. Mở My Orders 2. Click tab 'Đã giao' | J26: Chỉ hiển thị đơn hàng đã giao. Count badge đúng | L26: Add new | M26: By AI | N26: Manual | O26: Untested | T26: Untested
A27: TC_MO_F_005 | B27: MH My Orders - Filter | C27: US-26 | D27: My Orders - Filter | E27: Click tab 'Tất cả' hiển thị toàn bộ | F27: ✅ Positive | G27: **🟢 P2** | I27: 1. Đang ở tab filter khác 2. Click 'Tất cả' | J27: Hiển thị toàn bộ đơn hàng. Count badge = tổng đơn | L27: Add new | M27: By AI | N27: Manual | O27: Untested | T27: Untested
A28: TC_MO_F_006 | B28: MH Chi tiết đơn | C28: US-27 | D28: My Orders - Detail | E28: Click 'Chi tiết' mở CustomerOrderDetailModal | F28: ✅ Positive | G28: **🟠 P1** | I28: 1. Mở My Orders 2. Click nút 'Chi tiết' trên 1 đơn hàng | J28: Mở modal chi tiết: mã đơn, trạng thái, timeline, danh sách items (ảnh, tên, màu, size, qty, giá), thông tin giao hàng. Có nút đóng (X) | L28: Add new | M28: By AI | N28: Manual | O28: Untested | T28: Untested
A29: TC_MO_F_007 | B29: MH My Orders - Hủy | C29: US-28 | D29: My Orders - Cancel | E29: Click 'Hủy đơn' khi trạng thái 'Chờ xác nhận' | F29: ✅ Positive | G29: **🟠 P1** | I29: 1. Mở My Orders 2. Tìm đơn trạng thái 'Chờ xác nhận' 3. Click 'Hủy đơn' | J29: Hiển thị confirm dialog: 'Bạn có chắc muốn hủy đơn hàng #TRY-XXX?'. Xác nhận → đơn chuyển sang 'Đã hủy'. Toast 'Đã hủy đơn hàng' | L29: Add new | M29: By AI | N29: Manual | O29: Untested | T29: Untested

Sheet POLICY PAGES
A1: TC_ID | B1: Screen | C1: US_Mapping | D1: Module | E1: Title | F1: Type | G1: Priority | H1: Pre-condition | I1: Steps | J1: Expected Result | K1: Actual Result | L1: Action Type | M1: Create TCs Type | N1: Execution Type | O1: Result_R1 | P1: Test Date_R1 | Q1: Tester_R1 | R1: Bug ID_R1 | S1: Bug Desc_R1 | T1: Result_R2 | U1: Test Date_R2 | V1: Tester_R2 | W1: Bug ID_R2 | X1: Bug Desc_R2 | Y1: Evidence | Z1: Notes | AA1: Review_Manual (Feedback)
A2: 📌 UI/UX
A3: TC_POL_UI_006 | B3: MH Policy | C3: US-HP-04 | D3: Policy - Layout | E3: 'Chính sách khác' grid hiển thị trên mỗi trang | F3: 🎨 UI/UX | G3: **🟢 P2** | I3: 1. Truy cập bất kỳ trang policy 2. Scroll xuống phần 'Chính sách khác' | J3: Hiển thị grid các trang policy liên quan (trừ trang hiện tại). Mỗi card có icon + title. Click navigate đúng | L3: Add new | M3: By AI | N3: Manual | O3: Untested | T3: Untested
A4: TC_POL_UI_001 | B4: Policy - Hướng dẫn | C4: US-HP-04 | D4: Policy - Hướng dẫn mua hàng | E4: Trang hướng dẫn mua hàng hiển thị đầy đủ | F4: 🎨 UI/UX | G4: **🟠 P1** | I4: 1. Truy cập /pages/huong-dan-mua-hang 2. Quan sát nội dung | J4: Hiển thị: header với icon + tiêu đề 'Hướng dẫn mua hàng', nút back, 7 steps: Truy cập → Chọn SP → Tạo Artwork → Chỉnh sửa → Preview → Đặt hàng → Thanh toán. Footer 'Chính sách khác' grid hiển thị | L4: Add new | M4: By AI | N4: Manual | O4: Untested | T4: Untested
A5: TC_POL_UI_002 | B5: Policy - Thanh toán | C5: US-HP-04 | D5: Policy - Thanh toán | E5: Trang chính sách thanh toán hiển thị đầy đủ | F5: 🎨 UI/UX | G5: **🟠 P1** | I5: 1. Truy cập /pages/chinh-sach-thanh-toan 2. Quan sát nội dung | J5: Hiển thị: phương thức MoMo only, thông tin SSL 256-bit, bảng phí giao hàng. Có link 'Chính sách khác' | L5: Add new | M5: By AI | N5: Manual | O5: Untested | T5: Untested
A6: TC_POL_UI_003 | B6: Policy - Vận chuyển | C6: US-HP-04 | D6: Policy - Vận chuyển | E6: Trang chính sách vận chuyển hiển thị đầy đủ | F6: 🎨 UI/UX | G6: **🟠 P1** | I6: 1. Truy cập /pages/chinh-sach-van-chuyen 2. Quan sát nội dung | J6: Hiển thị: Standard 5-7 ngày (miễn phí ≥500K), Express 2-3 ngày (30K). Bảng chi tiết phí | L6: Add new | M6: By AI | N6: Manual | O6: Untested | T6: Untested
A7: TC_POL_UI_004 | B7: Policy - Đổi trả | C7: US-HP-04 | D7: Policy - Đổi trả | E7: Trang chính sách đổi trả hiển thị đầy đủ | F7: 🎨 UI/UX | G7: **🟠 P1** | I7: 1. Truy cập /pages/chinh-sach-doi-tra 2. Quan sát nội dung | J7: Hiển thị: thời hạn 7 ngày, điều kiện đổi trả, quy trình 3 bước. Có icon minh họa | L7: Add new | M7: By AI | N7: Manual | O7: Untested | T7: Untested
A8: TC_POL_UI_005 | B8: Policy - Bảo mật | C8: US-HP-04 | D8: Policy - Bảo mật | E8: Trang bảo mật thông tin hiển thị đầy đủ | F8: 🎨 UI/UX | G8: **🟠 P1** | I8: 1. Truy cập /pages/chinh-sach-bao-mat 2. Quan sát nội dung | J8: Hiển thị: tuân thủ NĐ 13/2023, SSL encryption, bcrypt hashing, chính sách xử lý dữ liệu. Format các section rõ ràng | L8: Add new | M8: By AI | N8: Manual | O8: Untested | T8: Untested
A9: 📌 Validation
A10: TC_POL_V_001 | B10: Policy - Error | C10: US-HP-04 | D10: Policy - Invalid | E10: Truy cập slug không tồn tại | F10: ⚠️ Negative | G10: **🟠 P1** | I10: 1. Truy cập /pages/slug-khong-ton-tai 2. Quan sát trang | J10: Hiển thị error: 'Trang không tồn tại' với nút 'Về trang chủ'. Không crash, không blank | L10: Add new | M10: By AI | N10: Manual | O10: Untested | T10: Untested
A11: 📌 Functional
A12: TC_POL_F_002 | B12: MH Policy | C12: US-HP-04 | D12: Policy - Navigate | E12: Click card 'Chính sách khác' navigate đúng | F12: ✅ Positive | G12: **🟠 P1** | I12: 1. Mở /pages/huong-dan-mua-hang 2. Click card 'Chính sách vận chuyển' trong 'Chính sách khác' | J12: Navigate đến /pages/chinh-sach-van-chuyen. Trang hiển thị đúng | L12: Add new | M12: By AI | N12: Manual | O12: Untested | T12: Untested
A13: TC_POL_F_001 | B13: MH Policy | C13: US-HP-04 | D13: Policy - Navigate | E13: Click 'Về trang chủ' | F13: ✅ Positive | G13: **🟢 P2** | I13: 1. Mở bất kỳ trang policy 2. Click link 'Về trang chủ' | J13: Navigate đến /home. Trang chủ hiển thị | L13: Add new | M13: By AI | N13: Manual | O13: Untested | T13: Untested
A14: TC_POL_F_003 | B14: MH Policy | C14: US-HP-04 | D14: Policy - Navigate | E14: Click nút back trên header | F14: ✅ Positive | G14: **🟢 P2** | I14: 1. Mở trang policy 2. Click nút ← (back) trên header | J14: Quay về trang trước hoặc trang chủ | L14: Add new | M14: By AI | N14: Manual | O14: Untested | T14: Untested

Sheet E2E FLOW — LUỒNG ĐẦY ĐỦ
A1: STT | B1: TC_ID | C1: Tên luồng E2E | D1: Loại luồng | E1: Các bước thực hiện (Full Steps) | F1: Dữ liệu đầu vào | G1: Kết quả mong đợi (cuối luồng) | H1: Độ ưu tiên | I1: Expected_Result | J1: Actual_Result | K1: Thời gian thực thi | L1: Screenshot / Evidence | M1: Ghi chú / Bug | N1: Review_Manual (Feedback)
A2: ✅ HAPPY PATH — LUỒNG CHÍNH
A3: 1 | B3: TC_E2E_001 | C3: Happy Path: Mua ngay — Guest (Không đăng nhập) | D3: Happy Path | E3: 1. Truy cập Home 2. Nhập ý tưởng [Bạn muốn kể gì trên áo?] 3. Chọn phong cách: Tối giản 4. Click [Tạo ngay] → Chuyển sang Design Studio 5. View hộp thoại Try-AI Designer: 3 artwork hiển thị 6. Click chọn 1 artwork → Click [Dùng ảnh này] 7. View [Cài đặt hình ảnh] trên áo 8. Chỉnh Width/Height, Căn giữa 9. Click [Đặt hàng] → Click [Mua ngay] 10. MH Checkout: Nhập địa chỉ nhận hàng, chọn thanh toán COD 11. Click [Thanh toán + Số tiền] 12. MH Đặt hàng thành công: Hiển thị mã đơn 13. Click [Xem đơn hàng] | F3: Ý tưởng: 'Rồng Việt Nam phong cách watercolor' Phong cách: Tối giản Thông tin: Nguyễn Văn A, 0901234567, Q1 TPHCM Thanh toán: COD | G3: Đặt hàng thành công, hiển thị mã đơn, xem được chi tiết đơn hàng | H3: P0
A4: 2 | B4: TC_E2E_002 | C4: Happy Path: Mua ngay — Đã đăng nhập | D4: Happy Path | E4: 1. Đăng nhập tài khoản trước 2. Truy cập Home → Nhập ý tưởng → Chọn phong cách 3. Click [Tạo ngay] → Design Studio 4. View 3 artwork → Chọn 1 → [Dùng ảnh này] 5. Cài đặt hình ảnh: Xóa nền ON, Căn giữa 6. [Đặt hàng] → [Mua ngay] 7. MH Checkout: Thông tin tự động auto-fill từ Profile 8. Kiểm tra auto-fill đúng → Chọn thanh toán 9. Click [Thanh toán] → Thành công 10. Xem đơn hàng | F4: Ý tưởng: 'Mèo galaxy neon' Phong cách: Sáng tạo User đã login Google | G4: Auto-fill đúng thông tin, đặt hàng thành công, xem đơn hàng OK | H4: P0
A5: 3 | B5: TC_E2E_003 | C5: Happy Path: Thêm giỏ hàng → Thanh toán | D5: Happy Path | E5: 1. Home → Nhập ý tưởng → [Tạo ngay] 2. Design Studio → View 3 artwork → [Dùng ảnh này] 3. Cài đặt hình ảnh → Chỉnh sửa OK 4. [Đặt hàng] → Click [Thêm giỏ hàng] 5. Kiểm tra badge giỏ hàng +1, thông báo thành công 6. Mở Giỏ hàng → Kiểm tra sản phẩm 7. Click [Thanh toán ngay] trong giỏ 8. MH Checkout → Nhập thông tin → Thanh toán 9. Đặt hàng thành công → Xem đơn | F5: Ý tưởng: 'Phong cảnh Hội An' Size: L | G5: Sản phẩm vào giỏ, checkout từ giỏ thành công, mã đơn hiển thị | H5: P0
A6: 📂 LUỒNG TỪ THƯ VIỆN MẪU & UPLOAD ẢNH
A7: 4 | B7: TC_E2E_027 | C7: Chọn từ mẫu có sẵn → Dùng template → Checkout (Guest) | D7: Template | E7: 1. Truy cập Home 2. Click [Chọn từ mẫu có sẵn] — 'Khám phá thư viện mẫu' 3. Chuyển sang MH Thư viện mẫu 4. Duyệt danh mục → Click chọn 1 template 5. Template apply lên canvas Design Studio 6. View [Cài đặt hình ảnh] → Chỉnh W/H, Căn giữa 7. [Đặt hàng] → [Mua ngay] 8. MH Checkout: Nhập thông tin → Thanh toán 9. Đặt hàng thành công → Xem đơn hàng | F7: Entry: Home → [Chọn từ mẫu có sẵn] Template: chọn mẫu bất kỳ Guest — COD | G7: Template apply đúng trên canvas, chỉnh sửa OK, đặt hàng thành công | H7: P0
A8: 5 | B8: TC_E2E_028 | C8: Chọn từ mẫu có sẵn → Sửa template → Checkout (Đăng nhập) | D8: Template | E8: 1. Đăng nhập trước 2. Home → Click [Chọn từ mẫu có sẵn] 3. Thư viện mẫu → Chọn template 4. Template lên canvas → Click [Sửa với AI] 5. Ảnh template đính kèm tự động → Nhập prompt sửa 6. [Tạo Artwork mới] → View 3 artwork 7. [Dùng ảnh này] → Cài đặt hình ảnh 8. [Đặt hàng] → Checkout (auto-fill) → Thành công | F8: Entry: Home → [Chọn từ mẫu có sẵn] Sửa: 'Đổi phong cách tối giản' User đã login | G8: Template + AI sửa thành công, auto-fill, đặt hàng OK | H8: P0
A9: 6 | B9: TC_E2E_029 | C9: Chọn từ mẫu có sẵn → Thêm giỏ hàng → Checkout | D9: Template | E9: 1. Home → [Chọn từ mẫu có sẵn] → Thư viện mẫu 2. Chọn template → Apply lên canvas 3. Cài đặt hình ảnh → Xóa nền, Căn giữa 4. [Đặt hàng] → [Thêm giỏ hàng] 5. Badge giỏ +1, toast thành công 6. Mở Giỏ hàng → [Thanh toán ngay] 7. Checkout → Thành công | F9: Entry: Home → [Chọn từ mẫu có sẵn] Xóa nền ON Thêm giỏ hàng | G9: Template vào giỏ, checkout từ giỏ thành công | H9: P1
A10: 7 | B10: TC_E2E_030 | C10: Tải lên ảnh của bạn → Upload file → Checkout (Guest) | D10: Upload | E10: 1. Truy cập Home 2. Click [Tải lên ảnh của bạn] — 'Sử dụng file thiết kế riêng' 3. Hộp thoại Upload → Chọn file PNG/JPG từ máy 4. Ảnh upload thành công → Apply lên canvas Design Studio 5. View [Cài đặt hình ảnh]: Xóa nền, Chỉnh W/H, Căn giữa 6. [Đặt hàng] → [Mua ngay] 7. MH Checkout: Nhập thông tin → Thanh toán 8. Đặt hàng thành công → Xem đơn hàng | F10: Entry: Home → [Tải lên ảnh của bạn] File: logo_company.png (1200x1200) Guest — COD | G10: Ảnh upload hiển thị đúng trên canvas, chỉnh sửa OK, đặt hàng thành công | H10: P0
A11: 8 | B11: TC_E2E_031 | C11: Tải lên ảnh → Sửa với AI → Checkout (Đăng nhập) | D11: Upload | E11: 1. Đăng nhập trước 2. Home → [Tải lên ảnh của bạn] → Upload file PNG 3. Ảnh lên canvas → Click [Sửa với AI] 4. Ảnh gốc đính kèm tự động → Nhập: 'Thêm viền neon glow' 5. [Tạo Artwork mới] → View 3 artwork 6. [Dùng ảnh này] → Cài đặt → Căn giữa 7. [Đặt hàng] → Checkout (auto-fill) → Thành công | F11: Entry: Home → [Tải lên ảnh của bạn] File: my_design.jpg Sửa: 'Thêm viền neon glow' User đã login | G11: Upload + AI enhance thành công, auto-fill, đặt hàng OK | H11: P0
A12: 9 | B12: TC_E2E_032 | C12: Tải lên ảnh → Thêm giỏ hàng → Upload ảnh khác → Thêm giỏ → Checkout | D12: Upload | E12: 1. Home → [Tải lên ảnh của bạn] → Upload file 1 2. Ảnh 1 lên canvas → Cài đặt → [Thêm giỏ hàng] 3. Quay lại Home → [Tải lên ảnh của bạn] → Upload file 2 4. Ảnh 2 lên canvas → Cài đặt → [Thêm giỏ hàng] 5. Giỏ hàng: 2 SP upload khác nhau 6. [Thanh toán ngay] → Checkout → Thành công | F12: File 1: team_logo.png File 2: event_poster.jpg Multi-item upload checkout | G12: 2 SP upload khác nhau trong giỏ, tổng tiền đúng, checkout OK | H12: P1 | I12: Untested | M12: Multi-upload test
A13: 🔄 LUỒNG SỬA ARTWORK — LOOP DESIGN
A14: 10 | B14: TC_E2E_004 | C14: Sửa tiếp 1 lần → Dùng ảnh → Checkout | D14: Sửa tiếp | E14: 1. Home → Nhập ý tưởng → [Tạo ngay] 2. Design Studio → View 3 artwork 3. Nhập [Bạn muốn sửa gì?]: 'Đổi tông màu ấm hơn' 4. Click [Sửa tiếp] → AI tạo lại 3 artwork mới 5. Duyệt ảnh bằng [>] [<] → Chọn ảnh ưng ý 6. Click [Dùng ảnh này] 7. Cài đặt hình ảnh → Căn giữa 8. [Đặt hàng] → [Mua ngay] → Checkout → Thành công | F14: Ý tưởng gốc: 'Hoa sen Việt Nam' Sửa: 'Đổi tông màu ấm hơn' | G14: Artwork mới phản ánh chỉnh sửa, đặt hàng thành công | H14: P0
A15: 11 | B15: TC_E2E_005 | C15: Sửa tiếp nhiều lần (3 lần loop) → Dùng ảnh | D15: Sửa tiếp | E15: 1. Home → Nhập ý tưởng → [Tạo ngay] 2. View 3 artwork → [Sửa tiếp] lần 1: 'Thêm hiệu ứng glow' 3. View 3 artwork mới → [Sửa tiếp] lần 2: 'Làm đậm nét hơn' 4. View 3 artwork mới → [Sửa tiếp] lần 3: 'Giảm màu nền' 5. View 3 artwork cuối → [Dùng ảnh này] 6. Cài đặt hình ảnh → Đặt hàng → Checkout → Thành công | F15: 3 lần sửa liên tiếp với prompt khác nhau | G15: Mỗi lần sửa tạo artwork mới đúng prompt, cuối cùng đặt hàng OK | H15: P1 | M15: Loop stress test
A16: 12 | B16: TC_E2E_006 | C16: Sửa với AI → Tạo artwork mới từ ảnh gốc → Checkout | D16: Sửa với AI | E16: 1. Home → Nhập ý tưởng → [Tạo ngay] 2. View 3 artwork → [Dùng ảnh này] 3. Cài đặt hình ảnh → Xem preview trên áo 4. Click [Sửa với AI] 5. MH Tạo artwork mới: Ảnh gốc đã đính kèm tự động 6. Nhập: 'Sửa màu sáng lên, thêm tia nắng' 7. Click [Tạo Artwork mới] → View 3 artwork mới 8. [Dùng ảnh này] → Cài đặt → Đặt hàng → Checkout → Thành công | F16: Ảnh gốc + Sửa: 'Sửa màu sáng lên, thêm tia nắng' | G16: AI tạo artwork dựa trên gốc + prompt sửa, đặt hàng thành công | H16: P0
A17: 13 | B17: TC_E2E_007 | C17: Chọn mẫu này → Chỉnh canvas → Đặt hàng | D17: Chọn mẫu | E17: 1. Home → Nhập ý tưởng → [Tạo ngay] 2. View 3 artwork → [Dùng ảnh này] 3. View artwork trên áo canvas 4. Click [Chọn mẫu này] → MH Cài đặt hình ảnh 5. Bật Xóa nền, chỉnh W/H, Thứ tự lớp, Căn giữa 6. Kéo/drag artwork trên canvas trực tiếp 7. [Đặt hàng] → [Mua ngay] → Checkout → Thành công | F17: Chỉnh: Xóa nền ON, W=250, H=300, Căn giữa | G17: Artwork hiển thị đúng tùy chỉnh trên áo, đặt hàng OK | H17: P0
A18: 14 | B18: TC_E2E_008 | C18: Sửa tiếp → Sửa với AI → Chọn mẫu → Checkout (Full loop) | D18: Kết hợp | E18: 1. Home → [Tạo ngay] → View 3 artwork 2. [Sửa tiếp] → View 3 artwork mới → [Dùng ảnh này] 3. Canvas → [Sửa với AI] → Nhập prompt → [Tạo Artwork mới] 4. View 3 artwork mới → [Dùng ảnh này] 5. Canvas → [Chọn mẫu này] → Cài đặt hình ảnh 6. Chỉnh sửa → [Đặt hàng] → Checkout → Thành công | F18: Kết hợp cả 3 nút: Sửa tiếp + Sửa với AI + Chọn mẫu | G18: Mọi bước chuyển đổi mượt, artwork cuối cùng đúng, đặt hàng OK | H18: P1 | M18: Full combination test
A19: 💳 LUỒNG CHECKOUT — ĐĂNG NHẬP
A20: 15 | B20: TC_E2E_009 | C20: Guest → Đăng nhập Facebook tại Checkout → Thanh toán | D20: Checkout Login | E20: 1. Home → Tạo artwork → Dùng ảnh → Cài đặt → [Đặt hàng] → [Mua ngay] 2. MH Checkout (chưa đăng nhập) 3. Click [Đăng nhập qua Facebook] 4. Popup Facebook OAuth → Đăng nhập thành công 5. Thông tin tự động auto-fill 6. Chọn thanh toán → [Thanh toán] → Thành công | F20: Tài khoản Facebook hợp lệ | G20: Login Facebook OK, auto-fill thông tin, đặt hàng thành công | H20: P0
A21: 16 | B21: TC_E2E_010 | C21: Guest → Đăng nhập Google tại Checkout → Thanh toán | D21: Checkout Login | E21: 1. Home → Tạo artwork → Dùng ảnh → Cài đặt → [Đặt hàng] → [Mua ngay] 2. MH Checkout → Click [Đăng nhập qua Google] 3. Popup Google OAuth → Đăng nhập OK 4. Auto-fill → Thanh toán → Thành công | F21: Tài khoản Google hợp lệ | G21: Login Google OK, auto-fill đúng, đặt hàng thành công | H21: P0
A22: 17 | B22: TC_E2E_011 | C22: Guest → Đăng nhập Email tại Checkout → Thanh toán | D22: Checkout Login | E22: 1. Home → Tạo artwork → Dùng ảnh → Cài đặt → [Đặt hàng] → [Mua ngay] 2. MH Checkout → Click [Đăng nhập qua Email] 3. Nhập Email + Password → Đăng nhập 4. Auto-fill → Thanh toán → Thành công | F22: Email: test@example.com, Pass: **** | G22: Login Email OK, auto-fill đúng, đặt hàng thành công | H22: P1
A23: 18 | B23: TC_E2E_012 | C23: Thêm giỏ hàng nhiều sản phẩm → Checkout cùng lúc | D23: Multi-item | E23: 1. Home → Tạo artwork 1 → Dùng ảnh → [Thêm giỏ hàng] 2. Home → Tạo artwork 2 (ý tưởng khác) → Dùng ảnh → [Thêm giỏ hàng] 3. Mở Giỏ hàng → Kiểm tra 2 sản phẩm 4. [Thanh toán ngay] → Checkout → Kiểm tra tổng tiền 2 SP 5. Thanh toán → Thành công | F23: SP1: 'Rồng watercolor' Size M SP2: 'Mèo galaxy' Size L | G23: Giỏ hàng đúng 2 SP, tổng tiền chính xác, đặt hàng OK | H23: P0
A24: ⚙️ LUỒNG CHỈNH SỬA HÌNH ẢNH NÂNG CAO
A25: 19 | B25: TC_E2E_013 | C25: Xóa nền → Resize → Căn giữa → Đặt hàng | D25: Chỉnh sửa | E25: 1. Home → Tạo artwork → [Dùng ảnh này] 2. Cài đặt hình ảnh: Bật [Xóa nền] 3. Chỉnh Width = 200, Height = 300 4. Chọn Vị trí: [Căn giữa] 5. Preview trên áo → OK 6. [Đặt hàng] → [Mua ngay] → Checkout → Thành công | F25: Xóa nền: ON W: 200, H: 300 Vị trí: Căn giữa | G25: Artwork không nền, đúng kích thước, căn giữa, đặt hàng OK | H25: P0
A26: 20 | B26: TC_E2E_014 | C26: Drag trên canvas → Thay đổi layer → Đặt hàng | D26: Chỉnh sửa | E26: 1. Home → Tạo artwork → [Dùng ảnh này] 2. Kéo (drag) artwork đến vị trí mong muốn trên canvas 3. Resize bằng handle góc 4. Thứ tự lớp: [Đưa lên trên] 5. Kiểm tra preview → [Đặt hàng] → Checkout → Thành công | F26: Drag: Vị trí ngực trái Layer: Đưa lên trên | G26: Artwork ở đúng vị trí drag, layer đúng, đặt hàng OK | H26: P1
A27: 21 | B27: TC_E2E_015 | C27: Chỉnh sửa → Undo/Tắt xóa nền → Đặt hàng | D27: Chỉnh sửa | E27: 1. Home → Tạo artwork → [Dùng ảnh này] 2. Bật [Xóa nền] → kiểm tra ảnh không nền 3. TẮT [Xóa nền] → kiểm tra nền hiện lại 4. Chỉnh kích thước cuối cùng → Căn giữa 5. [Đặt hàng] → Checkout → Thành công | F27: Xóa nền: ON → OFF → verify | G27: Toggle xóa nền hoạt động đúng 2 chiều, đặt hàng OK | H27: P1
A28: 📱 LUỒNG MOBILE / RESPONSIVE
A29: 22 | B29: TC_E2E_016 | C29: Full flow trên Mobile 375px (iPhone SE) | D29: Mobile | E29: 1. Mobile 375px: Home → Nhập ý tưởng → [Tạo ngay] 2. Design Studio mobile → View 3 artwork (swipe) 3. [Dùng ảnh này] → Cài đặt hình ảnh mobile 4. Chỉnh sửa trên canvas touch → Pinch zoom/drag 5. [Đặt hàng] → [Mua ngay] → Checkout mobile 6. Nhập form → Thanh toán → Thành công | F29: Viewport: 375x667 Touch: Swipe, Pinch, Drag | G29: Mọi bước responsive đúng, touch hoạt động, đặt hàng OK | H29: P0
A30: 23 | B30: TC_E2E_017 | C30: Full flow trên Tablet 768px (iPad) | D30: Tablet | E30: 1. Tablet 768px: Home → Nhập ý tưởng → [Tạo ngay] 2. Design Studio → View artwork → [Dùng ảnh] 3. Cài đặt hình ảnh (sidebar/panel layout) 4. [Đặt hàng] → Checkout → Thành công | F30: Viewport: 768x1024 | G30: Layout tablet hiển thị đúng, không bị vỡ UI, đặt hàng OK | H30: P1
A31: ⚠️ LUỒNG NEGATIVE / GIÁN ĐOẠN
A32: 24 | B32: TC_E2E_018 | C32: Refresh trang giữa Bước Cài đặt hình ảnh | D32: Negative | E32: 1. Home → Tạo artwork → [Dùng ảnh này] 2. Cài đặt hình ảnh: chỉnh W/H, xóa nền 3. *** REFRESH TRANG (F5) *** 4. Kiểm tra: artwork và cài đặt có được giữ lại không? 5. Nếu giữ lại → tiếp tục Đặt hàng → Checkout → Thành công 6. Nếu mất → phải tạo lại từ đầu | F32: F5 refresh tại bước Cài đặt hình ảnh | G32: Artwork và settings được giữ lại (hoặc recover được), UX rõ ràng | H32: P1
A33: 25 | B33: TC_E2E_019 | C33: Back browser từ Checkout → quay lại Design Studio | D33: Negative | E33: 1. Home → Tạo → Dùng ảnh → Cài đặt → [Đặt hàng] → [Mua ngay] 2. Đang ở MH Checkout 3. *** CLICK BACK BROWSER *** 4. Kiểm tra: quay lại Design Studio, artwork còn trên canvas? 5. Tiếp tục [Đặt hàng] lại → Checkout → Thành công | F33: Browser Back tại Checkout | G33: Quay lại DS bình thường, artwork không mất, đặt lại được | H33: P1
A34: 26 | B34: TC_E2E_020 | C34: Mất mạng khi AI đang tạo artwork | D34: Negative | E34: 1. Home → Nhập ý tưởng → [Tạo ngay] 2. *** MẤT KẾT NỐI MẠNG khi AI đang xử lý *** 3. Kiểm tra: hiển thị lỗi mạng + nút [Thử lại] 4. Bật lại mạng → Click [Thử lại] 5. AI tạo artwork OK → tiếp tục flow → Checkout → Thành công | F34: Tắt WiFi tại bước AI generate | G34: Lỗi mạng xử lý gracefully, retry hoạt động, không mất data | H34: P1
A35: 27 | B35: TC_E2E_021 | C35: Checkout → Submit form với field trống | D35: Negative | E35: 1. Home → Tạo → Dùng ảnh → Cài đặt → [Đặt hàng] → [Mua ngay] 2. MH Checkout: BỎ TRỐNG một số field bắt buộc 3. Click [Thanh toán] 4. Kiểm tra: hiển thị lỗi validation rõ ràng 5. Sửa lại field → Submit lại → Thành công | F35: Để trống: SĐT, Địa chỉ | G35: Validation lỗi đúng field, sửa lại và submit OK | H35: P0
A36: 28 | B36: TC_E2E_022 | C36: Không chọn ảnh/không nhập ý tưởng → luồng bị chặn | D36: Negative | E36: 1. Home → KHÔNG nhập ý tưởng → Click [Tạo ngay] 2. Kiểm tra: hiển thị lỗi validation 3. Nhập ý tưởng → [Tạo ngay] → View 3 artwork 4. KHÔNG chọn ảnh nào → thử [Dùng ảnh này] 5. Kiểm tra xử lý khi chưa select ảnh 6. Chọn ảnh → tiếp tục flow → Checkout → Thành công | F36: (trống ý tưởng) + (không chọn ảnh) | G36: Validation chặn đúng chỗ, hướng dẫn user rõ, flow recover được | H36: P0
A37: 🔥 LUỒNG ĐẶC BIỆT
A38: 29 | B38: TC_E2E_023 | C38: Tạo 2 đơn hàng liên tiếp cùng session | D38: Đặc biệt | E38: 1. Home → Tạo artwork 1 → Dùng ảnh → [Đặt hàng] → [Mua ngay] → Checkout → Thành công (Đơn 1) 2. Quay lại Home → Tạo artwork 2 (ý tưởng khác) 3. Dùng ảnh → [Đặt hàng] → [Mua ngay] → Checkout → Thành công (Đơn 2) 4. Kiểm tra: 2 đơn hàng riêng biệt, mã khác nhau | F38: Đơn 1: 'Rồng VN' COD Đơn 2: 'Hoa sen' Chuyển khoản | G38: 2 đơn hàng tạo thành công, mã khác nhau, không conflict | H38: P1
A39: 30 | B39: TC_E2E_024 | C39: Thêm giỏ → Sửa artwork → Thêm giỏ lại → Checkout | D39: Đặc biệt | E39: 1. Home → Tạo artwork → Dùng ảnh → [Thêm giỏ hàng] (SP bản gốc) 2. Quay lại canvas → [Sửa với AI] → Nhập prompt → Tạo mới 3. Dùng ảnh mới → [Thêm giỏ hàng] (SP bản sửa) 4. Giỏ hàng: kiểm tra 2 SP khác nhau (gốc vs sửa) 5. Checkout toàn bộ giỏ → Thành công | F39: SP1: artwork gốc SP2: artwork đã sửa AI | G39: Giỏ có 2 SP khác nhau, thumbnail đúng, checkout OK | H39: P1
A40: 31 | B40: TC_E2E_025 | C40: Full flow với phong cách khác: 3D / Anime / Trừu tượng | D40: Đặc biệt | E40: 1. Home → Ý tưởng: 'Samurai Nhật Bản' 2. Chọn phong cách: 3D (hoặc Anime, Trừu tượng) 3. [Tạo ngay] → View 3 artwork phong cách 3D 4. Dùng ảnh → Cài đặt → Đặt hàng → Checkout → Thành công 5. Kiểm tra artwork thật sự giống phong cách đã chọn | F40: Phong cách: 3D Ý tưởng: 'Samurai Nhật Bản' | G40: Artwork đúng phong cách 3D, không bị lẫn style, đặt hàng OK | H40: P1 | M40: Lặp lại với Anime, Trừu tượng
A41: 32 | B41: TC_E2E_026 | C41: Input chứa ký tự đặc biệt / emoji → Full flow | D41: Đặc biệt | E41: 1. Home → Ý tưởng: '🐉 Rồng & Phượng <b>HTML</b> @#$%' 2. [Tạo ngay] → AI xử lý được prompt đặc biệt 3. View artwork → Dùng ảnh → Cài đặt → Đặt hàng 4. Checkout → Thông tin bình thường → Thành công | F41: Ý tưởng chứa: emoji, HTML, special chars | G41: Không XSS, AI xử lý được, full flow thành công | H41: P1 | M41: Security + Functional
A43: 📊 THỐNG KÊ E2E FLOW
A44: Tổng luồng E2E | B44: 32
A45: Số nhóm | B45: 8
A46: P0 (Critical) | B46: 17
A47: P1 (High) | B47: 15

Sheet DỮ LIỆU TEST ARTWORK
A1: STT | B1: Danh mục | C1: Loại Artwork | D1: Phong cách / Biến thể | E1: Mô tả | F1: Xuất xứ / Văn hóa | G1: Độ phức tạp màu | H1: Mức độ chi tiết | I1: Trong suốt (Alpha) | J1: Định dạng file | K1: Kỹ thuật in | L1: Chất lượng in dự kiến | M1: Thách thức AI Try-on | N1: Trọng tâm kiểm thử | O1: Prompt mẫu (AI Gen) | P1: Độ ưu tiên | Q1: [Result]- Tạo Artwork | R1: Đánh giá kết quả Tạo Artwork | S1: Link data kết quả Tạo Artwork | T1: [Result] Try-on Model AI (Nam) | U1: Đánh giá Model AI (Nam) | V1: Link data kết quả Tryon (Nam) | W1: [Result] Try-on Model AI (Nữ) | X1: Đánh giá Model AI (Nữ) | Y1: Link data kết quả Tryon (Nữ) | Z1: Link Ảnh Sample
A2: 🎨 NGHỆ THUẬT TRUYỀN THỐNG
A3: 1 | B3: NGHỆ THUẬT TRUYỀN THỐNG | C3: Tranh sơn dầu | D3: Trường phái Ấn tượng | E3: Nét cọ mềm mại, tập trung ánh sáng, màu hòa quyện | F3: Châu Âu (Pháp) | G3: Cao | H3: Phức tạp | I3: Không | J3: JPG/PNG | K3: DTG, Thăng hoa | L3: Tốt | M3: Trung bình | N3: Độ chính xác tái tạo màu, kết cấu nét cọ trên vải | O3: Tranh sơn dầu ấn tượng hoa hướng dương lúc hoàng hôn | P3: P1 | Z3: 📂 TC_001
A4: 2 | B4: NGHỆ THUẬT TRUYỀN THỐNG | C4: Tranh sơn dầu | D4: Siêu thực | E4: Tranh giống ảnh thật với chi tiết cực cao | F4: Toàn cầu | G4: Rất cao | H4: Cực cao | I4: Không | J4: JPG/PNG | K4: DTG | L4: Xuất sắc | M4: Thấp | N4: Xử lý độ phân giải cực cao, độ sắc nét cạnh trên vải | O4: Tranh sơn dầu siêu thực giọt nước trên kính | P4: P1 | Z4: 📂 TC_002
A5: 3 | B5: NGHỆ THUẬT TRUYỀN THỐNG | C5: Tranh màu nước | D5: Ướt trên ướt | E5: Lớp rửa trong suốt, cạnh mềm, loang tự nhiên | F5: Toàn cầu | G5: Trung bình | H5: Vừa phải | I5: Có | J5: PNG | K5: DTG, Thăng hoa | L5: Tốt | M5: Trung bình | N5: Bảo toàn độ trong suốt, gradient mềm trên vải | O5: Tranh màu nước hoa anh đào kỹ thuật ướt | P5: P1 | Z5: 📂 TC_003
A6: 4 | B6: NGHỆ THUẬT TRUYỀN THỐNG | C6: Tranh màu nước | D6: Minh họa thực vật | E6: Vẽ cây chính xác với kỹ thuật màu nước | F6: Châu Âu (Anh) | G6: Trung bình | H6: Phức tạp | I6: Có | J6: PNG | K6: DTG | L6: Xuất sắc | M6: Thấp | N6: Bảo toàn đường nét mảnh + hòa trộn màu nước trong suốt | O6: Minh họa thực vật màu nước loài phong lan | P6: P2 | Z6: 📂 TC_004
A7: 5 | B7: NGHỆ THUẬT TRUYỀN THỐNG | C7: Tranh acrylic | D7: Biểu hiện Trừu tượng | E7: Màu đậm, kết cấu dày, bố cục năng động | F7: Mỹ | G7: Rất cao | H7: Phức tạp | I7: Không | J7: JPG/PNG | K7: DTG, Thăng hoa | L7: Tốt | M7: Thấp | N7: Tái tạo độ rực rỡ màu, kết cấu vẽ | O7: Tranh acrylic trừu tượng với vệt sơn đậm | P7: P1 | Z7: 📂 TC_005
A8: 6 | B8: NGHỆ THUẬT TRUYỀN THỐNG | C8: Tranh than chì | D8: Chân dung | E8: Đơn sắc, tương phản cao, chuyển sắc tinh tế | F8: Toàn cầu | G8: Thấp | H8: Phức tạp | I8: Không | J8: JPG/PNG | K8: DTG, In lụa | L8: Xuất sắc | M8: Thấp | N8: Độ chính xác thang xám, bảo toàn chi tiết mảnh | O8: Tranh than chì chân dung người già | P8: P2 | Z8: 📂 TC_006
A9: 7 | B9: NGHỆ THUẬT TRUYỀN THỐNG | C9: Tranh mực | D9: Nét vẽ (Line Art) | E9: Đường nét sạch, ít bóng đổ, phong cách bút mực | F9: Toàn cầu | G9: Thấp | H9: Đơn giản | I9: Có | J9: SVG/PNG | K9: In lụa, DTG | L9: Xuất sắc | M9: Không | N9: Độ sắc nét đường, khả năng co giãn, xử lý trong suốt | O9: Tranh mực nét vẽ phong cảnh núi | P9: P0 | Z9: 📂 TC_007
A10: 8 | B10: NGHỆ THUẬT TRUYỀN THỐNG | C10: Phác thảo bút chì | D10: Phác thảo thực tế | E10: Chì trên giấy, bóng đổ mềm, dải tông rộng | F10: Toàn cầu | G10: Thấp | H10: Vừa phải | I10: Không | J10: JPG/PNG | K10: DTG | L10: Tốt | M10: Thấp | N10: Chuyển sắc tông tinh tế, kết cấu giấy | O10: Phác thảo chi tiết bút chì con mèo | P10: P2 | Z10: 📂 TC_008
A11: 9 | B11: NGHỆ THUẬT TRUYỀN THỐNG | C11: Tranh phấn màu | D11: Phấn mềm | E11: Kết cấu mịn, màu rực mềm, hòa trộn | F11: Châu Âu | G11: Cao | H11: Vừa phải | I11: Không | J11: JPG/PNG | K11: DTG, Thăng hoa | L11: Tốt | M11: Trung bình | N11: Tái tạo gradient mềm, độ chính xác màu phấn | O11: Phong cảnh phấn mềm cánh đồng oải hương | P11: P2 | Z11: 📂 TC_009
A12: 10 | B12: NGHỆ THUẬT TRUYỀN THỐNG | C12: Tranh khắc | D12: Khắc gỗ / Lino | E12: Hình dạng đồ họa đậm, tương phản cao, kết cấu chạm khắc | F12: Nhật/Châu Âu | G12: Thấp | H12: Vừa phải | I12: Không | J12: SVG/PNG | K12: In lụa | L12: Xuất sắc | M12: Không | N12: Vùng màu đặc sạch, cạnh sắc nét | O12: Tranh khắc gỗ con sói trong rừng | P12: P1 | Z12: 📂 TC_010
A13: 11 | B13: NGHỆ THUẬT TRUYỀN THỐNG | C13: Tranh khắc | D13: In đá (Lithography) | E13: Chuyển sắc tông, in màu nhiều lớp | F13: Châu Âu | G13: Trung bình | H13: Phức tạp | I13: Không | J13: JPG/PNG | K13: DTG | L13: Tốt | M13: Thấp | N13: Tái tạo đa tông, độ chính xác chồng lớp | O13: Tranh in đá thực vật cổ điển | P13: P2 | Z13: 📂 TC_011
A14: 12 | B14: NGHỆ THUẬT TRUYỀN THỐNG | C14: Nghệ thuật khảm | D14: Byzantine / Gạch men | E14: Mẫu pixel hóa từ mảnh nhỏ, hình học | F14: Trung Đông/Địa Trung Hải | G14: Cao | H14: Phức tạp | I14: Không | J14: JPG/PNG | K14: DTG, Thăng hoa | L14: Tốt | M14: Thấp | N14: Độ rõ mẫu, phân đoạn màu trên vải | O14: Khảm Byzantine thiên thần vàng | P14: P3 | Z14: 📂 TC_012
A15: 💻 NGHỆ THUẬT SỐ
A16: 13 | B16: NGHỆ THUẬT SỐ | C16: Đồ họa vector | D16: Thiết kế phẳng (Flat) | E16: Hình hình học sạch, màu phẳng đặc, không gradient | F16: Toàn cầu | G16: Trung bình | H16: Đơn giản | I16: Có | J16: SVG/AI/PNG | K16: In lụa, DTG, HTV | L16: Xuất sắc | M16: Không | N16: Test co giãn, độ chính xác màu phẳng, trong suốt | O16: Minh họa vector phẳng cảnh thành phố | P16: P0 | Z16: 📂 TC_013
A17: 14 | B17: NGHỆ THUẬT SỐ | C17: Đồ họa vector | D17: Isometric | E17: Góc nhìn 3D giả với phối cảnh đẳng cự | F17: Toàn cầu | G17: Trung bình | H17: Vừa phải | I17: Có | J17: SVG/PNG | K17: DTG | L17: Xuất sắc | M17: Thấp | N17: Độ chính xác phối cảnh, đường thẳng trên đường cong cơ thể | O17: Minh họa isometric quán cà phê | P17: P2 | Z17: 📂 TC_014
A18: 15 | B18: NGHỆ THUẬT SỐ | C18: Vẽ kỹ thuật số | D18: Bán thực tế | E18: Nét cọ số hòa trộn, độ thực vừa phải | F18: Toàn cầu | G18: Cao | H18: Phức tạp | I18: Không | J18: PNG/PSD | K18: DTG, Thăng hoa | L18: Tốt | M18: Trung bình | N18: Kết cấu cọ trên vải, độ sâu màu | O18: Tranh số bán thực tế nhân vật chiến binh | P18: P1 | Z18: 📂 TC_015
A19: 16 | B19: NGHỆ THUẬT SỐ | C19: Vẽ kỹ thuật số | D19: Concept Art | E19: Thiết kế nhân vật/môi trường cho game/phim | F19: Toàn cầu | G19: Cao | H19: Phức tạp | I19: Có | J19: PNG/PSD | K19: DTG | L19: Tốt | M19: Trung bình | N19: Cắt bố cục phức tạp, trong suốt nền | O19: Concept art tàu vũ trụ sci-fi trong tinh vân | P19: P1 | Z19: 📂 TC_016
A20: 17 | B20: NGHỆ THUẬT SỐ | C20: Pixel Art | D20: Retro 8-bit | E20: Pixel thô, bảng màu giới hạn, game cổ điển | F20: Nhật/Mỹ | G20: Thấp | H20: Đơn giản | I20: Có | J20: PNG/GIF | K20: In lụa, DTG | L20: Xuất sắc | M20: Không | N20: Pixel sắc nét (không anti-alias), chất lượng phóng to | O20: Pixel art 8-bit nhân vật game retro | P20: P1 | Z20: 📂 TC_017
A21: 18 | B21: NGHỆ THUẬT SỐ | C21: Pixel Art | D21: Pixel độ phân giải cao | E21: Pixel art hiện đại canvas lớn, nhiều màu hơn | F21: Toàn cầu | G21: Trung bình | H21: Vừa phải | I21: Có | J21: PNG | K21: DTG | L21: Xuất sắc | M21: Thấp | N21: Duy trì lưới pixel ở kích thước in | O21: Pixel art phong cảnh hi-res với lớp parallax | P21: P2 | Z21: 📂 TC_018
A22: 19 | B22: NGHỆ THUẬT SỐ | C22: Render 3D | D22: Render ảnh thực | E22: Cảnh 3D ray-traced với ánh sáng, bóng đổ | F22: Toàn cầu | G22: Rất cao | H22: Cực cao | I22: Không | J22: JPG/PNG | K22: DTG, Thăng hoa | L22: Xuất sắc | M22: Thấp | N22: Render bóng, phản quang trên vải | O22: Render 3D thực tế robot chrome | P22: P1 | Z22: 📂 TC_019
A23: 20 | B23: NGHỆ THUẬT SỐ | C23: Render 3D | D23: Low Poly | E23: 3D đơn giản hóa với mặt đa giác nhìn thấy | F23: Toàn cầu | G23: Trung bình | H23: Vừa phải | I23: Có | J23: PNG | K23: DTG, In lụa | L23: Xuất sắc | M23: Không | N23: Sắc nét cạnh đa giác, gradient trong các mặt | O23: Chân dung đầu thú low poly 3D | P23: P1 | Z23: 📂 TC_020
A24: 21 | B24: NGHỆ THUẬT SỐ | C24: Collage kỹ thuật số | D24: Chỉnh sửa ảnh ghép | E24: Ghép nhiều ảnh với hiệu ứng số | F24: Toàn cầu | G24: Rất cao | H24: Cực cao | I24: Có | J24: PNG/PSD | K24: DTG | L24: Tốt | M24: Trung bình | N24: Hòa trộn lớp trên vải, phát hiện artifact cạnh | O24: Collage siêu thực đảo bay lơ lửng | P24: P2 | Z24: 📂 TC_021
A25: 22 | B25: NGHỆ THUẬT SỐ | C25: Khung Motion Graphics | D25: Poster động | E25: Khung đơn từ animation, bố cục năng động | F25: Toàn cầu | G25: Cao | H25: Phức tạp | I25: Có | J25: PNG | K25: DTG | L25: Tốt | M25: Trung bình | N25: Độ rõ phần tử động trong bản in tĩnh | O25: Poster động với hạt particle chảy | P25: P3 | Z25: 📂 TC_022
A26: 23 | B26: NGHỆ THUẬT SỐ | C26: Nghệ thuật sinh tạo | D26: Thuật toán / Fractal | E26: Mẫu tạo bằng toán học, chi tiết vô hạn | F26: Toàn cầu | G26: Rất cao | H26: Cực cao | I26: Không | J26: PNG/JPG | K26: Thăng hoa | L26: Tốt | M26: Thấp | N26: Độ phân giải chi tiết fractal ở kích thước in | O26: Fractal Mandelbrot gradient cầu vồng | P26: P2 | Z26: 📂 TC_023
A27: 🤖 PHONG CÁCH AI TẠO SINH
A28: 24 | B28: PHONG CÁCH AI TẠO SINH | C28: AI Thực tế | D28: Chân dung giống ảnh thật | E28: Chân dung người AI tạo, gần chất lượng ảnh thật | F28: AI (Midjourney/SD) | G28: Cao | H28: Cực cao | I28: Không | J28: PNG/JPG | K28: DTG | L28: Tốt | M28: Cao | N28: Phát hiện artifact AI khi in, khuôn mặt in vs model try-on | O28: Chân dung thực tế phụ nữ với hoa trong tóc, ánh sáng dramatic | P28: P0 | Z28: 📂 TC_024
A29: 25 | B29: PHONG CÁCH AI TẠO SINH | C29: AI Fantasy | D29: Cảnh Fantasy hoành tráng | E29: Phong cảnh fantasy kịch tính, nhân vật nghệ thuật | F29: AI (Midjourney/SD) | G29: Rất cao | H29: Cực cao | I29: Không | J29: PNG | K29: DTG, Thăng hoa | L29: Tốt | M29: Thấp | N29: Độ rực rỡ màu, bảo toàn chi tiết ở scale áo | O29: Rồng fantasy bay trên núi sương mù | P29: P1 | Z29: 📂 TC_025
A30: 26 | B30: PHONG CÁCH AI TẠO SINH | C30: AI Anime | D30: Anime / Manga | E30: Phong cách hoạt hình Nhật với AI tạo | F30: AI (Midjourney --niji) | G30: Cao | H30: Phức tạp | I30: Có | J30: PNG | K30: DTG | L30: Xuất sắc | M30: Trung bình | N30: Chất lượng nét anime, cel-shading trên vải | O30: Samurai cyber phong cách anime với katana neon | P30: P0 | Z30: 📂 TC_026
A31: 27 | B31: PHONG CÁCH AI TẠO SINH | C31: AI Trừu tượng | D31: Nghệ thuật chất lỏng | E31: Mẫu trừu tượng chảy do AI tạo | F31: AI (Midjourney/SD) | G31: Rất cao | H31: Phức tạp | I31: Không | J31: PNG/JPG | K31: DTG, Thăng hoa | L31: Tốt | M31: Thấp | N31: Hòa trộn màu mượt, cạnh liền mạch cho allover | O31: Nghệ thuật chất lỏng trừu tượng vàng pha xanh ngọc | P31: P1 | Z31: 📂 TC_027
A32: 28 | B32: PHONG CÁCH AI TẠO SINH | C32: AI Chibi | D32: Kawaii / Chibi | E32: Nhân vật dễ thương, đầu to quá cỡ | F32: AI (Midjourney --niji) | G32: Trung bình | H32: Vừa phải | I32: Có | J32: PNG | K32: DTG, In lụa | L32: Xuất sắc | M32: Thấp | N32: Bảo toàn độ dễ thương, cắt alpha sạch | O32: Mèo chibi kawaii phi hành gia với nền ngôi sao | P32: P1 | Z32: 📂 TC_028
A33: 29 | B33: PHONG CÁCH AI TẠO SINH | C33: AI Typography | D33: Text 3D / Chữ nghệ thuật | E33: Artwork typography do AI tạo | F33: AI (Midjourney/SD) | G33: Trung bình | H33: Vừa phải | I33: Có | J33: PNG | K33: DTG, In lụa | L33: Tốt | M33: Không | N33: Độ đọc được của text, hiệu ứng 3D trên vải phẳng | O33: Text chrome 3D 'DREAM BIG' với ngọn lửa | P33: P1 | Z33: 📂 TC_029
A34: 30 | B34: PHONG CÁCH AI TẠO SINH | C34: AI Siêu thực | D34: Dreamcore / Chủ nghĩa siêu thực | E34: Bố cục giấc mơ siêu thực | F34: AI (Midjourney/SD) | G34: Cao | H34: Cực cao | I34: Không | J34: PNG/JPG | K34: DTG | L34: Tốt | M34: Trung bình | N34: Độ rõ phần tử siêu thực, nhận dạng đối tượng trên áo | O34: Cầu thang siêu thực dẫn lên mây với đồng hồ bay | P34: P2 | Z34: 📂 TC_030
A35: 31 | B35: PHONG CÁCH AI TẠO SINH | C35: AI Retro | D35: Retrowave / Synthwave | E35: Thẩm mỹ neon thập niên 80, retro-futuristic | F35: AI (Midjourney/SD) | G35: Cao | H35: Vừa phải | I35: Không | J35: PNG | K35: DTG, Thăng hoa | L35: Tốt | M35: Thấp | N35: Tái tạo hiệu ứng neon trên vải, banding gradient | O35: Hoàng hôn synthwave với cây cọ và DeLorean | P35: P1 | Z35: 📂 TC_031
A36: 32 | B36: PHONG CÁCH AI TẠO SINH | C36: AI Sticker | D36: Sticker kiểu dán | E36: Sticker có viền trắng, nhìn bóng loáng | F36: AI (Midjourney/SD) | G36: Trung bình | H36: Đơn giản | I36: Có | J36: PNG | K36: DTG, HTV | L36: Xuất sắc | M36: Không | N36: Sắc nét viền, ảo giác sticker trên vải | O36: Sticker dễ thương Corgi với viền trắng dày | P36: P0 | Z36: 📂 TC_032
A37: 33 | B37: PHONG CÁCH AI TẠO SINH | C37: AI Màu nước | D37: Mô phỏng màu nước AI | E37: Hiệu ứng màu nước do AI tạo | F37: AI (Midjourney/SD) | G37: Trung bình | H37: Phức tạp | I37: Có | J37: PNG | K37: DTG | L37: Tốt | M37: Trung bình | N37: Hiệu ứng loang màu nước, cạnh trong suốt | O37: Tranh màu nước AI quán café Paris trong mưa | P37: P2 | Z37: 📂 TC_033
A38: 34 | B38: PHONG CÁCH AI TẠO SINH | C38: AI Truyện tranh | D38: Comic / Tiểu thuyết đồ họa | E38: Phong cách comic AI với halftone, nét đậm | F38: AI (Midjourney/SD) | G38: Cao | H38: Phức tạp | I38: Không | J38: PNG | K38: DTG, In lụa | L38: Xuất sắc | M38: Thấp | N38: Mẫu halftone, render bong bóng hội thoại | O38: Siêu anh hùng comic trong tư thế hành động | P38: P2 | Z38: 📂 TC_034
A39: 🌍 NGHỆ THUẬT VĂN HÓA / VÙNG MIỀN
A40: 35 | B40: NGHỆ THUẬT VĂN HÓA / VÙNG MIỀN | C40: Ukiyo-e Nhật Bản | D40: Tranh khắc gỗ | E40: Phong cách Edo, màu phẳng, đường viền đậm, thiên nhiên/nhân vật | F40: Nhật Bản | G40: Trung bình | H40: Phức tạp | I40: Không | J40: JPG/PNG | K40: DTG, In lụa | L40: Xuất sắc | M40: Thấp | N40: Bảng màu truyền thống, kết cấu vân gỗ | O40: Sóng lớn phong cách Ukiyo-e với twist hiện đại | P40: P1 | Z40: 📂 TC_035
A41: 36 | B41: NGHỆ THUẬT VĂN HÓA / VÙNG MIỀN | C41: Thủy mặc Trung Quốc | D41: Sumi-e / Shui-mo | E41: Tranh cọ tối giản, gradient mực, zen | F41: Trung Quốc | G41: Thấp | H41: Vừa phải | I41: Có | J41: PNG | K41: DTG | L41: Tốt | M41: Trung bình | N41: Trong suốt mực, nét cọ tinh tế trên vải | O41: Tranh thủy mặc tre trong sương | P41: P1 | Z41: 📂 TC_036
A42: 37 | B42: NGHỆ THUẬT VĂN HÓA / VÙNG MIỀN | C42: Thư pháp Trung Quốc | D42: Chữ cổ điển | E42: Nét cọ nghệ thuật, ý nghĩa văn hóa | F42: Trung Quốc | G42: Thấp | H42: Đơn giản | I42: Có | J42: SVG/PNG | K42: In lụa, DTG | L42: Xuất sắc | M42: Không | N42: Độ rõ ký tự, chính xác nét | O42: Thư pháp câu đối với triện đỏ | P42: P2 | Z42: 📂 TC_037
A43: 38 | B43: NGHỆ THUẬT VĂN HÓA / VÙNG MIỀN | C43: Nghệ thuật Ấn Độ | D43: Madhubani / Mithila | E43: Nghệ thuật dân gian mẫu phức tạp, màu tươi, họa tiết thiên nhiên | F43: Ấn Độ (Bihar) | G43: Cao | H43: Phức tạp | I43: Không | J43: JPG/PNG | K43: DTG, Thăng hoa | L43: Tốt | M43: Thấp | N43: Mật độ mẫu, bão hòa màu, đối xứng | O43: Tranh Madhubani công với viền hoa | P43: P1 | Z43: 📂 TC_038
A44: 39 | B44: NGHỆ THUẬT VĂN HÓA / VÙNG MIỀN | C44: Nghệ thuật Ấn Độ | D44: Mandala | E44: Mẫu hình học tròn đối xứng, họa tiết tâm linh | F44: Ấn Độ/Tây Tạng | G44: Cao | H44: Cực cao | I44: Có | J44: SVG/PNG | K44: DTG, Thăng hoa | L44: Tốt | M44: Thấp | N44: Chính xác đối xứng tròn, nét mảnh ở rìa | O44: Mandala tinh xảo chi tiết vàng và ngọc lam | P44: P0 | Z44: 📂 TC_039
A45: 40 | B45: NGHỆ THUẬT VĂN HÓA / VÙNG MIỀN | C45: Nghệ thuật Ấn Độ | D45: Kalamkari | E45: Vẽ tay/in khuôn, chủ đề thần thoại, nhuộm tự nhiên | F45: Ấn Độ (AP/Telangana) | G45: Trung bình | H45: Phức tạp | I45: Không | J45: JPG/PNG | K45: DTG | L45: Tốt | M45: Thấp | N45: Dòng chảy mẫu hữu cơ, tái tạo tông đất | O45: Cây đời Kalamkari với chim và hoa | P45: P2 | Z45: 📂 TC_040
A46: 41 | B46: NGHỆ THUẬT VĂN HÓA / VÙNG MIỀN | C46: Nghệ thuật Châu Phi | D46: Bộ lạc / Mẫu hình học | E46: Hình hình học đậm, họa tiết biểu tượng, palette đất/tươi | F46: Châu Phi (nhiều vùng) | G46: Cao | H46: Vừa phải | I46: Không | J46: SVG/PNG | K46: In lụa, DTG, Thăng hoa | L46: Xuất sắc | M46: Không | N46: Căn chỉnh lặp mẫu, bảo toàn tương phản đậm | O46: Mẫu hình học bộ lạc Phi terracotta và đen | P46: P1 | Z46: 📂 TC_041
A47: 42 | B47: NGHỆ THUẬT VĂN HÓA / VÙNG MIỀN | C47: Nghệ thuật Châu Phi | D47: Kente / Ankara | E47: Mẫu dệt/in vải trên vải, ý nghĩa văn hóa | F47: Ghana / Tây Phi | G47: Rất cao | H47: Phức tạp | I47: Không | J47: JPG/PNG | K47: Thăng hoa | L47: Tốt | M47: Thấp | N47: Độ rực rỡ bảng màu truyền thống, căn sọc | O47: Mẫu vải Kente allover vàng và xanh lá | P47: P2 | Z47: 📂 TC_042
A48: 43 | B48: NGHỆ THUẬT VĂN HÓA / VÙNG MIỀN | C48: Nghệ thuật Châu Phi | D48: Vải bùn (Bògòlanfini) | E48: Nhuộm bùn lên men, mẫu hình học đất | F48: Mali | G48: Thấp | H48: Đơn giản | I48: Không | J48: JPG/PNG | K48: In lụa, DTG | L48: Xuất sắc | M48: Không | N48: Chính xác tông đất, kết cấu hữu cơ | O48: Mẫu vải bùn nâu và kem | P48: P2 | Z48: 📂 TC_043
A49: 44 | B49: NGHỆ THUẬT VĂN HÓA / VÙNG MIỀN | C49: Nghệ thuật Trung Đông | D49: Hình học Hồi giáo / Arabesque | E49: Tessellation hình học phức tạp, mẫu vô hạn | F49: Trung Đông / Thế giới Hồi giáo | G49: Trung bình | H49: Cực cao | I49: Không | J49: SVG/PNG | K49: Thăng hoa, DTG | L49: Xuất sắc | M49: Không | N49: Chính xác hình học, ghép liền mạch, chi tiết mảnh | O49: Mẫu ngôi sao hình học Hồi giáo xanh dương và vàng | P49: P1 | Z49: 📂 TC_044
A50: 45 | B50: NGHỆ THUẬT VĂN HÓA / VÙNG MIỀN | C50: Nghệ thuật Mỹ Latinh | D50: Nghệ thuật dân gian Mexico / Alebrije | E50: Màu rực rỡ, sinh vật kỳ ảo, họa tiết Ngày Người Chết | F50: Mexico | G50: Rất cao | H50: Phức tạp | I50: Có | J50: PNG | K50: DTG | L50: Tốt | M50: Thấp | N50: Độ rực rỡ cực độ, render sinh vật chi tiết | O50: Rồng alebrije đầy màu sắc với mẫu phức tạp | P50: P1 | Z50: 📂 TC_045
A51: 46 | B51: NGHỆ THUẬT VĂN HÓA / VÙNG MIỀN | C51: Nghệ thuật Thổ dân | D51: Chấm Dot Painting | E51: Mẫu từ chấm, tông đất, câu chuyện thời mơ | F51: Úc | G51: Trung bình | H51: Vừa phải | I51: Không | J51: JPG/PNG | K51: DTG | L51: Tốt | M51: Thấp | N51: Rõ ràng mẫu chấm, kích thước chấm đều ở scale in | O51: Tranh chấm thổ dân kanguru dreamtime | P51: P2 | Z51: 📂 TC_046
... A55: 50 | B55: NGHỆ THUẬT VĂN HÓA / VÙNG MIỀN | C55: Nghệ thuật Celtic | D55: Nút thắt / Đan xen | E55: Mẫu đan lồng, không đầu cuối, xoắn ốc | F55: Ireland / Scotland | G55: Thấp | H55: Phức tạp | I55: Có | J55: SVG/PNG | K55: In lụa, DTG | L55: Xuất sắc | M55: Không | N55: Tính liên tục nút, nhất quán đường nét, co giãn | O55: Vòng tròn nút Celtic với nút trinity ở giữa | P55: P2 | Z55: 📂 TC_050
A56: 👕 THIẾT KẾ POD / ÁO THUN
A57: 51 | B57: THIẾT KẾ POD / ÁO THUN | C57: Thiết kế Typography | D57: Slogan đậm | E57: Text lớn, động lực/hài hước, font ấn tượng | F57: Toàn cầu | G57: Thấp | H57: Đơn giản | I57: Có | J57: SVG/PNG | K57: In lụa, HTV, DTG | L57: Xuất sắc | M57: Không | N57: Render font, dễ đọc qua các kích cỡ | O57: Typography đậm 'JUST CREATE' font distressed | P57: P0 | Z57: 📂 TC_051
A58: 52 | B58: THIẾT KẾ POD / ÁO THUN | C58: Thiết kế Typography | D58: Script Retro | E58: Chữ viết tay vintage, trang trí cầu kỳ | F58: Mỹ | G58: Trung bình | H58: Vừa phải | I58: Có | J58: SVG/PNG | K58: In lụa, DTG | L58: Tốt | M58: Không | N58: Dòng chảy chữ, bảo toàn nét mảnh | O58: Chữ viết tay retro 'California Vibes' với hoàng hôn | P58: P1 | Z58: 📂 TC_052
A59: 53 | B59: THIẾT KẾ POD / ÁO THUN | C59: Áo đồ họa | D59: Huy hiệu Vintage / Emblem | E59: Badge tròn/khiên, kết cấu cũ, retro | F59: Mỹ | G59: Trung bình | H59: Vừa phải | I59: Có | J59: SVG/PNG | K59: In lụa, DTG | L59: Xuất sắc | M59: Không | N59: Đối xứng badge, rõ kết cấu distress | O59: Badge camping vintage với núi và đại bàng | P59: P0 | Z59: 📂 TC_053
A60: 54 | B60: THIẾT KẾ POD / ÁO THUN | C60: Áo đồ họa | D60: Streetwear / Đô thị | E60: Đồ họa đậm, ảnh hưởng graffiti, typography mạnh | F60: Toàn cầu (Đô thị) | G60: Cao | H60: Phức tạp | I60: Có | J60: PNG | K60: DTG, In lụa | L60: Tốt | M60: Thấp | N60: Chi tiết cạnh, kết cấu graffiti | O60: Thiết kế streetwear đầu lâu với splash graffiti neon | P60: P1 | Z60: 📂 TC_054
A61: 55 | B61: THIẾT KẾ POD / ÁO THUN | C61: Nghệ thuật động vật | D61: Chân dung động vật thực tế | E61: Hình ảnh động vật giống thật, tập trung hoang dã | F61: Toàn cầu | G61: Cao | H61: Cực cao | I61: Có | J61: PNG | K61: DTG | L61: Tốt | M61: Thấp | N61: Chi tiết lông/lông vũ, render mắt, trong suốt nền | O61: Chân dung sói thực tế đôi mắt xanh dữ dội | P61: P1 | Z61: 📂 TC_055
A62: 56 | B62: THIẾT KẾ POD / ÁO THUN | C62: Nghệ thuật động vật | D62: Động vật hình học / Đa giác | E62: Động vật xây từ hình hình học, phong cách hiện đại | F62: Toàn cầu | G62: Trung bình | H62: Vừa phải | I62: Có | J62: SVG/PNG | K62: DTG, In lụa | L62: Xuất sắc | M62: Không | N62: Chính xác hình dạng, gradient fill trong đa giác | O62: Đầu gấu low-poly hình học tone ngọc bích | P62: P1 | Z62: 📂 TC_056
A63: 57 | B63: THIẾT KẾ POD / ÁO THUN | C63: Thiên nhiên / Phong cảnh | D63: In phong cảnh | E63: Cảnh núi, biển, rừng cho in áo | F63: Toàn cầu | G63: Cao | H63: Phức tạp | I63: Không | J63: JPG/PNG | K63: DTG, Thăng hoa | L63: Tốt | M63: Thấp | N63: Chính xác màu tự nhiên, vị trí đường chân trời | O63: Phong cảnh núi giờ vàng với hồ phản chiếu | P63: P2 | Z63: 📂 TC_057
A64: 58 | B64: THIẾT KẾ POD / ÁO THUN | C64: Mẫu lặp / Allover | D64: Mẫu hoa | E64: Mẫu hoa/thực vật lặp, ghép liền mạch | F64: Toàn cầu | G64: Cao | H64: Phức tạp | I64: Không | J64: JPG/PNG | K64: Thăng hoa | L64: Xuất sắc | M64: Thấp | N64: Chính xác lặp liền mạch, nhất quán màu qua tile | O64: Mẫu hoa nhiệt đới liền mạch với hoa dâm bụt | P64: P1 | Z64: 📂 TC_058
A65: 59 | B65: THIẾT KẾ POD / ÁO THUN | C65: Mẫu lặp / Allover | D65: Mẫu hình học lặp | E65: Hình hình học lặp, tessellation | F65: Toàn cầu | G65: Trung bình | H65: Vừa phải | I65: Không | J65: SVG/PNG | K65: Thăng hoa | L65: Xuất sắc | M65: Không | N65: Căn chỉnh tile, tỷ lệ mẫu qua các size | O65: Mẫu hình học art deco liền mạch vàng và navy | P65: P1 | Z65: 📂 TC_059
A66: 60 | B66: THIẾT KẾ POD / ÁO THUN | C66: Mẫu lặp / Allover | D66: Rằn ri / Quân sự | E66: Mẫu ngụy trang nhiều bảng màu | F66: Toàn cầu | G66: Trung bình | H66: Vừa phải | I66: Không | J66: JPG/PNG | K66: Thăng hoa | L66: Xuất sắc | M66: Thấp | N66: Hòa trộn hình hữu cơ, chính xác bảng màu | O66: Mẫu rằn ri đô thị tông xám | P66: P2 | Z66: 📂 TC_060
A67: 61 | B67: THIẾT KẾ POD / ÁO THUN | C67: Tối giản | D67: Icon / Biểu tượng đơn | E67: Thiết kế rất đơn giản một phần tử, nét sạch | F67: Toàn cầu | G67: Thấp | H67: Đơn giản | I67: Có | J67: SVG/PNG | K67: In lụa, HTV | L67: Xuất sắc | M67: Không | N67: Rõ icon ở vị trí nhỏ, cạnh sắc nét | O67: Icon trái tim nét đơn tối giản giữa ngực | P67: P0 | Z67: 📂 TC_061
A68: 62 | B68: THIẾT KẾ POD / ÁO THUN | C68: Văn hóa đại chúng | D68: Parody / Mashup | E68: Tham chiếu văn hóa pop, mashup, hài hước | F68: Toàn cầu | G68: Cao | H68: Phức tạp | I68: Có | J68: PNG | K68: DTG | L68: Tốt | M68: Thấp | N68: Chi tiết nhân vật, chính xác màu cho parody | O68: Mashup văn hóa pop mèo vũ trụ với pizza | P68: P2 | Z68: 📂 TC_062
A69: 63 | B69: THIẾT KẾ POD / ÁO THUN | C69: Thể thao / Đội nhóm | D69: Số áo Jersey | E69: Đánh số thể thao, đồ họa kiểu đội | F69: Toàn cầu | G69: Thấp | H69: Đơn giản | I69: Có | J69: SVG/PNG | K69: In lụa, HTV | L69: Xuất sắc | M69: Không | N69: Căn số, nhất quán vị trí trước/sau | O69: Số áo thể thao 23 với tên đội | P69: P2 | Z69: 📂 TC_063
A70: ⚠️ CÁC TRƯỜNG HỢP THÁCH THỨC KỸ THUẬT
A71: 64 | B71: CÁC TRƯỜNG HỢP THÁCH THỨC KỸ THUẬT | C71: Edge Case | D71: Toàn cảnh siêu rộng | E71: Artwork tỷ lệ rất rộng (3:1 hoặc hơn) | F71: N/A | G71: Cao | H71: Phức tạp | I71: Không | J71: JPG/PNG | K71: DTG | L71: Thách thức | M71: Trung bình | N71: Cắt tỷ lệ, hành vi auto-fit | O71: Dãy núi toàn cảnh tỷ lệ 3:1 | P71: P0 | Z71: 📂 TC_064
A72: 65 | B72: CÁC TRƯỜNG HỢP THÁCH THỨC KỸ THUẬT | C72: Edge Case | D72: Dọc siêu cao | E72: Artwork tỷ lệ rất cao (1:3 hoặc hơn) | F72: N/A | G72: Trung bình | H72: Vừa phải | I72: Không | J72: JPG/PNG | K72: DTG | L72: Thách thức | M72: Thấp | N72: Auto-fit dọc, căn chỉnh vùng áo | O72: Tranh cuộn dọc Nhật Bản cao | P72: P1 | Z72: 📂 TC_065
A73: 66 | B73: CÁC TRƯỜNG HỢP THÁCH THỨC KỸ THUẬT | C73: Edge Case | D73: Chi tiết siêu nhỏ | E73: Đường cực mảnh và chi tiết rất nhỏ | F73: N/A | G73: Thấp | H73: Cực cao | I73: Có | J73: SVG/PNG | K73: DTG | L73: Thách thức | M73: Không | N73: Hiển thị đường ở kích thước in, độ rộng đường tối thiểu | O73: Mandala cực chi tiết với đường 0.5pt | P73: P0 | Z73: 📂 TC_066
A74: 67 | B74: CÁC TRƯỜNG HỢP THÁCH THỨC KỸ THUẬT | C74: Edge Case | D74: Màu neon / Ngoài gamut | E74: Màu ngoài gamut CMYK, neon điện | F74: N/A | G74: Rất cao | H74: Vừa phải | I74: Không | J74: PNG | K74: DTG | L74: Thách thức | M74: Thấp | N74: Cắt gamut màu, fallback render neon | O74: Nghệ thuật trừu tượng xanh neon và xanh điện | P74: P0 | Z74: 📂 TC_067
A75: 68 | B75: CÁC TRƯỜNG HỢP THÁCH THỨC KỸ THUẬT | C75: Edge Case | D75: Artwork đen trên áo tối | E75: Artwork chỉ đen đặt trên áo đen | F75: N/A | G75: Thấp | H75: Đơn giản | I75: Có | J75: PNG | K75: DTG (lớp trắng nền) | L75: Thách thức | M75: Không | N75: Kiểm tra hiển thị, kích hoạt lớp trắng nền | O75: Nghệ thuật tattoo đen trên áo đen | P75: P1 | Z75: 📂 TC_068
A76: 69 | B76: CÁC TRƯỜNG HỢP THÁCH THỨC KỸ THUẬT | C76: Edge Case | D76: Artwork toàn trắng | E76: Thiết kế chỉ trắng, cần ngữ cảnh áo màu | F76: N/A | G76: Thấp | H76: Đơn giản | I76: Có | J76: PNG | K76: DTG (mực trắng), HTV | L76: Thách thức | M76: Không | N76: Xử lý mực trắng, phân biệt trong suốt vs trắng | O76: Logo silhouette trắng trên nền trong suốt | P76: P0 | Z76: 📂 TC_069
A77: 70 | B77: CÁC TRƯỜNG HỢP THÁCH THỨC KỸ THUẬT | C77: Edge Case | D77: Độ phân giải rất thấp (72 DPI) | E77: Ảnh gốc độ phân giải web, không đủ cho in | F77: N/A | G77: Trung bình | H77: Đơn giản | I77: Không | J77: JPG | K77: DTG | L77: Thách thức | M77: Thấp | N77: Hệ thống cảnh báo DPI, kiểm tra chất lượng upscale | O77: Artwork JPG 500x500px độ phân giải thấp | P77: P0 | Z77: 📂 TC_070
A78: 71 | B78: CÁC TRƯỜNG HỢP THÁCH THỨC KỸ THUẬT | C78: Edge Case | D78: Siêu cao phân giải (600+ DPI) | E78: File cực lớn, sử dụng bộ nhớ cao | F78: N/A | G78: Cao | H78: Cực cao | I78: Không | J78: PNG/TIFF | K78: DTG | L78: Xuất sắc | M78: Thấp | N78: Hiệu năng upload, xử lý bộ nhớ, thời gian xử lý | O78: Artwork 8000x8000px ở 600 DPI | P78: P0 | Z78: 📂 TC_071
A79: 72 | B79: CÁC TRƯỜNG HỢP THÁCH THỨC KỸ THUẬT | C79: Edge Case | D79: GIF động → Tĩnh | E79: User upload GIF động, platform phải xử lý | F79: N/A | G79: Trung bình | H79: Đơn giản | I79: Có | J79: GIF | K79: DTG | L79: Thách thức | M79: Không | N79: Trích xuất frame đầu, xử lý từ chối animation | O79: GIF lấp lánh động upload làm artwork | P79: P1 | Z79: 📂 TC_072
A80: 73 | B80: CÁC TRƯỜNG HỢP THÁCH THỨC KỸ THUẬT | C80: Edge Case | D80: Upload PDF CMYK | E80: PDF sẵn sàng in trong không gian màu CMYK | F80: N/A | G80: Trung bình | H80: Vừa phải | I80: Không | J80: PDF | K80: DTG | L80: Tốt | M80: Không | N80: Chuyển đổi CMYK sang RGB, kiểm tra lệch màu | O80: PDF CMYK logo thương hiệu | P80: P1 | Z80: 📂 TC_073
A81: 74 | B81: CÁC TRƯỜNG HỢP THÁCH THỨC KỸ THUẬT | C81: Edge Case | D81: Text cực lớn | E81: Text lớn che toàn bộ mặt trước áo | F81: N/A | G81: Thấp | H81: Đơn giản | I81: Có | J81: SVG/PNG | K81: In lụa, DTG | L81: Tốt | M81: Không | N81: Giới hạn scale text, tràn ranh giới áo | O81: Một chữ 'A' phủ toàn bộ vùng in | P81: P1 | Z81: 📂 TC_074
A82: 75 | B82: CÁC TRƯỜNG HỢP THÁCH THỨC KỸ THUẬT | C82: Edge Case | D82: Nhiều vật thể nhỏ | E82: 100+ icon/vật thể nhỏ trong một artwork | F82: N/A | G82: Cao | H82: Cực cao | I82: Có | J82: PNG/SVG | K82: DTG | L82: Thách thức | M82: Thấp | N82: Rõ ràng vật nhỏ, hiệu năng render | O82: Mẫu 100 emoji icon nhỏ khác nhau | P82: P2 | Z82: 📂 TC_075
... A84: 77 | B84: CÁC TRƯỜNG HỢP THÁCH THỨC KỸ THUẬT | C84: Edge Case | D84: Cạnh gradient trong suốt | E84: Cạnh artwork mờ dần thành trong suốt | F84: N/A | G84: Trung bình | H84: Vừa phải | I84: Có | J84: PNG | K84: DTG | L84: Tốt | M84: Trung bình | N84: Render gradient trong suốt trên vải | O84: Hiệu ứng khói mờ từ đặc sang trong suốt | P84: P1 | Z84: 📂 TC_077
A86: 📊 THỐNG KÊ TỔNG HỢP
A87: Tổng loại Artwork | B87: 77
A88: Số danh mục | B88: 6
A89: P0 (Quan trọng) | B89: 16
A90: P1 (Cao) | B90: 33
A91: P2 (Trung bình) | B91: 25
A92: P3 (Thấp) | B92: 3
A93: AI Try-on thách thức cao | B93: 3
A94: Chất lượng in: Thách thức | B94: 9

Sheet GỢI Ý SIZE - TEST DATA
A1: STT | B1: Danh mục Test | C1: TC_ID | D1: Giới tính | E1: Chiều cao (cm) | F1: Cân nặng (kg) | G1: Size kỳ vọng | H1: Mô tả kịch bản | I1: Độ ưu tiên | J1: Expected_Result | K1: Actual_Result | L1: Ghi chú
A2: 📏 TRƯỜNG HỢP CHUẨN — NAM
A3: 1 | B3: TRƯỜNG HỢP CHUẨN — NAM | C3: TC_SZ_001 | D3: Nam | E3: 155 | F3: 45 | G3: XS | H3: Nam nhỏ nhất: thấp và nhẹ → XS | I3: P0 | L3: Boundary min cho Nam
A4: 2 | B4: TRƯỜNG HỢP CHUẨN — NAM | C4: TC_SZ_002 | D4: Nam | E4: 158 | F4: 50 | G4: S | H4: Nam nhỏ: chiều cao TB thấp, cân nặng nhẹ → S | I4: P0
A5: 3 | B5: TRƯỜNG HỢP CHUẨN — NAM | C5: TC_SZ_003 | D5: Nam | E5: 163 | F5: 58 | G5: S | H5: Nam nhỏ-vừa: chiều cao dưới TB, cân vừa → S | I5: P1
A6: 4 | B6: TRƯỜNG HỢP CHUẨN — NAM | C6: TC_SZ_004 | D6: Nam | E6: 165 | F6: 60 | G6: M | H6: Nam trung bình Việt Nam: 165cm/60kg → M | I6: P0 | L6: Case phổ biến nhất VN
A7: 5 | B7: TRƯỜNG HỢP CHUẨN — NAM | C7: TC_SZ_005 | D7: Nam | E7: 168 | F7: 63 | G7: M | H7: Nam TB: chiều cao TB, cân nặng TB → M | I7: P0
A8: 6 | B8: TRƯỜNG HỢP CHUẨN — NAM | C8: TC_SZ_006 | D8: Nam | E8: 170 | F8: 68 | G8: M | H8: Nam TB-cao: 170/68 → M hoặc L | I8: P1 | L8: Ranh giới M/L
A9: 7 | B9: TRƯỜNG HỢP CHUẨN — NAM | C9: TC_SZ_007 | D9: Nam | E9: 172 | F9: 72 | G9: L | H9: Nam cao-vừa: 172/72 → L | I9: P0
A10: 8 | B10: TRƯỜNG HỢP CHUẨN — NAM | C10: TC_SZ_008 | D10: Nam | E10: 175 | F10: 75 | G10: L | H10: Nam cao: 175/75 → L | I10: P0
A11: 9 | B11: TRƯỜNG HỢP CHUẨN — NAM | C11: TC_SZ_009 | D11: Nam | E11: 178 | F11: 80 | G11: XL | H11: Nam cao-to: 178/80 → XL | I11: P0
A12: 10 | B12: TRƯỜNG HỢP CHUẨN — NAM | C12: TC_SZ_010 | D12: Nam | E12: 180 | F12: 85 | G12: XL | H12: Nam rất cao: 180/85 → XL | I12: P1
A13: 11 | B13: TRƯỜNG HỢP CHUẨN — NAM | C13: TC_SZ_011 | D13: Nam | E13: 183 | F13: 90 | G13: XXL | H13: Nam to lớn: 183/90 → XXL | I13: P0
A14: 12 | B14: TRƯỜNG HỢP CHUẨN — NAM | C14: TC_SZ_012 | D14: Nam | E14: 188 | F14: 100 | G14: XXL | H14: Nam rất to: 188/100 → XXL | I14: P1 | L14: Boundary max bình thường
A15: 📏 TRƯỜNG HỢP CHUẨN — NỮ
A16: 13 | B16: TRƯỜNG HỢP CHUẨN — NỮ | C16: TC_SZ_013 | D16: Nữ | E16: 150 | F16: 40 | G16: XS | H16: Nữ nhỏ nhất: 150/40 → XS | I16: P0 | L16: Boundary min cho Nữ
A17: 14 | B17: TRƯỜNG HỢP CHUẨN — NỮ | C17: TC_SZ_014 | D17: Nữ | E17: 153 | F17: 45 | G17: XS | H17: Nữ nhỏ: 153/45 → XS | I17: P1
A18: 15 | B18: TRƯỜNG HỢP CHUẨN — NỮ | C18: TC_SZ_015 | D18: Nữ | E18: 155 | F18: 48 | G18: S | H18: Nữ nhỏ-vừa: 155/48 → S | I18: P0
A19: 16 | B19: TRƯỜNG HỢP CHUẨN — NỮ | C19: TC_SZ_016 | D19: Nữ | E19: 158 | F19: 50 | G19: S | H19: Nữ TB Việt Nam: 158/50 → S | I19: P0 | L19: Case phổ biến nhất VN Nữ
A20: 17 | B20: TRƯỜNG HỢP CHUẨN — NỮ | C20: TC_SZ_017 | D20: Nữ | E20: 160 | F20: 53 | G20: M | H20: Nữ TB: 160/53 → M | I20: P0
A21: 18 | B21: TRƯỜNG HỢP CHUẨN — NỮ | C21: TC_SZ_018 | D21: Nữ | E21: 163 | F21: 55 | G21: M | H21: Nữ TB-cao: 163/55 → M | I21: P1
A22: 19 | B22: TRƯỜNG HỢP CHUẨN — NỮ | C22: TC_SZ_019 | D22: Nữ | E22: 165 | F22: 60 | G22: L | H22: Nữ cao: 165/60 → L | I22: P0
A23: 20 | B23: TRƯỜNG HỢP CHUẨN — NỮ | C23: TC_SZ_020 | D23: Nữ | E23: 168 | F23: 65 | G23: L | H23: Nữ cao-vừa: 168/65 → L | I23: P1
A24: 21 | B24: TRƯỜNG HỢP CHUẨN — NỮ | C24: TC_SZ_021 | D24: Nữ | E24: 170 | F24: 70 | G24: XL | H24: Nữ cao-to: 170/70 → XL | I24: P0
A25: 22 | B25: TRƯỜNG HỢP CHUẨN — NỮ | C25: TC_SZ_022 | D25: Nữ | E25: 173 | F25: 75 | G25: XL | H25: Nữ rất cao: 173/75 → XL | I25: P1
A26: 23 | B26: TRƯỜNG HỢP CHUẨN — NỮ | C26: TC_SZ_023 | D26: Nữ | E26: 175 | F26: 80 | G26: XXL | H26: Nữ to lớn: 175/80 → XXL | I26: P0
A27: 24 | B27: TRƯỜNG HỢP CHUẨN — NỮ | C27: TC_SZ_024 | D27: Nữ | E27: 178 | F27: 85 | G27: XXL | H27: Nữ rất to: 178/85 → XXL | I27: P1
A28: ⚖️ RANH GIỚI SIZE (Boundary)
A29: 25 | B29: RANH GIỚI SIZE (Boundary) | C29: TC_SZ_025 | D29: Nam | E29: 158 | F29: 50 | G29: XS/S | H29: Ranh giới XS↔S Nam: đúng ngưỡng chuyển | I29: P0 | L29: Kiểm tra logic chuyển size
A30: 26 | B30: RANH GIỚI SIZE (Boundary) | C30: TC_SZ_026 | D30: Nam | E30: 163 | F30: 58 | G30: S/M | H30: Ranh giới S↔M Nam: chiều cao gần M, cân S | I30: P0
A31: 27 | B31: RANH GIỚI SIZE (Boundary) | C31: TC_SZ_027 | D31: Nam | E31: 170 | F31: 70 | G31: M/L | H31: Ranh giới M↔L Nam: đúng ngưỡng | I31: P0 | L31: Case nhạy cảm nhất
A32: 28 | B32: RANH GIỚI SIZE (Boundary) | C32: TC_SZ_028 | D32: Nam | E32: 176 | F32: 78 | G32: L/XL | H32: Ranh giới L↔XL Nam: đúng ngưỡng | I32: P0
A33: 29 | B33: RANH GIỚI SIZE (Boundary) | C33: TC_SZ_029 | D33: Nam | E33: 180 | F33: 88 | G33: XL/XXL | H33: Ranh giới XL↔XXL Nam: đúng ngưỡng | I33: P0
A34: 30 | B34: RANH GIỚI SIZE (Boundary) | C34: TC_SZ_030 | D34: Nữ | E34: 155 | F34: 48 | G34: XS/S | H34: Ranh giới XS↔S Nữ: đúng ngưỡng | I34: P0
A35: 31 | B35: RANH GIỚI SIZE (Boundary) | C35: TC_SZ_031 | D35: Nữ | E35: 160 | F35: 53 | G35: S/M | H35: Ranh giới S↔M Nữ: đúng ngưỡng | I35: P0
A36: 32 | B36: RANH GIỚI SIZE (Boundary) | C36: TC_SZ_032 | D36: Nữ | E36: 165 | F36: 60 | G36: M/L | H36: Ranh giới M↔L Nữ: đúng ngưỡng | I36: P0
A37: 33 | B37: RANH GIỚI SIZE (Boundary) | C37: TC_SZ_033 | D37: Nữ | E37: 170 | F37: 68 | G37: L/XL | H37: Ranh giới L↔XL Nữ: đúng ngưỡng | I37: P0
A38: 34 | B38: RANH GIỚI SIZE (Boundary) | C38: TC_SZ_034 | D38: Nữ | E38: 175 | F38: 78 | G38: XL/XXL | H38: Ranh giới XL↔XXL Nữ: đúng ngưỡng | I38: P0
A39: 🏋️ CHIỀU CAO THẤP + CÂN NẶNG CAO (Overweight)
A40: 35 | B40: CHIỀU CAO THẤP + CÂN NẶNG CAO (Overweight) | C40: TC_SZ_035 | D40: Nam | E40: 160 | F40: 80 | G40: L/XL | H40: Nam thấp nhưng nặng: 160/80 | I40: P0 | L40: Ưu tiên cân nặng hay chiều cao?
A41: 36 | B41: CHIỀU CAO THẤP + CÂN NẶNG CAO (Overweight) | C41: TC_SZ_036 | D41: Nam | E41: 165 | F41: 90 | G41: XL/XXL | H41: Nam TB nhưng rất nặng: 165/90 | I41: P1 | L41: Stress test logic
A42: 37 | B42: CHIỀU CAO THẤP + CÂN NẶNG CAO (Overweight) | C42: TC_SZ_037 | D42: Nam | E42: 155 | F42: 75 | G42: L | H42: Nam rất thấp mà nặng: 155/75 | I42: P1
A43: 38 | B43: CHIỀU CAO THẤP + CÂN NẶNG CAO (Overweight) | C43: TC_SZ_038 | D43: Nữ | E43: 150 | F43: 65 | G43: L | H43: Nữ rất thấp mà nặng: 150/65 | I43: P0
A44: 39 | B44: CHIỀU CAO THẤP + CÂN NẶNG CAO (Overweight) | C44: TC_SZ_039 | D44: Nữ | E44: 155 | F44: 70 | G44: L/XL | H44: Nữ thấp nhưng nặng: 155/70 | I44: P1
A45: 40 | B45: CHIỀU CAO THẤP + CÂN NẶNG CAO (Overweight) | C45: TC_SZ_040 | D45: Nữ | E45: 160 | F45: 80 | G45: XL/XXL | H45: Nữ TB nhưng rất nặng: 160/80 | I45: P1
A46: 🦒 CHIỀU CAO LỚN + CÂN NẶNG THẤP (Underweight)
A47: 41 | B47: CHIỀU CAO LỚN + CÂN NẶNG THẤP (Underweight) | C47: TC_SZ_041 | D47: Nam | E47: 180 | F47: 55 | G47: S/M | H47: Nam rất cao nhưng rất gầy: 180/55 | I47: P0 | L47: Ưu tiên chiều cao hay cân nặng?
A48: 42 | B48: CHIỀU CAO LỚN + CÂN NẶNG THẤP (Underweight) | C48: TC_SZ_042 | D48: Nam | E48: 185 | F48: 60 | G48: M/L | H48: Nam cực cao mà nhẹ: 185/60 | I48: P1
A49: 43 | B49: CHIỀU CAO LỚN + CÂN NẶNG THẤP (Underweight) | C49: TC_SZ_043 | D49: Nam | E49: 175 | F49: 55 | G49: S/M | H49: Nam cao mà gầy: 175/55 | I49: P1
A50: 44 | B50: CHIỀU CAO LỚN + CÂN NẶNG THẤP (Underweight) | C50: TC_SZ_044 | D50: Nữ | E50: 170 | F50: 45 | G50: S | H50: Nữ cao nhưng rất gầy: 170/45 | I50: P0
A51: 45 | B51: CHIỀU CAO LỚN + CÂN NẶNG THẤP (Underweight) | C51: TC_SZ_045 | D51: Nữ | E51: 175 | F51: 50 | G51: S/M | H51: Nữ rất cao mà nhẹ: 175/50 | I51: P1
A52: 46 | B52: CHIỀU CAO LỚN + CÂN NẶNG THẤP (Underweight) | C52: TC_SZ_046 | D52: Nữ | E52: 168 | F52: 48 | G52: S | H52: Nữ cao mà gầy: 168/48 | I52: P1
A53: 🚫 GIÁ TRỊ INVALID / EDGE CASE
A54: 47 | B54: GIÁ TRỊ INVALID / EDGE CASE | C54: TC_SZ_047 | D54: Nam | E54: 0 | F54: 0 | G54: Lỗi | H54: Chiều cao và cân nặng = 0 | I54: P0 | L54: Phải hiển thị lỗi validation
A55: 48 | B55: GIÁ TRỊ INVALID / EDGE CASE | C55: TC_SZ_048 | D55: Nam | E55: -170 | F55: 70 | G55: Lỗi | H55: Chiều cao âm | I55: P0 | L55: Phải reject giá trị âm
A56: 49 | B56: GIÁ TRỊ INVALID / EDGE CASE | C56: TC_SZ_049 | D56: Nam | E56: 170 | F56: -60 | G56: Lỗi | H56: Cân nặng âm | I56: P0 | L56: Phải reject giá trị âm
A57: 50 | B57: GIÁ TRỊ INVALID / EDGE CASE | C57: TC_SZ_050 | D57: Nam | E57: 100 | F57: 50 | G57: Lỗi | H57: Chiều cao quá thấp (ngoài range): 100cm | I57: P1 | L57: Ngoài giới hạn hợp lệ
A58: 51 | B58: GIÁ TRỊ INVALID / EDGE CASE | C58: TC_SZ_051 | D58: Nam | E58: 250 | F58: 80 | G58: Lỗi | H58: Chiều cao quá cao: 250cm | I58: P1 | L58: Ngoài giới hạn hợp lệ
A59: 52 | B59: GIÁ TRỊ INVALID / EDGE CASE | C59: TC_SZ_052 | D59: Nam | E59: 170 | F59: 200 | G59: Lỗi | H59: Cân nặng quá lớn: 200kg | I59: P1 | L59: Ngoài giới hạn hợp lệ
A60: 53 | B60: GIÁ TRỊ INVALID / EDGE CASE | C60: TC_SZ_053 | D60: Nam | E60: 170 | F60: 10 | G60: Lỗi | H60: Cân nặng quá nhỏ: 10kg | I60: P1 | L60: Ngoài giới hạn hợp lệ
A61: 54 | B61: GIÁ TRỊ INVALID / EDGE CASE | C61: TC_SZ_054 | E61: 170 | F61: 70 | G61: Lỗi | H61: Không chọn giới tính | I61: P0 | L61: Giới tính bắt buộc
A62: 55 | B62: GIÁ TRỊ INVALID / EDGE CASE | C62: TC_SZ_055 | D62: Nam | G62: Lỗi | H62: Không nhập chiều cao và cân nặng | I62: P0 | L62: Validate required fields
A63: 56 | B63: GIÁ TRỊ INVALID / EDGE CASE | C63: TC_SZ_056 | D63: Nam | E63: abc | F63: 70 | G63: Lỗi | H63: Nhập chữ vào ô chiều cao | I63: P1 | L63: Validate kiểu dữ liệu
A64: 57 | B64: GIÁ TRỊ INVALID / EDGE CASE | C64: TC_SZ_057 | D64: Nam | E64: 170 | F64: xyz | G64: Lỗi | H64: Nhập chữ vào ô cân nặng | I64: P1 | L64: Validate kiểu dữ liệu
A65: 58 | B65: GIÁ TRỊ INVALID / EDGE CASE | C65: TC_SZ_058 | D65: Nam | E65: 170.5 | F65: 65.3 | G65: M | H65: Nhập số thập phân: 170.5cm / 65.3kg | I65: P1 | L65: Hệ thống có chấp nhận decimal?
A66: 🔄 CHUYỂN ĐỔI GIỚI TÍNH (Cùng chiều cao/cân nặng)
A67: 59 | B67: CHUYỂN ĐỔI GIỚI TÍNH (Cùng chiều cao/cân nặng) | C67: TC_SZ_059 | D67: Nam | E67: 165 | F67: 60 | G67: M | H67: Nam 165/60 → kiểm tra size | I67: P0 | L67: So sánh kết quả Nam vs Nữ cùng input
A68: 60 | B68: CHUYỂN ĐỔI GIỚI TÍNH (Cùng chiều cao/cân nặng) | C68: TC_SZ_060 | D68: Nữ | E68: 165 | F68: 60 | G68: L | H68: Nữ 165/60 → size phải KHÁC Nam (lớn hơn 1 bậc) | I68: P0 | L68: Nữ cần form rộng hơn ở lower body
A69: 61 | B69: CHUYỂN ĐỔI GIỚI TÍNH (Cùng chiều cao/cân nặng) | C69: TC_SZ_061 | D69: Nam | E69: 170 | F69: 65 | G69: M | H69: Nam 170/65 → kiểm tra | I69: P1
A70: 62 | B70: CHUYỂN ĐỔI GIỚI TÍNH (Cùng chiều cao/cân nặng) | C70: TC_SZ_062 | D70: Nữ | E70: 170 | F70: 65 | G70: L | H70: Nữ 170/65 → so sánh với Nam | I70: P1
A71: 63 | B71: CHUYỂN ĐỔI GIỚI TÍNH (Cùng chiều cao/cân nặng) | C71: TC_SZ_063 | D71: Nam | E71: 175 | F71: 75 | G71: L | H71: Nam 175/75 → kiểm tra | I71: P1
A72: 64 | B72: CHUYỂN ĐỔI GIỚI TÍNH (Cùng chiều cao/cân nặng) | C72: TC_SZ_064 | D72: Nữ | E72: 175 | F72: 75 | G72: XL | H72: Nữ 175/75 → so sánh với Nam | I72: P1
A73: 📐 KIỂM TRA HIỂN THỊ UI GỢI Ý SIZE
A74: 65 | B74: KIỂM TRA HIỂN THỊ UI GỢI Ý SIZE | C74: TC_SZ_065 | D74: Nam | E74: 170 | F74: 70 | G74: M | H74: Popup gợi ý size: hiển thị đúng M + highlight trên bảng size | I74: P0 | L74: Kiểm tra UI popup/overlay
A75: 66 | B75: KIỂM TRA HIỂN THỊ UI GỢI Ý SIZE | C75: TC_SZ_066 | D75: Nữ | E75: 160 | F75: 53 | G75: M | H75: Popup gợi ý size Nữ: hiển thị kết quả + guide ảnh | I75: P0
A76: 67 | B76: KIỂM TRA HIỂN THỊ UI GỢI Ý SIZE | C76: TC_SZ_067 | D76: Nam | E76: 170 | F76: 70 | G76: M | H76: Sau khi chọn size gợi ý → auto-select trong dropdown sản phẩm | I76: P1 | L76: Kiểm tra logic auto-fill
A77: 68 | B77: KIỂM TRA HIỂN THỊ UI GỢI Ý SIZE | C77: TC_SZ_068 | D77: Nam | E77: 170 | F77: 70 | G77: M | H77: Thay đổi giới tính sau khi đã gợi ý → recalculate | I77: P0 | L77: Size phải cập nhật lại
A78: 69 | B78: KIỂM TRA HIỂN THỊ UI GỢI Ý SIZE | C78: TC_SZ_069 | D78: Nam | E78: 170 | F78: 70 | G78: M | H78: Thay đổi chiều cao/cân nặng → recalculate real-time | I78: P1 | L78: Nếu có tính năng live update
A79: 70 | B79: KIỂM TRA HIỂN THỊ UI GỢI Ý SIZE | C79: TC_SZ_070 | D79: Nam | E79: 170 | F79: 70 | G79: M | H79: Responsive: popup gợi ý size trên mobile 375px | I79: P1 | L79: Kiểm tra responsive
A81: 📊 THỐNG KÊ
A82: Tổng test cases | B82: 70
A83: Số danh mục | B83: 8
A84: P0 (Quan trọng) | B84: 39
A85: P1 (Cao) | B85: 31
A86: Test cases Nam | B86: 42
A87: Test cases Nữ | B87: 27
